Workbook
Name _C1: Hoja3!$A$2:$A$7
Name _C10: Hoja3!$J$2:$J$9
Name _C11: Hoja3!$K$2:$K$7
Name _C12: Hoja3!$L$2:$L$3
Name _C13: Hoja3!$M$2:$M$5
Name _C14: Hoja3!$N$2:$N$4
Name _C15: Hoja3!$O$2:$O$6
Name _C16: Hoja3!$P$2:$P$11
Name _C17: Hoja3!$Q$2:$Q$11
Name _C18: Hoja3!$R$2:$R$4
Name _C19: Hoja3!$S$2:$S$15
Name _C2: Hoja3!$B$2:$B$5
Name _C20: Hoja3!$T$2:$T$7
Name _C21: Hoja3!$U$2:$U$6
Name _C22: Hoja3!$V$2:$V$5
Name _C23: Hoja3!$W$2:$W$9
Name _C24: Hoja3!$X$2:$X$6
Name _C25: Hoja3!$Y$2:$Y$5
Name _C26: Hoja3!$Z$2:$Z$3
Name _C27: Hoja3!$AA$2:$AA$10
Name _C28: Hoja3!$AB$2:$AB$9
Name _C29: Hoja3!$AC$2:$AC$12
Name _C3: Hoja3!$C$2:$C$10
Name _C30: Hoja3!$AD$2:$AD$9
Name _C31: Hoja3!$AE$2:$AE$10
Name _C32: Hoja3!$AF$2:$AF$4
Name _C33: Hoja3!$AG$2:$AG$8
Name _C34: Hoja3!$AH$2:$AH$3
Name _C35: Hoja3!$AI$2:$AI$5
Name _C36: Hoja3!$AJ$2:$AJ$9
Name _C37: Hoja3!$AK$2:$AK$5
Name _C38: Hoja3!$AL$2:$AL$6
Name _C39: Hoja3!$AM$2:$AM$9
Name _C4: Hoja3!$D$2:$D$5
Name _C40: Hoja3!$AN$2:$AN$6
Name _C5: Hoja3!$E$2:$E$8
Name _C6: Hoja3!$F$2:$F$4
Name _C7: Hoja3!$G$2:$G$6
Name _C8: Hoja3!$H$2:$H$4
Name _C9: Hoja3!$I$2:$I$7
Name Accion_Evangelizadora: Hoja2!$O$40
Name Actualizar_oferta_de_programas: Hoja2!$J$40:$J$43
Name Articular_Modelo_De_Autoevaluacion: Hoja2!$G$40:$G$41
Name Asp_C1: Listas!$O$4:$O$4
Name Asp_C10: Listas!$X$4:$X$10
Name Asp_C11: Listas!$Y$4:$Y$6
Name Asp_C12: Listas!$Z$4:$Z$5
Name Asp_C13: Listas!$AA$4:$AA$6
Name Asp_C14: Listas!$AB$4:$AB$4
Name Asp_C15: Listas!$AC$4:$AC$5
Name Asp_C16: Listas!$AD$4:$AD$5
Name Asp_C17: Listas!$AE$4:$AE$5
Name Asp_C18: Listas!$AF$4:$AF$5
Name Asp_C19: Listas!$AG$4:$AG$5
Name Asp_C2: Listas!$P$4:$P$6
Name Asp_C20: Listas!$AH$4:$AH$5
Name Asp_C21: Listas!$AI$4:$AI$6
Name Asp_C22: Listas!$AJ$4:$AJ$6
Name Asp_C23: Listas!$AK$4:$AK$5
Name Asp_C24: Listas!$AL$4:$AL$4

Sheet Listas
A1: LISTAS PARA DESPLEGABLES (NO BORRAR ESTA HOJA)
A3: FACTORES | C3: F1 | D3: F2 | E3: F3 | F3: F4 | G3: F5 | H3: F6 | I3: F7 | J3: F8 | K3: F9 | L3: F10 | M3: F11 | N3: F12 | O3: C1 | P3: C2 | Q3: C3 | R3: C4 | S3: C5 | T3: C6 | U3: C7 | V3: C8 | W3: C9 | X3: C10 | Y3: C11 | Z3: C12 | AA3: C13 | AB3: C14 | AC3: C15 | AD3: C16 | AE3: C17 | AF3: C18 | AG3: C19 | AH3: C20 | AI3: C21 | AJ3: C22 | AK3: C23 | AL3: C24 | AM3: C25 | AN3: C26 | AO3: C27 | AP3: C28 | AQ3: C29 | AR3: C30 | AS3: C31 | AT3: C32 | AU3: C33 | AV3: C34 | AW3: C35 | AX3: C36 | AY3: C37 | AZ3: C38 | BA3: C39 | BB3: C40 | BC3: C41 | BD3: C42 | BE3: C43 | BF3: C44 | BG3: C45 | BH3: C46 | BI3: C47 | BJ3: C48 | BL3: Tipo de acción | BM3: PROCESO RESPONSABLE | BO3: OBJETIVOS | BP3: OE1_Diseñar e implementar estrategias integrales e innovadoras para arraigar la identidad de UNICESMAG | BQ3: OE2_Articular las labores institucionales desde una óptica transformadora de la persona para impactar la sociedad desde el reconocimiento de las culturas y las comunidades | BR3: OE3_Desarrollar una arquitectura institucional bajo los principios de ética y buen gobierno
A4: F1. Proyecto Educativo del Programa e Identidad Institucional | C4: C1. Proyecto Educativo del Programa | D4: C3. Participación en actividades de formación integral | E4: C8. Selección, vinculación y permanencia | F4: C16. Seguimiento de los egresados | G4: C18. Integralidad de los aspectos curriculares | H4: C27. Políticas, estrategias y estructura para la permanencia y la graduación | I4: C31. Inserción del programa en contextos académicos nacionales e internacionales | J4: C34. Formación para la investigación, desarrollo tecnológico, la innovación y la creación | K4: C36. Programas y servicios | L4: C38. Estrategias y recursos de apoyo a profesores | M4: C41. Organización y administración | N4: C47. Recursos de infraestructura física y tecnológica. | O4: A1. Demostrar coherencia del Proyecto Educativo del Programa (PEP) o el que haga sus veces, con los lineamientos y políticas Institucionales, así como en la definición de objetivos de formación y resultados de aprendizaje y la manera cómo el PEP ha ido mejorando, como resultado de los procesos de aseguramiento de la calidad, la consolidación de la identidad Institucional y la relación que mantiene con la comunidad y sus grupos de interés. | P4: A2. Análisis sobre las tendencias, necesidades y líneas de desarrollo de la disciplina o profesión, en el contexto regional, nacional e internacional. | Q4: A5. Apreciación de los estudiantes en relación con su participación en las actividades de investigación, desarrollo tecnológico, creación artística, culturales, deportivas y de extensión, que contribuyen a su formación integral, junto con las acciones emprendidas como resultado de dichas apreciaciones. | R4: A9. Evidencia de los efectos en la formación de los estudiantes, a partir de los procesos de orientación y seguimiento de los estudiantes, teniendo como referencia sus características de ingreso. | S4: A10. Evidencia de los resultados de las estrategias de seguimiento y evaluación de los resultados de aprendizaje en el desarrollo de capacidades para el trabajo autónomo del estudiante. | T4: A11. Apreciación de estudiantes y profesores del programa sobre la pertinencia, vigencia y aplicación del reglamento estudiantil y las políticas académicas y, sobre las estrategias de divulgación de dicha reglamentación, junto con las acciones emprendidas como resultado de dichas apreciaciones. | U4: A13. Evidencia de los beneficios generados por el otorgamiento de estímulos académicos y apoyos socioeconómicos a los estudiantes. | V4: A15. Evidencia de la aplicación de los procesos de selección, vinculación y permanencia de los profesores, en coherencia con el nivel de formación, modalidad del programa académico y lugar de desarrollo. | W4: A17. Evidencias que demuestren los resultados de la aplicación del estatuto profesoral, o el que haga sus veces, sobre la trayectoria profesoral, la inclusión, el reconocimiento de méritos y el ascenso en el escalafón, de acuerdo con el nivel de formación y la modalidad del programa. | X4: A20. Evidencia de la coherencia entre el número, dedicación, nivel de formación y experiencia de los profesores de tiempo completo, con el número de estudiantes, nivel de formación y modalidad del programa académico. | Y4: A27. Análisis de los resultados de la aplicación de políticas y estrategias Institucionales en materia de desarrollo integral del profesorado, que incluya la capacitación y la actualización en los aspectos académicos, profesionales y pedagógicos relacionados con la naturaleza, nivel de formación y modalidad del programa. | Z4: A30. Evidencia de los efectos generados en el desempeño de las labores de docencia, investigación y extensión con el otorgamiento de estímulos a los profesores. | AA4: A32. Evidencia de la efectividad de los criterios de evaluación del material producido por los profesores en la calidad de los aprendizajes de los estudiantes, de acuerdo con el nivel de formación y modalidad del programa académico. | AB4: A35. La remuneración que reciben los profesores está de acuerdo con sus méritos académicos y profesionales, el aporte en el desarrollo de los componentes formativos, pedagógicos y de evaluación, la interacción y relevancia social, el nivel de formación y la modalidad del programa académico. | AC4: A36. Apreciación de los profesores, directivos y estudiantes sobre los criterios y mecanismos para la evaluación de los profesores; su transparencia, equidad y eficacia y; su coherencia con la naturaleza de la institución, el nivel de formación y la modalidad del programa, junto con las acciones emprendidas como resultado de dichas apreciaciones. | AD4: A38. Resultado de los estudios sistémicos aplicados sobre el desarrollo profesional y laboral de los egresados, el alcance de las competencias adquiridas, la correspondencia entre el desempeño de los egresados y el perfil de egreso o resultados de aprendizaje del programa. | AE4: A40. Evidencia del impacto de los egresados en el medio social y académico, científico y cultural, como un mecanismo para establecer los aportes del programa a la solución de problemas de la sociedad y/o la creación e innovación de conocimiento. | AF4: A42. Resultados de la aplicación de ejercicios continuos de evaluación de la integralidad del currículo que conduzcan a la realización de ajustes y mejoras que impactan a la formación en valores, actitudes, aptitudes, conocimientos, métodos, capacidades y habilidades, de acuerdo con el estado del arte y con el ejercicio de la disciplina, profesión, ocupación u oficio, y que busca la formación integral del estudiante en coherencia con la misión Institucional y los objetivos propios del programa académico. | AG4: A44. Evidencia de procesos de flexibilización como, doble titulación; articulación pregrado-posgrado; reconocimiento de créditos, homologación y oferta de cursos electivos en distintas modalidades y lugares de desarrollo entre otros, que permiten al estudiante interactuar con otros programas a nivel I, nacional e internacional. | AH4: A46. Evidencia de la implementación de las estrategias que promueven y estimulan la interdisciplinariedad curricular del programa, y el resultado de su aplicación en las diferentes rutas formativas seguidas por los estudiantes. | AI4: A48. Apreciación de profesores y estudiantes sobre la coherencia de las estrategias pedagógicas utilizadas que facilitan el logro de los resultados de aprendizaje esperados, incluyendo los escenarios de práctica para los programas que lo requieren, valorando la calidad, la pertinencia, el acompañamiento y el cumplimiento de la normatividad específica para su desarrollo, junto con las acciones emprendidas como resultado de dichas apreciaciones. | AJ4: A51. Apreciación de profesores y estudiantes sobre los sistemas de evaluación de los resultados de aprendizaje que desarrolla o implementa el programa, junto con las acciones emprendidas como resultado de dichas apreciaciones. | AK4: A54. Evidencia de la aplicación de una política Institucional que establezca parámetros para la formulación, evaluación y mejora continua de los resultados de aprendizaje establecidos en el programa, en alineación con el perfil de formación y acorde con el nivel y la modalidad de formación. | AL4: A56. Evidencia del resultado de la aplicación de estrategias para el desarrollo de las competencias previstas acordes con el perfil de formación del programa. | AM4: A57. Evidencia del cumplimiento de planes de mejoramiento y de innovación producto del proceso de autoevaluación del programa. | AN4: A59. Evidencia de la participación de los profesores y estudiantes en la proyección social del programa. | AO4: A61. Análisis del efecto de las políticas, estrategias y acciones orientadas al mejoramiento de la permanencia y la graduación en el programa, que incluyan el comportamiento en los últimos seis años o en la vigencia de la acreditación si se trata de una renovación, de la tasa de deserción interanual, tasa de deserción por cohorte y la tasa de graduación acumulada del programa. | AP4: A62. Evidencia de la existencia e implementación de un sistema de alertas tempranas que permita reconocer las particularidades de los estudiantes según su contexto sociocultural y la puesta en marcha de acciones que faciliten su proceso formativo, de acuerdo, al menos, con las normas nacionales vigentes en materia de inclusión y diversidad. | AQ4: A65. Evidencia de la evaluación y el mejoramiento de los aspectos curriculares derivados de los análisis del desempeño académico de los estudiantes, la permanencia y la graduación. | AR4: A66. Evidencia y análisis de la evolución de la matrícula total de estudiantes del programa y de la relación entre aspirantes inscritos, admitidos y matriculados en cada periodo, a fin de establecer la tasa de selectividad y/o absorción del programa. | AS4: A68. Evidencia del efecto de la aplicación de políticas y estrategias de cooperación con comunidades, nacionales e internacionales, en el desarrollo de labores formativas, académicas, docentes, científicas, culturales, deportivas y de extensión, así como en aspectos curriculares y en la revisión de tendencias y referentes nacionales e internacionales que contribuyan al mejoramiento continuo del programa. | AT4: A69. Evidencia y análisis de los resultados de la cooperación académica y científica del programa, mediante convenios, proyectos conjuntos, intercambios de profesores, estudiantes y la participación en redes científicas, culturales y de extensión. | AU4: A71. Evidencia de la incidencia de las estrategias empleadas para el desarrollo de las competencias comunicativas en una segunda lengua y las interacciones de profesores y estudiantes con otras comunidades no hispanohablantes de acuerdo con el nivel de formación y modalidad del programa. | AV4: A72. Evidencia de las estrategias implementadas para el desarrollo de las competencias investigativas, de innovación o creación artística y cultural de los estudiantes, en coherencia con la naturaleza, nivel de formación y la modalidad de oferta del programa. | AW4: A74. Evidencia de la existencia de un reglamento de propiedad intelectual, de grupos de investigación categorizados y de profesores investigadores reconocidos en las convocatorias de medición de Minciencias, acorde con el Proyecto Educativo del Programa, el nivel de formación y la modalidad del programa. | AX4: A76. Análisis sistemáticos de la participación de estudiantes y profesores en las actividades de bienestar en cada uno de los escenarios de práctica. | AY4: A78. Análisis sistemáticos de la participación de la comunidad del programa en los planes y las actividades de bienestar, de acuerdo con las particularidades de la población estudiantil, académica y administrativa. | AZ4: A80. Demostración de los resultados y la incidencia de la implementación de las estrategias y recursos de apoyo (pedagógico-didáctico) en los contextos de actuación de los profesores para el mejoramiento de sus prácticas de enseñanza-aprendizaje teniendo en cuenta la diversidad y la inclusión. | BA4: A83. Evidencia de la disponibilidad y capacidad de talleres, laboratorios, equipos, medios audiovisuales, sitios de práctica, estaciones y granjas experimentales, escenarios de simulación virtual, entre otros, para el adecuado desarrollo de la actividad docente, investigativa y de extensión, según requerimientos del programa. | BB4: A86. Análisis de la correspondencia entre la inversión en recursos bibliográficos y de información, su utilización por parte de la comunidad del programa, demostrando la suficiencia y pertinencia para el desarrollo de actividades de docencia, investigación y extensión, de acuerdo con el nivel de formación y modalidad del programa. | BC4: A88. Evidencia de la participación de representantes de la comunidad académica, a través de estructuras organizacionales definidas por la institución, y de su contribución, en el desarrollo y mejoramiento del programa. | BD4: A90. Evidencia de los mecanismos existentes para la dirección y gestión del programa que contribuyen al mejoramiento de las dinámicas administrativas y académicas y al relacionamiento con los grupos de interés. | BE4: A92. Presentación de estudios de satisfacción de profesores y estudiantes del programa acerca de la suficiencia y calidad de los recursos y sistemas de comunicación e información. | BF4: A95. Presentación de estadísticas y análisis de las capacidades Institucionales en materia de recursos humanos (planta docente y personal administrativo), técnicos, tecnológicos y financieros, que favorecen la permanencia, el desarrollo académico y la graduación de los estudiantes. | BG4: A97. Demostración de la consistencia entre la asignación y distribución presupuestal del programa, y el desarrollo de las actividades de docencia, investigación, creación artística y cultural, deportiva, proyección social, bienestar institucional e internacionalización, y la implementación de los planes de mejoramiento. | BH4: A99. Evidencia de la consolidación de un Sistema Interno de Aseguramiento de la Calidad que permita verificar, mediante unos procesos periódicos y participativos de autoevaluación, la alta calidad en cada uno de los factores y características del modelo del Consejo Nacional de Acreditación, en el programa. | BI4: A101. Demostración de la existencia de aulas, laboratorios, talleres, centros de simulación, plataformas tecnológicas, biblioteca y salas de estudio, para el cumplimiento de las labores formativas, académicas, docentes, científicas, culturales y de extensión, en coherencia con el nivel de formación y la modalidad de oferta del programa. | BJ4: A103. Evidencia de la coherencia entre los recursos informáticos y de comunicación con las necesidades para el desarrollo y cumplimiento de las labores formativas, académicas, docentes, científicas, culturales del programa en el lugar de desarrollo y en los escenarios de práctica. | BL4: Mejoramiento | BM4: DOCENCIA | BO4: OE1_Diseñar e implementar estrategias integrales e innovadoras para arraigar la identidad de UNICESMAG | BP4: Innovación en el Modelo Pedagógico | BQ4: Trazabilidad de los RA en el macro, meso y micro currículo | BR4: Transformación y apropiación de la gobernabilidad y gobernanza institucional, mediante un marco normativo actualizado y pertinente.
A5: F2. Estudiantes | C5: C2. Relevancia académica y pertinencia social del programa académico | D5: C4. Orientación y seguimiento a estudiantes | E5: C9. Estatuto profesoral | F5: C17. Impacto de los egresados en el medio social y académico | G5: C19. Flexibilidad de los aspectos curriculares. | H5: C28. Caracterización de estudiantes y sistema de alertas tempranas. | I5: C32. Relaciones externas de profesores y estudiantes | J5: C35. Compromiso con la investigación, desarrollo tecnológico, la innovación y la creación | K5: C37. Participación y seguimiento | L5: C39. Estrategias y recursos de apoyo a estudiantes | M5: C42. Dirección y gestión | N5: C48. Recursos informáticos y de comunicación. | P5: A3. Estudio de la pertinencia social del programa desde la perspectiva de la comunidad académica y de sus grupos de interés con el fin de identificar necesidades y requerimientos del entorno local, regional o nacional en términos productivos y de competitividad, tecnológicos, culturales, científicos y de talento humano. | Q5: A6. Resultados del análisis de la participación y principales logros de los estudiantes en actividades de investigación, desarrollo tecnológico, innovación, creación artística, culturales y deportivas. | T5: A12. Evidencia de los mecanismos para la aplicación, actualización y divulgación del reglamento estudiantil. | U5: A14. Apreciación de los estudiantes del programa frente a la aplicación de los estímulos académicos y apoyos socioeconómicos, y el cumplimiento institucional de estas medidas, junto con las acciones emprendidas como resultado de dichas apreciaciones. | V5: A16. Apreciación de los profesores sobre la aplicación, pertinencia y vigencia de las políticas, normas y criterios académicos establecidos por la institución para su selección, vinculación y permanencia, junto con las acciones emprendidas como resultado de dichas apreciaciones. | W5: A18. Resultados en el mejoramiento de la calidad del programa, a partir de la aplicación de un estatuto que promueve la trayectoria profesoral, la inclusión, el reconocimiento de los méritos y el ascenso en el escalafón. | X5: A21. Evidencia de la existencia de un núcleo básico de profesores de tiempo completo, preferiblemente con contratación a término indefinido, y su relación con la formación de la comunidad académica del programa y el cumplimiento con alta calidad de las funciones esenciales del programa. | Y5: A28. Evidencia de cómo el desarrollo profesoral atiende a la diversidad de los estudiantes, a las modalidades de la docencia y a los requerimientos de internacionalización y de inter y multiculturalidad de profesores y estudiantes. | Z5: A31. Apreciación de directivos y profesores del programa, sobre el efecto que ha tenido el régimen de estímulos al profesorado en el ejercicio cualificado de la docencia, la investigación, la innovación, la creación artística y cultural, la extensión o proyección social, en los aportes al desarrollo técnico y tecnológico y la cooperación internacional, junto con las acciones emprendidas como resultado de dichas apreciaciones. | AA5: A33. Presentación de los resultados de evaluación de los materiales académicos producidos por los profesores para el desarrollo de las diversas actividades académicas, que soportan los ambientes de aprendizaje, de acuerdo con el nivel de formación y modalidad. | AC5: A37. Demostración del mejoramiento continuo del programa, a partir de las evaluaciones permanentes realizadas a los profesores, en coherencia con el nivel de formación y modalidad. | AD5: A39. Apreciación de los egresados en relación con el perfil de formación, las competencias adquiridas y las posibilidades que les ha ofrecido su formación para su desarrollo profesional y laboral, junto con las acciones emprendidas como resultado de dichas apreciaciones. | AE5: A41. Apreciación de empleadores sobre el desempeño destacado de los egresados y su aporte en la solución de los problemas académicos, ambientales, tecnológicos, sociales y culturales, junto con las acciones emprendidas como resultado de dichas apreciaciones. | AF5: A43. Evaluación de las estrategias y acciones del programa para el mejoramiento de las competencias definidas por el programa. | AG5: A45. Apreciación de estudiantes, profesores y egresados sobre las rutas de formación alternativas y adoptadas por los estudiantes a partir de sus necesidades e intereses, derivadas de las estrategias de flexibilidad curricular definidas por la institución, junto con las acciones emprendidas como resultado de dichas apreciaciones. | AH5: A47. Apreciación de los estudiantes y profesores frente a los mecanismos y criterios dispuestos por la institución para la interdisciplinariedad curricular del programa, los resultados de su análisis y la evidencia de los logros en el mejoramiento en la calidad del programa. | AI5: A49. Evidencia de la evaluación y el mejoramiento de las estrategias y prácticas pedagógicas, a partir de los aportes de la investigación pedagógica y de los procesos de actualización de los profesores. | AJ5: A52. Evidencia de los resultados obtenidos a partir de la implementación de los sistemas de evaluación de estudiantes basado en políticas y normas claras, universales y transparentes. | AK5: A55. Evidencia del proceso de mejoramiento continuo relacionado con la evaluación entre los resultados de aprendizaje esperados y los alcanzados por los estudiantes, el sistema de evaluación de estudiantes y las acciones de ajuste de los aspectos curriculares y las metodologías de enseñanza - aprendizaje derivadas de dicha evaluación. | AM5: A58. Apreciación de los profesores y estudiantes sobre la calidad y pertinencia del proceso de evaluación y autorregulación del programa, junto con las acciones emprendidas como resultado de dichas apreciaciones. | AN5: A60. Evidencia del efecto de las estrategias y acciones de proyección social como un mecanismo para establecer los aportes del programa a la solución de problemas de la sociedad y a las mejoras de los aspectos curriculares. | AP5: A63. Apreciación de estudiantes y profesores sobre la contribución de las estrategias del sistema de alertas tempranas en su permanencia y graduación, junto con las acciones emprendidas como resultado de dichas apreciaciones. | AR5: A67. Análisis de la correlación entre los mecanismos de selección, de desempeño académico, permanencia y graduación que resulte en ajustes a los procesos de selección del programa. | AT5: A70. Apreciación de profesores, estudiantes y egresados sobre los resultados de la cooperación académica y científica derivados de la aplicación de políticas y estrategias que favorezcan la interacción de profesores y estudiantes con sus homólogos, a nivel nacional e internacional, junto con las acciones emprendidas como resultado de dichas apreciaciones. | AV5: A73. Apreciación de los estudiantes acerca de la formación para la investigación, el desarrollo de un pensamiento crítico, creativo e innovador, así como el desarrollo tecnológico, la innovación y la creación promovida en el programa, junto con las acciones emprendidas como resultado de dichas apreciaciones. | AW5: A75. Evidencia de resultados de investigación, desarrollo tecnológico, innovación o creación de los profesores del programa, que contribuyan al fortalecimiento de los aspectos curriculares, la formación de los estudiantes y a la generación de nuevo conocimiento o a la solución de problemas de la sociedad, en coherencia con el Proyecto Educativo del Programa, el nivel de formación y la modalidad del programa. | AX5: A77. Apreciación de los estudiantes, profesores y personal administrativo sobre la incidencia de la implementación de políticas, programas y servicios de bienestar, en coherencia con las condiciones y necesidades de la comunidad en cada uno de los lugares y escenarios de práctica donde desarrolla sus labores, en correspondencia con el nivel de formación y la modalidad del programa, junto con las acciones emprendidas como resultado de dichas apreciaciones. | AY5: A79. Evaluación de la calidad y pertinencia de la infraestructura, espacios y servicios de bienestar por parte de la comunidad del programa, junto con las acciones emprendidas como resultado de dicha evaluación. | AZ5: A81. Apreciación de los profesores y los estudiantes en relación con las estrategias pedagógicas, tecnológicas y de acompañamiento dispuestas por el programa para el desarrollo de las habilidades comunicativas y de interacción de los profesores con los estudiantes, junto con las acciones emprendidas como resultado de dichas apreciaciones. | BA5: A84. Apreciación de los estudiantes sobre la utilidad y pertinencia de las estrategias y recursos de apoyo brindados por la institución para el desarrollo de su proceso formativo en diferentes contextos, junto con las acciones emprendidas como resultado de dichas apreciaciones. | BB5: A87. Apreciación de estudiantes y profesores acerca de la pertinencia, actualización y suficiencia del material bibliográfico con que cuenta el programa, para apoyar el desarrollo de las distintas actividades académicas, de acuerdo con su nivel de formación y modalidad, junto con las acciones emprendidas como resultado de dichas apreciaciones. | BC5: A89. Apreciación de estudiantes, profesores y egresados sobre su participación en cuerpos colegiados, y en decisiones orientadas al mejoramiento del programa, junto con las acciones emprendidas como resultado de dichas apreciaciones. | BD5: A91. Apreciación de profesores y estudiantes sobre la eficiencia, eficacia y orientación de los procesos administrativos hacia el desarrollo de las labores formativas, académicas, docentes, científicas, culturales y de extensión, junto con las acciones emprendidas como resultado de dichas apreciaciones. | BE5: A93. Presentación de estadísticas y análisis del uso de los sistemas de comunicación e información, y de la implementación de estrategias que garanticen la conectividad a los miembros de la comunidad académica del programa. | BF5: A96. Apreciación de profesores y estudiantes del programa con respecto a la correspondencia entre las capacidades Institucionales en materia de sus recursos humanos, técnicos, tecnológicos y financieros, y el número de estudiantes matriculados, en cumplimiento del Proyecto Educativo del Programa, junto con las acciones emprendidas como resultado de dichas apreciaciones. | BG5: A98. Presentación de la proyección y la ejecución del presupuesto de inversión y de funcionamiento del programa y los mecanismos de seguimiento y control. | BH5: A100. En el caso de los programas académicos del área de la salud, evidencia de los procesos de autoevaluación sobre el funcionamiento del convenio docencia servicio en cada uno de los escenarios de práctica y su incidencia en los procesos de mejoramiento. | BI5: A102. Evidencia de planes y proyectos realizados o en ejecución, para la conservación, expansión, mejoras y mantenimiento de la planta física para el programa, de acuerdo con las normas técnicas respectivas y con el nivel de formación y la modalidad de oferta del programa. | BJ5: A104. Apreciación de directivos, profesores y estudiantes del programa sobre la pertinencia, correspondencia y suficiencia de los recursos informáticos y de comunicación con que cuenta el programa. | BL5: Fortalecimiento | BM5: INVESTIGACIÓN Y EXTENSIÓN | BO5: OE2_Articular las labores institucionales desde una óptica transformadora de la persona para impactar la sociedad desde el reconocimiento de las culturas y las comunidades | BP5: Apropiación de la identidad institucional | BQ5: Interacción social pertinente | BR5: Consolidación de la comunidad UNICESMAG, a través de una arquitectura institucional eficiente.
A6: F3. Profesores | D6: C5. Capacidad de trabajo autónomo | E6: C10. Número, dedicación, nivel de formación y experiencia | G6: C20. Interdisciplinariedad | H6: C29. Ajustes a los aspectos curriculares | I6: C33. Habilidades comunicativas en una segunda lengua | L6: C40. Recursos bibliográficos y de información | M6: C43. Sistemas de comunicación e información | P6: A4. Evidencia de las transformaciones sociales pertinentes para el contexto y el territorio en el que se ofrece el programa académico, y del entorno tanto nacional como internacional. | Q6: A7. Resultados del análisis de la participación y principales logros de los estudiantes en proyectos de desarrollo empresarial, relacionamiento nacional e internacional. | W6: A19. Apreciación de los profesores sobre la aplicación y pertinencia del estatuto profesoral y de las políticas que establecen distinciones, estímulos que promueven la trayectoria profesoral, junto con las acciones emprendidas como resultado de dichas apreciaciones. | X6: A22. Evidencia de la vinculación de una planta profesoral pertinente con el área disciplinar del programa (TyT) con título de especialista y experiencia pedagógica y profesional certificada en los campos de formación del programa, que garantice del logro de los resultados de aprendizaje de los estudiantes y el cumplimiento de las funciones asignadas en condiciones de calidad, atendiendo a estándares internacionales, en coherencia con el nivel de formación y modalidad del programa. | Y6: A29. Apreciación de directivos y profesores del programa sobre los resultados que han tenido las acciones orientadas al desarrollo integral de los profesores, en el mejoramiento de las competencias pedagógicas, científicas y sociales para el sostenimiento de las funciones misionales, junto con las acciones emprendidas como resultado de dichas apreciaciones. | AA6: A34. Apreciación de los estudiantes y directivos del programa sobre la pertinencia y calidad del material académico producido, de acuerdo con el nivel de formación y la modalidad del programa, junto con las acciones emprendidas como resultado de dichas apreciaciones. | AI6: A50. En el caso de programas académicos del área de la salud, presentar análisis de la incidencia de las actividades desarrolladas en el marco de los convenios de docencia servicio con los distintos escenarios de práctica (con énfasis en el escenario principal, cuando aplique) en los procesos de formación. Los análisis se deben realizar entre las partes que participan en el convenio. | AJ6: A53. Evidencia de sistemas de evaluación que integran la innovación para generar transformaciones profundas en el Aprendizaje, y que acogen dinámicas en referencia a cambios en el conocimiento. | AP6: A64. Presentación del análisis de los resultados derivados del sistema de alertas tempranas y su impacto en el currículo, para mejorar el desempeño académico de los estudiantes, su permanencia y graduación. | AZ6: A82. En el caso de programas académicos del área de la salud, análisis de las acciones que realizan conjuntamente el programa con los escenarios de práctica, en sus procesos de certificación, acreditación, reconocimiento como hospital universitario y acciones de mejora. | BA6: A85. En el caso de los programas académicos del área de la salud, evidencia de la disponibilidad de laboratorios especializados y/o de simulación en los distintos lugares de desarrollo y los escenarios de práctica, y análisis del nivel de uso por parte de profesores y estudiantes. | BE6: A94. Evidencia de la aplicación de mecanismos de gestión documental, organización, actualización y seguridad de los registros y archivos académicos de estudiantes, profesores, personal directivo y administrativo. | BM6: DIRECCIONAMIENTO ESTRATÉGICO | BO6: OE3_Desarrollar una arquitectura institucional bajo los principios de ética y buen gobierno | BP6: Fomento de la cultura de autoevaluación al quehacer institucional | BQ6: Sostenibilidad administrativa y financiera. | BR6: Toma de decisiones con base en información confiable
A7: F4. Egresados | D7: C6. Reglamento estudiantil y política académica | E7: C11. Desarrollo profesoral | G7: C21. Estrategias pedagógicas. | H7: C30. Mecanismos de selección | M7: C44. Estudiantes y capacidad institucional | Q7: A8. Resultados del análisis de la participación y principales logros de los estudiantes en otras acciones de formación complementaria, que promuevan la comprensión de la realidad social, la empatía, la ética, habilidades blandas, así como el relacionamiento con otras culturas y lenguas, de acuerdo con el nivel de formación y la modalidad del programa. | X7: A23. Evidencia de la vinculación de una planta profesoral pertinente con el área disciplinar del programa (Prof) con título de especialistas, magísteres y/o doctores con experiencia o formación pedagógica y profesional certificada, que garantice el logro de los resultados de aprendizaje de los estudiantes y el cumplimiento de las funciones asignadas en condiciones de calidad, atendiendo a estándares internacionales, en coherencia con el nivel de formación y modalidad del programa. | BM7: ASEGURAMIENTO Y GESTIÓN DE LA CALIDAD | BP7: Innovación en los procesos de bienestar, permanencia, inclusión y graduación | BQ7: Creación de entornos tecnológicos sostenibles para las labores formativas
A8: F5. Aspectos académicos y resultados de aprendizaje | D8: C7. Estímulos y apoyos para estudiantes | E8: C12. Estímulos a la trayectoria profesoral | G8: C22. Sistema de evaluación de estudiantes | M8: C45. Financiación del programa académico | X8: A24. Evidencia de la vinculación de una planta profesoral pertinente con el área disciplinar del programa (Esp) con título de medicina y especialidad médico-quirúrgica, con experiencia o formación pedagógica y profesional certificada en el campo de práctica de la especialidad, que garantice el logro de los resultados de aprendizaje de los estudiantes y el cumplimiento de las funciones asignadas en condiciones de calidad, atendiendo a estándares internacionales, en coherencia con el nivel de formación y modalidad del programa. | BM8: GESTIÓN JURÍDICA | BQ8: Interinstitucionalización de la UNICESMAG
A9: F6. Permanencia y graduación | E9: C13. Producción, pertinencia, utilización e impacto de material docente | G9: C23. Resultados de aprendizaje | M9: C46. Aseguramiento de la alta calidad y mejora continua | X9: A25. Evidencia de la vinculación de una planta profesoral pertinente con el área disciplinar del programa (Mg) con título de maestría y/o doctorado con experiencia o formación pedagógica, investigativa y profesional certificada y experiencia en investigación, que garantice el logro de los resultados de aprendizaje de los estudiantes y el cumplimiento de las funciones asignadas en condiciones de calidad, atendiendo a estándares internacionales, en coherencia con el nivel de formación y modalidad del programa. | BM9: GESTIÓN HUMANA | BQ9: Fortalecimiento de la investigación, innovación y/o creación artística y cultural
A10: F7. Interacción con el entorno nacional e internacional | E10: C14. Remuneración por méritos | G10: C24. Competencias | X10: A26. Evidencia de la vinculación de una planta profesoral pertinente con el área disciplinar del programa (Dr) con título de doctorado y con experiencia en la dirección de tesis doctorales, así como publicaciones en revistas indexadas y libros en los campos de conocimiento, reconocidos en el Ministerio de Ciencia, Tecnología e Innovación (Minciencias), con experiencia o formación pedagógica, que garantice el logro de los resultados de aprendizaje de los estudiantes y el cumplimiento de las funciones asignadas en condiciones de calidad, atendiendo a estándares internacionales, en coherencia con el nivel de formación y modalidad del programa. | BM10: GESTIÓN DEL BIENESTAR INSTITUCIONAL
A11: F8. Aportes de la investigación, la innovación, el desarrollo tecnológico y la creación, asociados al programa académico | E11: C15. Evaluación de profesores | G11: C25. Evaluación y autorregulación del programa académico | BM11: GESTIÓN DE LA COMUNICACIÓN
A12: F9. Bienestar de la comunidad académica del programa | G12: C26. Vinculación e interacción social | BM12: GESTIÓN DE LA EVANGELIZACIÓN
A13: F10. Medios educativos y ambientes de aprendizaje | BM13: GESTIÓN DE LA TECNOLOGÍA
A14: F11. Organización, administración y financiación del programa académico | BM14: GESTIÓN DE BIENES Y SERVICIOS
A15: F12. Recursos físicos y tecnológicos | BM15: GESTIÓN FINANCIERA
BM16: GESTIÓN DOCUMENTAL

Sheet PM
D2: UNIVERSIDAD CESMAG
D4: PLAN DE MEJORAMIENTO | I4: INSTRUCCIONES: 1. No alterar la estructura del formato. 2. No combinar celdas horizontal o verticalmente, en caso que se requiera asociar varios indicadores a una actividad se debe repetir su postulado en las filas que sea necesario. 3. Utilizar las listas de selección en los campos cuyo encabezado está resaltado con fondo rojo. 4. Diligenciar completamente los campos para cada actividad de mejoramiento o fortalecimiento identificadas.
D5: AÑO: | E5: 2027 - 2029
D7: PROGRAMA:
B10: CÓDIGO OBJETIVO | C10: FACTOR | D10: CARACTERÍSTICA | E10: ASPECTO / HALLAZGO | F10: CALIFICACIÓN | G10: TIPO DE ACCIÓN | H10: OBJETIVO | I10: NOMBRE DE LA ACTIVIDAD | J10: DESCRIPCIÓN DE LA ACTIVIDAD | K10: INDICADOR | L10: META | M10: FECHA INICIO | N10: FECHA FIN | O10: RECURSOS | P10: VALOR PRESUPUESTO | Q10: PROCESO RESPONSABLE | R10: CARGO RESPONSABLE | S10: ALCANCE | T10: EJE ESTRATÉGICO | U10: OBJETIVO ESTRATÉGICO | V10: PROYECTO PDI
B11: OPM_01 | C11: F4. Egresados | D11: C17. Impacto de los egresados en el medio social y académico | H11: Desarrollar un estudio cualitativo y cuantitativo del contexto, para establecer propuestas de solución a las necesidades encontradas en el plan de estudios | I11: Estudio de las necesidades del contexto regional en el marco de la política pública nacional y regional. | J11: Se adelantará un estudiocualitativo y cuantitativo para reconocer las necesidades del contexto a nivel regional y nacional. El estudio del resultado para establecer propuestas de modificación del plan de estudios | K11: Documento estudio del contexto | L11: 1 | O11: Recursos humanos, tecnológicos y financieros | P11: =SUMIF(PERSONAL!H:H,PM!B11,PERSONAL!G:G)+SUMIF('ADQUISICIÓN DE ACTIVOS'!H:H,PM!B11,'ADQUISICIÓN DE ACTIVOS'!G:G)+SUMIF(PUBLICIDAD!H:H,PM!B11,PUBLICIDAD!G:G)+SUMIF('ÚTILES Y PAPELERÍA'!H:H,PM!B11,'ÚTILES Y PAPELERÍA'!G:G)+SUMIF('ESPACIOS FÍSICOS y EQUIP'!I:I,PM!B11,'ESPACIOS FÍSICOS y EQUIP'!H:H)+SUMIF(DIVERSOS!H:H,PM!B11,DIVERSOS!G:G) -> 18731250 | Q11: DOCENCIA | R11: Dirección Programa de Psicología | S11: PROGRAMA | U11: Ofrecer_programas_de_calidad | V11: Actualización de los PEP en coherencia con el PEI, Misión y Visión Institucionales y carácter institucional.
B12: OPM_02 | H12: Presentar propuestas que permitan realizar cambios en el plan de estudios en articulación con la renovación de registro calificado. | I12: Análisis del plan de estudios del Programa de Psicología | J12: A partir del estudio y las conclusiones del estudio de necesidades se presentarán propuestas para el plan de estudios ofertado por el Programa de Psicología. | K12: Documento propuestas para cambios en el plan de estudios | L12: 1 | O12: Recursos humanos, tecnológicos y financieros | P12: =SUMIF(PERSONAL!H:H,PM!B12,PERSONAL!G:G)+SUMIF('ADQUISICIÓN DE ACTIVOS'!H:H,PM!B12,'ADQUISICIÓN DE ACTIVOS'!G:G)+SUMIF(PUBLICIDAD!H:H,PM!B12,PUBLICIDAD!G:G)+SUMIF('ÚTILES Y PAPELERÍA'!H:H,PM!B12,'ÚTILES Y PAPELERÍA'!G:G)+SUMIF('ESPACIOS FÍSICOS y EQUIP'!I:I,PM!B12,'ESPACIOS FÍSICOS y EQUIP'!H:H)+SUMIF(DIVERSOS!H:H,PM!B12,DIVERSOS!G:G) -> 4052170.6 | Q12: DOCENCIA | R12: Dirección Programa de Psicología | S12: PROGRAMA
B13: OPM_03 | H13: Diseñar una estrategia para el seguimiento a los proyectos que adelanta el programa, mediante sus funciones de docencia, investigación, innovación, creación artística y cultural, y extensión. | I13: Estrategia de seguimiento a proyectos adelantados por el programa | J13: Identificación y sistematización de los proyectos que adelanta el programa, mediante sus funciones de docencia, investigación, innovación, creación artística y cultural, y extensión. | K13: Documento de la estrategia de seguimiento a proyectos adelantados por el programa | L13: 1 | O13: Recursos humanos, tecnológicos y financieros | P13: =SUMIF(PERSONAL!H:H,PM!B13,PERSONAL!G:G)+SUMIF('ADQUISICIÓN DE ACTIVOS'!H:H,PM!B13,'ADQUISICIÓN DE ACTIVOS'!G:G)+SUMIF(PUBLICIDAD!H:H,PM!B13,PUBLICIDAD!G:G)+SUMIF('ÚTILES Y PAPELERÍA'!H:H,PM!B13,'ÚTILES Y PAPELERÍA'!G:G)+SUMIF('ESPACIOS FÍSICOS y EQUIP'!I:I,PM!B13,'ESPACIOS FÍSICOS y EQUIP'!H:H)+SUMIF(DIVERSOS!H:H,PM!B13,DIVERSOS!G:G) -> 0 | Q13: DOCENCIA | R13: Dirección Programa de Psicología | S13: PROGRAMA
B14: OPM_04 | P14: =SUMIF(PERSONAL!H:H,PM!B14,PERSONAL!G:G)+SUMIF('ADQUISICIÓN DE ACTIVOS'!H:H,PM!B14,'ADQUISICIÓN DE ACTIVOS'!G:G)+SUMIF(PUBLICIDAD!H:H,PM!B14,PUBLICIDAD!G:G)+SUMIF('ÚTILES Y PAPELERÍA'!H:H,PM!B14,'ÚTILES Y PAPELERÍA'!G:G)+SUMIF('ESPACIOS FÍSICOS y EQUIP'!I:I,PM!B14,'ESPACIOS FÍSICOS y EQUIP'!H:H)+SUMIF(DIVERSOS!H:H,PM!B14,DIVERSOS!G:G) -> 0
B15: OPM_05 | P15: =SUMIF(PERSONAL!H:H,PM!B15,PERSONAL!G:G)+SUMIF('ADQUISICIÓN DE ACTIVOS'!H:H,PM!B15,'ADQUISICIÓN DE ACTIVOS'!G:G)+SUMIF(PUBLICIDAD!H:H,PM!B15,PUBLICIDAD!G:G)+SUMIF('ÚTILES Y PAPELERÍA'!H:H,PM!B15,'ÚTILES Y PAPELERÍA'!G:G)+SUMIF('ESPACIOS FÍSICOS y EQUIP'!I:I,PM!B15,'ESPACIOS FÍSICOS y EQUIP'!H:H)+SUMIF(DIVERSOS!H:H,PM!B15,DIVERSOS!G:G) -> 0
B16: OPM_06 | P16: =SUMIF(PERSONAL!H:H,PM!B16,PERSONAL!G:G)+SUMIF('ADQUISICIÓN DE ACTIVOS'!H:H,PM!B16,'ADQUISICIÓN DE ACTIVOS'!G:G)+SUMIF(PUBLICIDAD!H:H,PM!B16,PUBLICIDAD!G:G)+SUMIF('ÚTILES Y PAPELERÍA'!H:H,PM!B16,'ÚTILES Y PAPELERÍA'!G:G)+SUMIF('ESPACIOS FÍSICOS y EQUIP'!I:I,PM!B16,'ESPACIOS FÍSICOS y EQUIP'!H:H)+SUMIF(DIVERSOS!H:H,PM!B16,DIVERSOS!G:G) -> 0
B17: OPM_07 | P17: =SUMIF(PERSONAL!H:H,PM!B17,PERSONAL!G:G)+SUMIF('ADQUISICIÓN DE ACTIVOS'!H:H,PM!B17,'ADQUISICIÓN DE ACTIVOS'!G:G)+SUMIF(PUBLICIDAD!H:H,PM!B17,PUBLICIDAD!G:G)+SUMIF('ÚTILES Y PAPELERÍA'!H:H,PM!B17,'ÚTILES Y PAPELERÍA'!G:G)+SUMIF('ESPACIOS FÍSICOS y EQUIP'!I:I,PM!B17,'ESPACIOS FÍSICOS y EQUIP'!H:H)+SUMIF(DIVERSOS!H:H,PM!B17,DIVERSOS!G:G) -> 0
B18: OPM_08 | P18: =SUMIF(PERSONAL!H:H,PM!B18,PERSONAL!G:G)+SUMIF('ADQUISICIÓN DE ACTIVOS'!H:H,PM!B18,'ADQUISICIÓN DE ACTIVOS'!G:G)+SUMIF(PUBLICIDAD!H:H,PM!B18,PUBLICIDAD!G:G)+SUMIF('ÚTILES Y PAPELERÍA'!H:H,PM!B18,'ÚTILES Y PAPELERÍA'!G:G)+SUMIF('ESPACIOS FÍSICOS y EQUIP'!I:I,PM!B18,'ESPACIOS FÍSICOS y EQUIP'!H:H)+SUMIF(DIVERSOS!H:H,PM!B18,DIVERSOS!G:G) -> 0
B19: OPM_09 | P19: =SUMIF(PERSONAL!H:H,PM!B19,PERSONAL!G:G)+SUMIF('ADQUISICIÓN DE ACTIVOS'!H:H,PM!B19,'ADQUISICIÓN DE ACTIVOS'!G:G)+SUMIF(PUBLICIDAD!H:H,PM!B19,PUBLICIDAD!G:G)+SUMIF('ÚTILES Y PAPELERÍA'!H:H,PM!B19,'ÚTILES Y PAPELERÍA'!G:G)+SUMIF('ESPACIOS FÍSICOS y EQUIP'!I:I,PM!B19,'ESPACIOS FÍSICOS y EQUIP'!H:H)+SUMIF(DIVERSOS!H:H,PM!B19,DIVERSOS!G:G) -> 0
B20: OPM_10 | P20: =SUMIF(PERSONAL!H:H,PM!B20,PERSONAL!G:G)+SUMIF('ADQUISICIÓN DE ACTIVOS'!H:H,PM!B20,'ADQUISICIÓN DE ACTIVOS'!G:G)+SUMIF(PUBLICIDAD!H:H,PM!B20,PUBLICIDAD!G:G)+SUMIF('ÚTILES Y PAPELERÍA'!H:H,PM!B20,'ÚTILES Y PAPELERÍA'!G:G)+SUMIF('ESPACIOS FÍSICOS y EQUIP'!I:I,PM!B20,'ESPACIOS FÍSICOS y EQUIP'!H:H)+SUMIF(DIVERSOS!H:H,PM!B20,DIVERSOS!G:G) -> 0
P21: =SUMIF(PERSONAL!H:H,PM!B21,PERSONAL!G:G)+SUMIF('ADQUISICIÓN DE ACTIVOS'!H:H,PM!B21,'ADQUISICIÓN DE ACTIVOS'!G:G)+SUMIF(PUBLICIDAD!H:H,PM!B21,PUBLICIDAD!G:G)+SUMIF('ÚTILES Y PAPELERÍA'!H:H,PM!B21,'ÚTILES Y PAPELERÍA'!G:G)+SUMIF('ESPACIOS FÍSICOS y EQUIP'!I:I,PM!B21,'ESPACIOS FÍSICOS y EQUIP'!H:H)+SUMIF(DIVERSOS!H:H,PM!B21,DIVERSOS!G:G) -> 0
P22: =SUMIF(PERSONAL!H:H,PM!B22,PERSONAL!G:G)+SUMIF('ADQUISICIÓN DE ACTIVOS'!H:H,PM!B22,'ADQUISICIÓN DE ACTIVOS'!G:G)+SUMIF(PUBLICIDAD!H:H,PM!B22,PUBLICIDAD!G:G)+SUMIF('ÚTILES Y PAPELERÍA'!H:H,PM!B22,'ÚTILES Y PAPELERÍA'!G:G)+SUMIF('ESPACIOS FÍSICOS y EQUIP'!I:I,PM!B22,'ESPACIOS FÍSICOS y EQUIP'!H:H)+SUMIF(DIVERSOS!H:H,PM!B22,DIVERSOS!G:G) -> 0
P23: =SUMIF(PERSONAL!H:H,PM!B23,PERSONAL!G:G)+SUMIF('ADQUISICIÓN DE ACTIVOS'!H:H,PM!B23,'ADQUISICIÓN DE ACTIVOS'!G:G)+SUMIF(PUBLICIDAD!H:H,PM!B23,PUBLICIDAD!G:G)+SUMIF('ÚTILES Y PAPELERÍA'!H:H,PM!B23,'ÚTILES Y PAPELERÍA'!G:G)+SUMIF('ESPACIOS FÍSICOS y EQUIP'!I:I,PM!B23,'ESPACIOS FÍSICOS y EQUIP'!H:H)+SUMIF(DIVERSOS!H:H,PM!B23,DIVERSOS!G:G) -> 0
P24: =SUMIF(PERSONAL!H:H,PM!B24,PERSONAL!G:G)+SUMIF('ADQUISICIÓN DE ACTIVOS'!H:H,PM!B24,'ADQUISICIÓN DE ACTIVOS'!G:G)+SUMIF(PUBLICIDAD!H:H,PM!B24,PUBLICIDAD!G:G)+SUMIF('ÚTILES Y PAPELERÍA'!H:H,PM!B24,'ÚTILES Y PAPELERÍA'!G:G)+SUMIF('ESPACIOS FÍSICOS y EQUIP'!I:I,PM!B24,'ESPACIOS FÍSICOS y EQUIP'!H:H)+SUMIF(DIVERSOS!H:H,PM!B24,DIVERSOS!G:G) -> 0
P25: =SUMIF(PERSONAL!H:H,PM!B25,PERSONAL!G:G)+SUMIF('ADQUISICIÓN DE ACTIVOS'!H:H,PM!B25,'ADQUISICIÓN DE ACTIVOS'!G:G)+SUMIF(PUBLICIDAD!H:H,PM!B25,PUBLICIDAD!G:G)+SUMIF('ÚTILES Y PAPELERÍA'!H:H,PM!B25,'ÚTILES Y PAPELERÍA'!G:G)+SUMIF('ESPACIOS FÍSICOS y EQUIP'!I:I,PM!B25,'ESPACIOS FÍSICOS y EQUIP'!H:H)+SUMIF(DIVERSOS!H:H,PM!B25,DIVERSOS!G:G) -> 0
P26: =SUMIF(PERSONAL!H:H,PM!B26,PERSONAL!G:G)+SUMIF('ADQUISICIÓN DE ACTIVOS'!H:H,PM!B26,'ADQUISICIÓN DE ACTIVOS'!G:G)+SUMIF(PUBLICIDAD!H:H,PM!B26,PUBLICIDAD!G:G)+SUMIF('ÚTILES Y PAPELERÍA'!H:H,PM!B26,'ÚTILES Y PAPELERÍA'!G:G)+SUMIF('ESPACIOS FÍSICOS y EQUIP'!I:I,PM!B26,'ESPACIOS FÍSICOS y EQUIP'!H:H)+SUMIF(DIVERSOS!H:H,PM!B26,DIVERSOS!G:G) -> 0
P27: =SUMIF(PERSONAL!H:H,PM!B27,PERSONAL!G:G)+SUMIF('ADQUISICIÓN DE ACTIVOS'!H:H,PM!B27,'ADQUISICIÓN DE ACTIVOS'!G:G)+SUMIF(PUBLICIDAD!H:H,PM!B27,PUBLICIDAD!G:G)+SUMIF('ÚTILES Y PAPELERÍA'!H:H,PM!B27,'ÚTILES Y PAPELERÍA'!G:G)+SUMIF('ESPACIOS FÍSICOS y EQUIP'!I:I,PM!B27,'ESPACIOS FÍSICOS y EQUIP'!H:H)+SUMIF(DIVERSOS!H:H,PM!B27,DIVERSOS!G:G) -> 0
P28: =SUMIF(PERSONAL!H:H,PM!B28,PERSONAL!G:G)+SUMIF('ADQUISICIÓN DE ACTIVOS'!H:H,PM!B28,'ADQUISICIÓN DE ACTIVOS'!G:G)+SUMIF(PUBLICIDAD!H:H,PM!B28,PUBLICIDAD!G:G)+SUMIF('ÚTILES Y PAPELERÍA'!H:H,PM!B28,'ÚTILES Y PAPELERÍA'!G:G)+SUMIF('ESPACIOS FÍSICOS y EQUIP'!I:I,PM!B28,'ESPACIOS FÍSICOS y EQUIP'!H:H)+SUMIF(DIVERSOS!H:H,PM!B28,DIVERSOS!G:G) -> 0
P29: =SUMIF(PERSONAL!H:H,PM!B29,PERSONAL!G:G)+SUMIF('ADQUISICIÓN DE ACTIVOS'!H:H,PM!B29,'ADQUISICIÓN DE ACTIVOS'!G:G)+SUMIF(PUBLICIDAD!H:H,PM!B29,PUBLICIDAD!G:G)+SUMIF('ÚTILES Y PAPELERÍA'!H:H,PM!B29,'ÚTILES Y PAPELERÍA'!G:G)+SUMIF('ESPACIOS FÍSICOS y EQUIP'!I:I,PM!B29,'ESPACIOS FÍSICOS y EQUIP'!H:H)+SUMIF(DIVERSOS!H:H,PM!B29,DIVERSOS!G:G) -> 0

Sheet Hoja2
A1: FACTORES | B1: F1. Proyecto Educativo del Programa e Identidad Institucional | C1: F2. Estudiantes | D1: F3. Profesores | E1: F4. Egresados | F1: F5. Aspectos académicos y resultados de aprendizaje | G1: F6. Permanencia y graduación | H1: F7. Interacción con el entorno nacional e internacional | I1: F8. Aportes de la investigación, la innovación, el desarrollo tecnológico y la creación, asociados al programa académico | J1: F9. Bienestar de la comunidad académica del programa | K1: F10. Medios educativos y ambientes de aprendizaje | L1: F11. Organización, administración y financiación del programa académico | M1: F12. Recursos físicos y tecnológicos | O1: PROCESO RESPONSABLE
A2: F1. Proyecto Educativo del Programa e Identidad Institucional | B2: C1. Proyecto Educativo del Programa | C2: C3. Participación en actividades de formación integral | D2: C8. Selección, vinculación y permanencia | E2: C16. Seguimiento de los egresados | F2: C18. Integralidad de los aspectos curriculares | G2: C27. Políticas, estrategias y estructura para la permanencia y la graduación | H2: C31. Inserción del programa en contextos académicos nacionales e internacionales | I2: C34. Formación para la investigación, desarrollo tecnológico, la innovación y la creación | J2: C36. Programas y servicios | K2: C38. Estrategias y recursos de apoyo a profesores | L2: C41. Organización y administración | M2: C47. Recursos de infraestructura física y tecnológica. | O2: DOCENCIA
A3: F2. Estudiantes | B3: C2. Relevancia académica y pertinencia social del programa académico | C3: C4. Orientación y seguimiento a estudiantes | D3: C9. Estatuto profesoral | E3: C17. Impacto de los egresados en el medio social y académico | F3: C19. Flexibilidad de los aspectos curriculares. | G3: C28. Caracterización de estudiantes y sistema de alertas tempranas. | H3: C32. Relaciones externas de profesores y estudiantes | I3: C35. Compromiso con la investigación, desarrollo tecnológico, la innovación y la creación | J3: C37. Participación y seguimiento | K3: C39. Estrategias y recursos de apoyo a estudiantes | L3: C42. Dirección y gestión | M3: C48. Recursos informáticos y de comunicación. | O3: INVESTIGACIÓN Y EXTENSIÓN
A4: F3. Profesores | C4: C5. Capacidad de trabajo autónomo | D4: C10. Número, dedicación, nivel de formación y experiencia | F4: C20. Interdisciplinariedad | G4: C29. Ajustes a los aspectos curriculares | H4: C33. Habilidades comunicativas en una segunda lengua | K4: C40. Recursos bibliográficos y de información | L4: C43. Sistemas de comunicación e información | O4: DIRECCIONAMIENTO ESTRATÉGICO
A5: F4. Egresados | C5: C6. Reglamento estudiantil y política académica | D5: C11. Desarrollo profesoral | F5: C21. Estrategias pedagógicas. | G5: C30. Mecanismos de selección | L5: C44. Estudiantes y capacidad institucional | O5: ASEGURAMIENTO Y GESTIÓN DE LA CALIDAD
A6: F5. Aspectos académicos y resultados de aprendizaje | C6: C7. Estímulos y apoyos para estudiantes | D6: C12. Estímulos a la trayectoria profesoral | F6: C22. Sistema de evaluación de estudiantes | L6: C45. Financiación del programa académico | O6: GESTIÓN JURÍDICA
A7: F6. Permanencia y graduación | D7: C13. Producción, pertinencia, utilización e impacto de material docente | F7: C23. Resultados de aprendizaje | L7: C46. Aseguramiento de la alta calidad y mejora continua | O7: GESTIÓN HUMANA
A8: F7. Interacción con el entorno nacional e internacional | D8: C14. Remuneración por méritos | F8: C24. Competencias | O8: GESTIÓN DEL BIENESTAR INSTITUCIONAL
A9: F8. Aportes de la investigación, la innovación, el desarrollo tecnológico y la creación, asociados al programa académico | D9: C15. Evaluación de profesores | F9: C25. Evaluación y autorregulación del programa académico | O9: GESTIÓN DE LA COMUNICACIÓN
A10: F9. Bienestar de la comunidad académica del programa | F10: C26. Vinculación e interacción social | O10: GESTIÓN DE LA EVANGELIZACIÓN
A11: F10. Medios educativos y ambientes de aprendizaje | O11: GESTIÓN DE LA TECNOLOGÍA
A12: F11. Organización, administración y financiación del programa académico | O12: GESTIÓN DE BIENES Y SERVICIOS
A13: F12. Recursos físicos y tecnológicos | O13: GESTIÓN FINANCIERA
O14: GESTIÓN DOCUMENTAL
M19: ALCANCE
B20: F1. Proyecto Educativo del Programa e Identidad Institucional | M20: INSTITUCIONAL
B21: F2. Estudiantes | M21: PROGRAMA
B22: F3. Profesores
B23: F4. Egresados
B24: F5. Aspectos académicos y resultados de aprendizaje
B25: F6. Permanencia y graduación
B26: F7. Interacción con el entorno nacional e internacional
B27: F8. Aportes de la investigación, la innovación, el desarrollo tecnológico y la creación, asociados al programa académico
B28: F9. Bienestar de la comunidad académica del programa
B29: F10. Medios educativos y ambientes de aprendizaje
B30: F11. Organización, administración y financiación del programa académico
B31: F12. Recursos físicos y tecnológicos
B34: TIPO DE ACCIÓN
B35: MEJORAMIENTO
B36: FORTALECIMIENTO
A39: EJES | F39: OBJETIVO ESTRATÉGICO | G39: OE1_Diseñar e implementar estrategias integrales e innovadoras para arraigar la identidad de UNICESMAG | H39: OE2_Articular las labores institucionales desde una óptica transformadora de la persona para impactar la sociedad desde el reconocimiento de las culturas y las comunidades | I39: OE3_Desarrollar una arquitectura institucional bajo los principios de ética y buen gobierno
A40: DOCENCIA | F40: OE1_Diseñar e implementar estrategias integrales e innovadoras para arraigar la identidad de UNICESMAG | G40: Innovación en el Modelo Pedagógico | H40: Trazabilidad de los RA en el macro, meso y micro currículo | I40: Transformación y apropiación de la gobernabilidad y gobernanza institucional, mediante un marco normativo actualizado y pertinente.
A41: INVESTIGACIÓN | F41: OE2_Articular las labores institucionales desde una óptica transformadora de la persona para impactar la sociedad desde el reconocimiento de las culturas y las comunidades | G41: Apropiación de la identidad institucional | H41: Interacción social pertinente | I41: Consolidación de la comunidad UNICESMAG, a través de una arquitectura institucional eficiente.
A42: EXTENSIÓN Y PROYECCIÓN SOCIAL | F42: OE3_Desarrollar una arquitectura institucional bajo los principios de ética y buen gobierno | G42: Fomento de la cultura de autoevaluación al quehacer institucional | H42: Sostenibilidad administrativa y financiera. | I42: Toma de decisiones con base en información confiable
A43: IDENTIDAD INSTITUCIONAL | G43: Innovación en los procesos de bienestar, permanencia, inclusión y graduación | H43: Creación de entornos tecnológicos sostenibles para las labores formativas
A44: BIENESTAR INSTITUCIONAL | H44: Interinstitucionalización de la UNICESMAG
A45: INFRAESTRUCTURA FÍSICA Y TECNOLÓGICA | H45: Fortalecimiento de la investigación, innovación y/o creación artística y cultural
A46: INTERNACIONALIZACIÓN
A47: GESTIÓN ORGANIZACIONAL Y ADMINISTRATIVA
A48: AUTOEVALUACIÓN Y ACREDITACIÓN
A63: ADMINISTRACIÓN DE EMPRESAS
A64: ARQUITECTURA
A65: CONTADURÍA PÚBLICA
A66: DERECHO
A67: DISEÑO GRÁFICO
A68: ESP. EN GERENCIA DE PROYECTOS
A69: INGENIERÍA DE SISTEMAS
A70: INGENIERÍA ELECTRÓNICA
A71: LICENCIATURA EN EDUCACIÓN FÍSICA
... A75: TECNOLOGÍA EN GESTIÓN FINANCIERA

Sheet Hoja3
A1: C1. Proyecto Educativo del Programa | B1: C2. Relevancia académica y pertinencia social del programa académico | C1: C3. Participación en actividades de formación integral | D1: C4. Orientación y seguimiento a estudiantes | E1: C5. Capacidad de trabajo autónomo | F1: C6. Reglamento estudiantil y política académica | G1: C7. Estímulos y apoyos para estudiantes | H1: C8. Selección, vinculación y permanencia | I1: C9. Estatuto profesoral | J1: C10. Número, dedicación, nivel de formación y experiencia | K1: C11. Desarrollo profesoral | L1: C12. Estímulos a la trayectoria profesoral | M1: C13. Producción, pertinencia, utilización e impacto de material docente | N1: C14. Remuneración por méritos | O1: C15. Evaluación de profesores | P1: C16. Seguimiento de los egresados | Q1: C17. Impacto de los egresados en el medio social y académico | R1: C18. Integralidad de los aspectos curriculares | S1: C19. Flexibilidad de los aspectos curriculares. | T1: C20. Interdisciplinariedad | U1: C21. Estrategias pedagógicas. | V1: C22. Sistema de evaluación de estudiantes | W1: C23. Resultados de aprendizaje | X1: C24. Competencias | Y1: C25. Evaluación y autorregulación del programa académico | Z1: C26. Vinculación e interacción social | AA1: C27. Políticas, estrategias y estructura para la permanencia y la graduación | AB1: C28. Caracterización de estudiantes y sistema de alertas tempranas. | AC1: C29. Ajustes a los aspectos curriculares | AD1: C30. Mecanismos de selección | AE1: C31. Inserción del programa en contextos académicos nacionales e internacionales | AF1: C32. Relaciones externas de profesores y estudiantes | AG1: C33. Habilidades comunicativas en una segunda lengua | AH1: C34. Formación para la investigación, desarrollo tecnológico, la innovación y la creación | AI1: C35. Compromiso con la investigación, desarrollo tecnológico, la innovación y la creación | AJ1: C36. Programas y servicios | AK1: C37. Participación y seguimiento | AL1: C38. Estrategias y recursos de apoyo a profesores | AM1: C39. Estrategias y recursos de apoyo a estudiantes | AN1: C40. Recursos bibliográficos y de información | AW1: F1. Proyecto Educativo del Programa e Identidad Institucional | AX1: F2. Estudiantes | AY1: F3. Profesores | AZ1: F4. Egresados | BA1: F5. Aspectos académicos y resultados de aprendizaje | BB1: F6. Permanencia y graduación | BC1: F7. Interacción con el entorno nacional e internacional | BD1: F8. Aportes de la investigación, la innovación, el desarrollo tecnológico y la creación, asociados al programa académico | BE1: F9. Bienestar de la comunidad académica del programa | BF1: F10. Medios educativos y ambientes de aprendizaje | BG1: F11. Organización, administración y financiación del programa académico | BH1: F12. Recursos físicos y tecnológicos
A2: A1. Apropiación de la Visión y la Misión Institucional por parte de la comunidad académica. | B2: A7. Estrategias y mecanismos establecidos para la discusión, actualización y difusión del Proyecto Educativo del Programa académico. | C2: A11. Análisis realizados sobre las tendencias y líneas de desarrollo de la disciplina o profesión en el ámbito local, regional, nacional e internacional, y su incidencia en el programa. | D2: A20. Mecanismos de ingreso que garanticen transparencia en la selección de los estudiantes. | E2: A24. Políticas institucionales para la definición del número de estudiantes que se admiten al programa, acorde con el cuerpo docente, los recursos físicos y de apoyo académico disponible. | F2: A31. Políticas y estrategias definidas por el programa en materia de formación integral de los estudiantes. | G2: A34. Mecanismos utilizados para la divulgación del reglamento estudiantil y académico. | H2: A39. Aplicación de las políticas, las normas y los créditos académicos establecidos por la Institución para la selección y la vinculación de los profesores. | I2: A42. Mecanismos de divulgación del estatuto profesoral. | J2: A48. Profesores de planta con título de especialización, maestría y doctorado en relación con el objeto de conocimiento del programa adscritos directamente o a través de la Facultad o Departamento respectivo, e información demostrada acerca de las Instituciones en las cuales fueron formados. | K2: A56. Políticas institucionales y evidencias de aplicación, en materia de desarrollo integral del profesorado, que incluyan la capacitación y actualización en los aspectos académicos, profesionales y pedagógicos relacionados con la metodología del programa. | L2: A62. Políticas de estímulo y reconocimiento a los profesores por el ejercicio calificado de la docencia, de la investigación, de la innovación, de la creación artística, de la técnica y tecnología, de la extensión o proyección social y de la cooperación internacional. | M2: A65. Producción, utilización y evaluación de materiales de apoyo docente, en los últimos cinco años, pertinentes a la naturaleza y metodología del programa y su función pedagógica. | N2: A69. Políticas y reglamentaciones institucionales en materia de remuneración de los profesores en las que se tengan en cuenta los méritos profesionales y académicos, así como los estímulos a la producción académica y de innovación debidamente evaluada. | O2: A72. Existencia y aplicación de políticas institucionales en materia de evaluación integral al desempeño de los profesores. La Institución presente evidencias sobre el desarrollo de estas políticas. | P2: A77. Existencia de criterios y mecanismos para el seguimiento y la evaluación del desarrollo de competencias, especialmente las actitudes, los conocimientos, las capacidades y las habilidades generales y aquellas que son específicas del ejercicio y de la cultura de la profesión o la disciplina en la que se forma al estudiante. | Q2: A87. Existencia y aplicación de políticas institucionales en materia de flexibilidad, referidas a la organización y jerarquización de los contenidos, reconocimiento de créditos, formación en competencias tales como actitudes, conocimientos, capacidades y habilidades, y estrategias pedagógicas, electividad, doble titulación y movilidad. | R2: A97. Espacios y actividades curriculares y extracurriculares con carácter explícitamente interdisciplinario. | S2: A100. Concordancia de los métodos de enseñanza y aprendizaje utilizados con el tipo y metodología del programa. | T2: A114. Criterios, políticas y reglamentaciones institucionales y del programa en materia de evaluación académica de los estudiantes. Evidencias de aplicación y divulgación de la misma. | U2: A120. Correspondencia entre el tipo de trabajos y actividades realizados por los estudiantes respecto a los objetivos y modalidad del programa. | V2: A125. Existencia y aplicación de políticas en materia de evaluación y autorregulación del programa académico que conduzcan al diseño y formulación de planes de mejoramiento continuo y a la gestión de la innovación. | W2: A129. Existencia y aplicación de criterios y políticas institucionales y del programa en materia de extensión o proyección social. | X2: A137. Estrategias y mecanismos orientados a incentivar en el estudiante la consulta y el uso de material bibliográfico. Evidencias de aplicación de estas estrategias y mecanismos. | Y2: A144. Disponibilidad para docentes, estudiantes, directivos y administrativos, actualización y calidad de los recursos informáticos y de comunicaciones para el desarrollo de los procesos académicos y de apoyo del programa, de acuerdo con su naturaleza. | Z2: A148. Dotación adecuada de equipos materiales e insumos en los laboratorios y talleres campos de práctica y plantas piloto, según la naturaleza, metodología y exigencias del programa. | AA2: A154. Existencia y aplicación de políticas institucionales en materia de referentes académicos externos, nacionales e internacionales para la revisión y actualización del plan de estudio. | AB2: A163. Convenios activos de intercambio con universidades nacionales y extranjeras. | AC2: A171. Criterios, estrategias y actividades del Programa, orientados a promover la capacidad de indagación y búsqueda, y la formación de un espíritu investigativo, creativo e innovador en los estudiantes. | AD2: A182. Criterios, estrategias y políticas institucionales en materia de investigación, innovación y creación artística y cultural que se evidencie en mecanismos efectivos que estimulen el desarrollo de los procesos investigativos, de innovación y creativos, y establezcan criterios de evaluación de su calidad y pertinencia, ampliamente difundidos y aceptados por la comunidad académica. | AE2: A190. Políticas sobre Bienestar Institucional suficientemente conocidas que propician el desarrollo integral de la comunidad institucional, reconozcan el valor y la diversidad y orientan la prestación de los servicios de bienestar. | AF2: A199. Tasas de deserción estudiantil acumulada y por periodos académicos, acorde con los reportes efectuados al sistema para la prevención de la Deserción de la Educación Superior –SPADIES-. | AG2: A202. Correspondencia entre la organización, administración y gestión del programa, y los fines de la docencia, la investigación, la innovación o creación artística y cultural, la extensión o proyección social y la cooperación nacional e internacional en el Programa. | AH2: A209. Existencia y utilización de sistemas de información integrados y mecanismos eficaces que faciliten la comunicación interna y externa el Programa. | AI2: A218. Apreciación de profesores y estudiantes del programa sobre la orientación académica que imparten los directivos del mismo y sobre el liderazgo que ejercen. | AJ2: A222. Existencia de registros actualizados sobre ocupación y ubicación profesional de los egresados del Programa. | AK2: A230. Índice de empleo entre los egresados del Programa. | AL2: A234. Espacios que se destinan al desarrollo de cada una de las funciones sustantivas a que se dedica el Programa y de las áreas destinadas al Bienestar Institucional. | AM2: A239. Origen, monto y distribución de los recursos presupuestales destinados al Programa. | AN2: A247. Manejo de los recursos físicos y financieros, en concordancia con los planes de desarrollo, los planes de mejoramiento y el tamaño y la complejidad de la Institución y del Programa. | AW2: C1. Proyecto Educativo del Programa | AX2: C3. Participación en actividades de formación integral | AY2: C8. Selección, vinculación y permanencia | AZ2: C16. Seguimiento de los egresados | BA2: C18. Integralidad de los aspectos curriculares | BB2: C27. Políticas, estrategias y estructura para la permanencia y la graduación | BC2: C31. Inserción del programa en contextos académicos nacionales e internacionales | BD2: C34. Formación para la investigación, desarrollo tecnológico, la innovación y la creación | BE2: C36. Programas y servicios | BF2: C38. Estrategias y recursos de apoyo a profesores | BG2: C41. Organización y administración | BH2: C47. Recursos de infraestructura física y tecnológica.
A3: A2. Correspondencia entre la Visión y la Misión Institucional y los objetivos del programa académico. | B3: A8. Apropiación del Proyecto Educativo del Programa por parte de la comunidad académica del programa. | C3: A12. Estudios orientados a identificar las necesidades y requerimientos del entorno laboral (local, regional y nacional) en términos productivos y de competitividad, tecnológicos y de talento humano. Acciones del programa para atenderlos. | D3: A21. Estudiantes que ingresaron mediante la aplicación de reglas generales y mecanismos de admisión excepcionales, en los últimos cinco años. | E3: A25. Apreciación de profesores y estudiantes del programa con respecto a la relación entre el número de admitidos, el cuerpo docente y los recursos académicos y físicos disponibles. | F3: A32. Apreciación de los estudiantes sobre la calidad de los espacios y estrategias que ofrece el programa, de acuerdo con la naturaleza y orientación de éste, para la participación en grupos o centros de estudio, proyectos de experimentación o de desarrollo empresarial y demás actividades académicas y culturales distintas de la docencia que contribuyan a su formación integral. | G3: A35. Apreciación de estudiantes y profesores del programa sobre pertinencia, vigencia y aplicación del reglamento estudiantil y académico. | H3: A40. Estrategias de la Institución para propiciar la permanencia de los profesores en el programa y el relevo generacional. | I3: A43. Apreciación de directivos y profesores del programa sobre la pertinencia, vigencia y aplicación del estatuto profesoral. | J3: A49. Profesores del programa adscritos en forma directa o a través de la Facultad o Departamento respectivo con dedicación de tiempo completo, medio tiempo y cátedra, según nivel de formación. | K3: A57. Número de profesores del programa adscritos directamente o a través de la Facultad o Departamento respectivo, que han participado en los últimos cinco años en programas de desarrollo profesoral o que han recibido apoyo a la capacitación y actualización permanente, como resultado de las políticas institucionales orientadas para tal fin. | L3: A63. Estrategias que promueven la creación artística y cultural, la innovación, la adaptación, la transferencia técnica y tecnológica, la creación de tecnofactos y prototipos, y la obtención de patentes, de acuerdo con la naturaleza del programa. | M3: A66. Apreciación de los estudiantes del programa sobre la calidad de los materiales de apoyo producidos o utilizados por los profesores adscritos al programa y su pertinencia de acuerdo con la metodología del programa. | N3: A70. Evidencias sobre la aplicación de estas políticas y reglamentaciones. | O3: A73. Criterios y mecanismos de evaluación de los profesores adscritos al programa, en correspondencia con la naturaleza del cargo, las funciones y los compromisos contraídos en relación con las metas institucionales y del programa. | P3: A78. Créditos académicos del programa correspondiente a asignaturas orientadas a ampliar la formación del estudiante en las dimensiones ética, estética, ambiental, filosófica, política y social. | Q3: A88. Existencia y aplicación de políticas y normas para asegurar la continuidad y movilidad del estudiante en el sistema educativo y en la Institución: homologaciones de créditos, reconocimientos de experiencias educativas y laborales previas, equivalencia de títulos y transferencias. | R3: A98. Mecanismos que permitan el tratamiento de problemas pertinentes al programa y al ejercicio laboral, a través de orientaciones interdisciplinarias por parte de profesores y estudiantes. | S3: A101. Correspondencia de los métodos de enseñanza y aprendizaje empleados para el desarrollo de los contenidos del plan de estudios del programa, como las competencias tales como las actitudes, los conocimientos, las capacidades y las habilidades que se espera desarrollar, la naturaleza de los saberes y las necesidades, objetivos y modalidad del programa. | T3: A115. Correspondencia entre las formas de evaluación de los aprendizajes, los propósitos de formación y los perfiles de egreso definidos por el programa. | U3: A121. Criterios y estrategias aplicados en el programa para efecto de la dosificación de la labor académica de los estudiantes en coherencia con el sistema de créditos. | V3: A126. Estrategias verificables de seguimiento, evaluación y mejoramiento continuo y gestión de la innovación de los procesos y logros del programa, así como de su pertinencia y relevancia social. | W3: A130. Proyectos y actividades de extensión o proyección a la comunidad desarrollados por directivos, profesores y estudiantes del programa en los últimos cinco años. | X3: A138. Existencia y aplicación de criterios y políticas institucionales y del programa en materia de acceso, adquisición y actualización de material bibliográfico. | Y3: A145. Estrategias que garanticen el rendimiento de los equipos, la capacidad de almacenamiento y la seguridad (confidencialidad, disponibilidad) en el manejo de la información. | Z3: A149. Dotación adecuada de laboratorios, máquinas y talleres suficientemente dotados con equipos y materiales, según la naturaleza, metodología y exigencias del programa, y que cumplen las normas sanitarias y de bioseguridad, seguridad industrial y de salud ocupacional y manejo de seres vivos, de acuerdo con la normativa vigente. | AA3: A155. Análisis sistemático de comparabilidad con otros programas nacionales e internacionales de la misma naturaleza. | AB3: A164. Número de estudiantes extranjeros en el Programa en los últimos 5 años. | AC3: A172. Existencia y utilización de mecanismos por parte de los profesores adscritos al programa para incentivar en los estudiantes la generación de ideas y problemas de investigación, la identificación de problemas en el ámbito empresarial susceptibles de resolver mediante la aplicación del conocimiento y la innovación. | AD3: A183. Correspondencia entre el número y nivel de formación de los profesores adscritos al programa con la actividad investigativa y de innovación y la creación artística y cultural, relacionadas con la naturaleza del programa. | AE3: A191. Estrategias que propicien un clima institucional adecuado que favorezca el desarrollo humano y promueva una cultura que reconozca el valor de la diversidad.. | AF3: A200. Registros periódicos de la caracterización de los estudiantes teniendo en cuenta variables de vulnerabilidad. | AG3: A203. Existencia de certificaciones y de mecanismos orientados al mejoramiento de la calidad de procesos. | AH3: A210. Existencia y efectividad de la página web institucional debidamente actualizada para mantener informados a los usuarios sobre los temas de interés institucional y facilitar la comunicación académica y administrativa. | AI3: A219. Lineamientos y políticas que orientan la gestión del programa, debidamente divulgados y apropiados por los directivos, profesores y personal administrativo del mismo. | AJ3: A223. Correspondencia entre la ocupación y ubicación profesional de los egresados y el perfil de formación del Programa. | AK3: A231. Egresados del programa que forman parte de comunidades académicas reconocidas, de asociaciones científicas, profesionales, tecnológicas, técnicas o artísticas, y del sector productivo y financiero, en el ámbito nacional o internacional. | AL3: A235. Existencia y uso adecuado de aulas, laboratorios, talleres, sitios de estudio para los alumnos, salas de cómputo, oficinas de profesores, sitios para la creación artística y cultural, auditorios y sales de conferencias, oficinas administrativas, cafeterías, baños, servicios, campos de juego, espacios libres, zonas verdes y demás espacios destinados al Bienestar en general. | AM3: A240. Mecanismos de seguimiento y verificación a la ejecución presupuestal del Programa con base en planes de mejoramiento y mantenimiento. | AN3: A248. Criterios y mecanismos para la elaboración, ejecución y seguimiento del presupuesto y para la asignación de recursos físicos y financieros para el Programa. | AW3: C2. Relevancia académica y pertinencia social del programa académico | AX3: C4. Orientación y seguimiento a estudiantes | AY3: C9. Estatuto profesoral | AZ3: C17. Impacto de los egresados en el medio social y académico | BA3: C19. Flexibilidad de los aspectos curriculares. | BB3: C28. Caracterización de estudiantes y sistema de alertas tempranas. | BC3: C32. Relaciones externas de profesores y estudiantes | BD3: C35. Compromiso con la investigación, desarrollo tecnológico, la innovación y la creación | BE3: C37. Participación y seguimiento | BF3: C39. Estrategias y recursos de apoyo a estudiantes | BG3: C42. Dirección y gestión | BH3: C48. Recursos informáticos y de comunicación.
A4: A3. El proyecto institucional orienta las acciones y decisiones del programa académico, en la gestión del currículo, la docencia, la investigación científica, la creación artística, la internacionalización, la proyección social, el bienestar de la comunidad institucional y demás áreas estratégicas de la institución. | B4: A9. Modelo pedagógico o concepción de aprendizaje que sustentan la metodología de enseñanza en que se ofrece el programa evaluado | C4: A13. Estudios que demuestren la necesidad social del programa en la metodología que se ofrece. | D4: A22. Existencia y utilización de sistemas y mecanismos de evaluación de los procesos de selección y admisión, y aplicación de los resultados de dicha evaluación. | E4: A26. Población de estudiantes que ingreso al programa en los últimos cinco años, el puntaje promedio obtenido por los admitidos en las pruebas de estado, el puntaje promedio estandarizado en pruebas de admisión cuando éstas se realicen, el puntaje mínimo aceptable para ingresar y la capacidad de selección y absorción de estudiantes por parte del programa (relación entre inscritos y admitidos, relación entre inscritos y matriculados). | F4: A33. Estudiantes que participan efectivamente en grupos o centros de estudio, proyectos de experimentación o de desarrollo empresarial o en las demás actividades académicas y culturales distintas de la docencia que brinda la institución o el programa para contribuir a la formación integral. | G4: A36. Evidencias sobre la aplicación de las normas establecidas en los reglamentos estudiantil y académico para atender las situaciones presentadas con los estudiantes. | H4: A41. Apreciación de directivos, profesores y estudiantes sobre la aplicación, pertinencia y vigencia de las políticas, las normas y los criterios académicos establecidos por la institución para la selección, vinculación y permanencia de sus profesores. | I4: A44. Información actualizada sobre el número de profesores adscritos a la facultad, al programa o departamento que sirva al mismo, por categorías académicas establecidas en el escalafón. | J4: A50. Tiempos de cada profesor del programa adscritos directamente o a través de la Facultad o Departamento respectivo, dedicados a la docencia (incluyendo el desarrollo de productos, artefactos, materiales y prototipos, entre otros), a la investigación, a la creación artística, a la extensión o proyección social, a la atención de funciones de gestión académica o administrativa, a la tutoría individual de los estudiantes, de acuerdo con la naturaleza del programa. | K4: A58. Apreciación de directivos y profesores del programa adscritos directamente o a través de la Facultad o Departamento respectivo, sobre el impacto que han tenido las acciones orientadas al desarrollo integral de los profesores, en el enriquecimiento de la calidad del programa. | L4: A64. Apreciación de directivos y profesores del programa, adscritos directamente o a través de la Facultad o Departamento respectivo, sobre el impacto que, para el enriquecimiento de la calidad del programa ha tenido el régimen de estímulos al profesorado por el ejercicio calificado de la docencia. La investigación, la innovación, la creación artística y cultural, la extensión o proyección social, los aportes al desarrollo técnico y tecnológico y la cooperación internacional. | M4: A67. Premios u otros reconocimientos a los materiales de apoyo a la labor docente, en el ámbito nacional o internacional, que hayan producido los profesores adscritos al programa. | N4: A71. Apreciación de los profesores con respecto a la correspondencia entre la remuneración y los méritos académicos y profesionales. | O4: A74. Evaluaciones realizadas a los profesores adscritos al programa durante los últimos cinco años y las acciones adelantadas por la Institución y por el programa a partir de dichos resultados. | P4: A79. Asignación de créditos y de distribución de tiempos directo e independiente, a las distintas actividades de formación de acuerdo con la modalidad en que se ofrece el programa. | Q4: A89. Mecanismos de actualización permanente del currículo en consonancia con los desarrollos disciplinares, profesionales y pedagógicos, y en atención a las necesidades del entorno. | R4: A99. Apreciación de profesores y estudiantes sobre la pertinencia y eficacia de la interdisciplinariedad del programa en el enriquecimiento de la calidad del mismo. | S4: A102. Apreciación de los estudiantes, profesores y directivos del programa sobre la correspondencia entre los métodos de enseñanza y aprendizaje que se emplean en el programa y el desarrollo de los contenidos del plan de estudios. | T4: A116. Apreciación de directivos, profesores y estudiantes del programa sobre la correspondencia entre las formas de evaluación académica de los estudiantes, la naturaleza del mismo y los métodos pedagógicos empleados para su desarrollo. | U4: A122. Apreciación de directivos y profesores adscritos al programa sobre la correspondencia entre la calidad de los trabajos realizados por los estudiantes y los objetivos de logro definidos para el mismo, incluyendo la formación personal. | V4: A127. Apreciación de directivos, profesores, estudiantes sobre la incidencia de los sistemas de evaluación y autorregulación del programa en el enriquecimiento de la calidad de éste. | W4: A131. Evidencias del impacto en el entorno que han generado los resultados de los proyectos de extensiones o proyección social desarrollados por el programa | X4: A139. Pertinencia, actualización y suficiencia del material bibliográfico con que cuenta el programa para apoyar el desarrollo de las distintas actividades académicas, de acuerdo con el tipo y modalidad de programa. | Y4: A146. Eficiencia, oportunidad y eficacia en cuanto a la actualización y al soporte técnico de la plataforma informática y los equipos computacionales. | Z4: A150. Disponibilidad y capacidad de talleres, laboratorios, equipos, medios audiovisuales, sitios de práctica, estaciones y granjas experimentales, escenarios de simulación virtual entre otros, para el óptimo desarrollo de la actividad docente, investigativa y de extensión, según requerimientos del programa. | AA4: A156. Convenios activos y actividades de cooperación académica desarrollados por el Programa con Instituciones y Programas de Alta Calidad y reconocimiento nacional e internacional. | AB4: A165. Experiencias de homologación de cursos realizados en otros programas nacionales o extranjeros. | AC4: A173. Estudiantes que están vinculados como monitores, auxiliares de investigación e integrantes de semilleros y/o grupos de investigación. | AD4: A184. Recursos humanos, logísticos y financieros con que cuenta el programa, asociados a proyectos y a otras actividades de investigación, innovación y creación artística y cultural. | AE4: A192. Programas, servicios y actividades de bienestar dirigidos a los profesores, estudiantes y personal administrativo del Programa. | AF4: A201. Existencia de proyectos que establezcan estrategias pedagógicas y actividades extracurriculares orientadas a optimizar las tasas de retención y de graduación de estudiantes en los tiempos previstos, manteniendo la calidad académica del Programa. | AG4: A204. Criterios institucionales para la toma de decisiones sobre asignación de cargos, responsabilidades y procedimientos en los diferentes programas académicos, evidencias sobre la aplicación de estos criterios. | AH4: A211. La página web institucional incluye información detallada y actualizada sobre el currículo y los profesores adscritos al programa, incluyendo su formación y trayectoria. | AI4: A220. Documentos institucionales que establecen la forma de operación (procesos y procedimientos) de las distintas instancias relacionadas con la gestión del Programa. | AJ4: A224. Apreciación de los egresados, empleadores y usuarios externos sobre la calidad de la formación dada por el programa. | AK4: A232. Egresados del programa que han recibido distinciones y reconocimientos significativos por su desempeño en la disciplina, profesión, ocupación u oficio correspondiente. | AL4: A236. Existencia de planes y proyectos en ejecución para la conservación, expansión, mejoras y mantenimiento de la planta física para el Programa, de acuerdo con las normas técnicas respectivas. | AM4: A241. Distribución de la asignación presupuestal para actividades de docencia, investigación, creación artística y cultural, proyección social, bienestar institucional e internacionalización que en forma directa o indirecta se reflejen en el Programa. | AN4: A249. Evidencias de los controles legales y administrativos para asegurar el manejo transparente de los recursos. | AX4: C5. Capacidad de trabajo autónomo | AY4: C10. Número, dedicación, nivel de formación y experiencia | BA4: C20. Interdisciplinariedad | BB4: C29. Ajustes a los aspectos curriculares | BC4: C33. Habilidades comunicativas en una segunda lengua | BF4: C40. Recursos bibliográficos y de información | BG4: C43. Sistemas de comunicación e información
A5: A4. La Institución cuenta con una política eficaz y tiene evidencias sobre alternativas de financiación para facilitar el ingreso y permanencia de los estudiantes que evidencian dificultades económicas. | B5: A10. Coherencia entre el Proyecto Educativo del Programa y las actividades académicas desarrolladas. | C5: A14. Correspondencia entre el perfil laboral y ocupacional del sector y el perfil profesional expresado en el Proyecto Educativo del Programa. | D5: A23. Requerimientos para el ingreso de estudiantes en condición de transferencia, homologación u otro proceso que amerite criterios específicos para el tránsito entre ciclos, niveles y/o instituciones. Beneficios de estos requerimientos en la formación integral de los estudiantes. | E5: A27. En los programas de salud, donde sea pertinente, evidenciar la utilización de escenarios de práctica requeridos para cumplir con los objetivos del programa. | G5: A37. Apreciación de directivos, profesores y estudiantes sobre la participación del estudiantado en los órganos de dirección del programa. | I5: A45. Aplicación de las políticas institucionales en materia de ubicación, permanencia y ascenso en las categorías del escalafón docente. | J5: A51. Tiempos de los profesores de cátedra dedicados a las tutorías, al acompañamiento de estudiante y el desarrollo de competencias, especialmente actitudes, conocimientos, capacidades y habilidades. | K5: A59. Acompañamiento por expertos, para la labor pedagógica de los profesores, de acuerdo con el tipo y metodología del programa. | M5: A68. Existencia y aplicación de un régimen de propiedad intelectual en la Institución aplicado a los materiales de apoyo a la docencia. | O5: A75. Información verificable sobre la participación de los distintos actores en la evaluación. | P5: A80. Apreciación de directivos, profesores y estudiantes sobre la calidad e integralidad del currículo. | Q5: A90. Índice de flexibilidad curricular y comparativos nacionales e internacionales. | S5: A103. Estrategias y mecanismos de seguimiento y acompañamiento por parte del docente al trabajo que realizan los estudiantes en las distintas actividades académicas, de acuerdo con sus capacidades y potencialidades y con el tipo y metodología del programa. | T5: A117. Apreciación de los estudiantes acerca de la utilidad del sistema de evaluación académica en la adquisición de competencias, tales como las actitudes, los conocimientos, las capacidades y las habilidades propias del programa. | U5: A123. Correspondencia entre las actividades y trabajos realizados por los estudiantes y las formas de evaluación por competencias especialmente en actitudes, conocimientos, capacidades y habilidades, según la naturaleza del programa y los métodos pedagógicos empleados para desarrollar los diversos procesos de formación. | V5: A128. Cambios específicos realizados en el programa, en los últimos cinco años, a partir de los resultados de los procesos de evaluación y autorregulación. | W5: A132. Participación del programa en la aplicación las políticas nacionales en materia de innovación y desarrollo económico, técnico y tecnológico (innovación, adaptación, transferencia), de acuerdo con el tipo y modalidad del programa. | X5: A140. Inversión anual en las adquisiciones de libros, revistas especializadas, bases de datos y suscripciones a publicaciones periódicas, relacionados con el programa académico, en los últimos cinco años. | Y5: A147. Apreciación de directivos, profesores y estudiantes del programa sobre la pertinencia, correspondencia y suficiencia de los recursos informáticos y de comunicación con que cuenta el programa. | Z5: A151. Convenios con centros, instituciones, empresas u organizaciones, que faciliten el uso de otros recursos y escenarios de enseñanza, aprendizaje, investigación y creación artística y cultural, por parte de la comunidad académica. | AA5: A157. Proyectos de investigación, innovación, creación artística y cultural y/o proyección desarrollados como producto de la cooperación académica y profesional, realizada por directivos, profesores y estudiantes del programa, con miembros de comunidades nacionales e internacionales de reconocido liderazgo en el área del Programa. | AB5: A166. Profesores o expertos visitantes nacionales y extranjeros que ha recibido el Programa en los últimos cinco años (objetivos, duración y resultados de su estadía). | AC5: A174. Grupos y semilleros de investigación del programa en los que participan estudiantes, de acuerdo con su tipo y modalidad. | AD5: A185. Grupos de investigación conformados por profesores y estudiantes adscritos al programa, reconocidos por COLCIENCIAS o por otro organismo. | AE5: A193. Participación de directivos, profesores, estudiantes y personal administrativo del programa en los programas, los servicios y las actividades de Bienestar Institucional. | AG5: A205. Cantidad y dedicación del talento humano para cubrir las necesidades del Programa. | AH5: A212. Sistema de consulta, registro y archivo de la información académica de los estudiantes y los profesores adscritos al programa. | AI5: A221. Mecanismos eficientes de participación de la comunidad académica en la gestión del Programa. | AJ5: A225. Apreciación de los egresados acerca de la forma como el programa favorece el desarrollo del proyecto de vida. | AK5: A233. Apreciación de empleadores sobre la calidad de la formación y el desempeño de los egresados del programa. | AL5: A237. Apreciación de directivos, profesores, estudiantes y personal administrativo del programa sobre las características de la planta física, desde el punto de vista de su accesibilidad, diseño, capacidad, iluminación, ventilación y condiciones de seguridad e higiene. | AM5: A242. Porcentaje de los ingresos que la Institución dedica a la inversión en el Programa. | AN5: A250. Apreciación de directivos y profesores adscritos al Programa sobre la equidad en la asignación de recursos físicos y financieros para el Programa. | AX5: C6. Reglamento estudiantil y política académica | AY5: C11. Desarrollo profesoral | BA5: C21. Estrategias pedagógicas. | BB5: C30. Mecanismos de selección | BG5: C44. Estudiantes y capacidad institucional
A6: A5. La Institución aplica una política eficaz que permite el acceso a la educación superior sin discriminación. Promueve estrategias eficaces orientadas a identificar, eliminar o disminuir barreras comunicativas para poblaciones diversas. | C6: A15. Estudios y/o proyectos formulados o en desarrollo, que propendan por la modernización, actualización y pertinencia del currículo de acuerdo con las necesidades del entorno. | E6: A28. Evidenciar que los convenios de docencia – servicios se realizan a largo plazo y con IPS acreditadas o con Hospitales Universitarios y en ellos la dinámica interinstitucional denota equilibrio y reciprocidad. | G6: A38. Políticas y estrategias sobre estímulos académicos para los estudiantes. El programa tiene evidencias sobre la aplicación de estas políticas y estrategias. | I6: A46. Apreciación de directivos y profesores sobre la aplicación de las políticas institucionales en materia de participación del profesorado en los órganos de dirección de la institución y del programa. | J6: A52. Experiencia profesional y/o académica de los profesores, según necesidades y exigencias del programa para el desarrollo óptimo de sus funciones sustantivas. | K6: A60. Reconocimiento a los profesores que participan en procesos de creación artística y cultural. | O6: A76. Apreciación de los profesores adscritos al programa, sobre los criterios y mecanismos para la evaluación de docentes, su transparencia, equidad y eficacia. | P6: A81. Estrategias aplicadas para el fomento de la creatividad y del desarrollo de pensamiento autónomo en los estudiantes. | Q6: A91. Apreciación de directivos, profesores y estudiantes del programa sobre aplicación y eficacia de las políticas institucionales en materia de flexibilidad curricular. | S6: A104. Incorporación de los adelantos y transformaciones que se han dado en las ciencias, las técnicas y las tecnologías implicadas, de acuerdo con el tipo y modalidad del programa. | T6: A118. Criterios y procedimientos orientados a la evaluación de competencias especialmente actitudes, conocimientos, capacidades y habilidades, y estrategias de retroalimentación de la actividad académica de los estudiantes | U6: A124. Trabajos académicos realizados por estudiantes del programa, en los últimos cinco años, que han merecido premios o reconocimientos significativos por la comunidad académica nacional o internacional. | W6: A133. Apreciación de empresarios, funcionarios públicos, líderes comunitarios y de otros agentes externos sobre el impacto social de los proyectos desarrollados por el programa. | X6: A141. Profesores y estudiantes del programa que utilizan recursos bibliográficos: libros, revistas especializadas y bases de datos, en los últimos cinco años, de acuerdo con el tipo y modalidad del programa. | Z6: A152. Para programas del área de Ciencias de la Salud, información sobre escenarios de práctica y convenios docente-asistenciales de largo plazo, con Hospitales Universitarios o IPS acreditadas, certificados por el Ministerio de Protección Social. Evidenciar su pertinencia, calidad docente y capacidad instalada en relación con el número de estudiantes del programa. | AA6: A158. Profesores, estudiantes y directivos del programa con participación activa en redes u organismos nacionales e internacionales de la que se hayan derivado productos concretos como publicaciones en coautoría, cofinanciación de proyectos, registros y patentes, entre otros. | AB6: A167. Profesores y estudiantes adscritos al programa que en los últimos cinco años han participado en actividades de cooperación académica y profesional con programas nacionales e internacionales de reconocido liderazgo en el área (semestre académico de intercambio, pasantía o práctica, rotación médica, curso corto, misión, profesor visitante/conferencia, estancia de investigación, estudios de postgrado, profesor en programa de pregrado y/o postgrado, congresos, foros, seminarios, simposios, educación continuada, par académico, parques tecnológicos, incubadoras de empresas, mesas y ruedas de negociación económica y tecnológica, entre otros). | AC6: A175. Actividades académicas – cursos electivos, seminarios, pasantías, eventos – derivados de líneas de investigación en los últimos cinco años. | AD6: A186. Impacto a nivel regional, nacional e internacional de la investigación, la innovación y la creación artística y cultural del programa, de acuerdo con su naturaleza. | AE6: A194. Apreciación de directivos, profesores, estudiantes y personal administrativo del programa sobre la calidad y pertinencia de los servicios y las actividades de bienestar y sobre su contribución a su desarrollo personal. | AG6: A206. Formación y experiencia de quienes orientan la administración del Programa. | AH6: A213. Mecanismos de gestión documental, organización, actualización y seguridad de los registros y archivos académicos de estudiantes, profesores, personal directivo y administrativo. | AJ6: A226. Utilización de la información contenida en el Observatorio Laboral para la Educación, como insumo para estudiar la pertinencia del programa. | AL6: A238. Disponibilidad de infraestructura física para atender las necesidades académicas, administrativas y de bienestar, que sea coherente con la modalidad en que se ofrece el Programa. | AM6: A243. Capacidad del programa para generar recursos externos para el apoyo a sus funciones misionales. | AN6: A251. En los programas de salud, donde sea pertinente, evidencia las dinámicas de administración compartida entre las Instituciones de Educación Superior y el Hospital Universitario o IPS, en cuanto a convenios docentes-asistenciales y escenarios de prácticas, entre otros. | AX6: C7. Estímulos y apoyos para estudiantes | AY6: C12. Estímulos a la trayectoria profesoral | BA6: C22. Sistema de evaluación de estudiantes | BG6: C45. Financiación del programa académico
A7: A6. La Institución cuenta con una política eficaz orientada a identificar, eliminar o disminuir barreras en infraestructura física. La institución tiene evidencias sobre la aplicación de esta política. | C7: A16. Estudios actualizados sobre las necesidades formativas en la región de influencia del programa. | E7: A29. En los programas de salud, donde sea pertinente, evidenciar que la relación entre el número de estudiantes y la capacidad instalada de los escenarios de práctica (camas, docentes, tutores, investigadores, entre otros) es adecuada y suficiente. | I7: A47. Evidencias sobre la participación de los profesores en los órganos de dirección del programa, de la facultad, del departamento y/o de la institución, durante los últimos cinco años. | J7: A53. Suficiencia del número de profesores con relación a la cantidad de estudiantes del programa y sus necesidades de formación de acuerdo con el proyecto educativo. | K7: A61. Estrategias orientadas a la actualización docente en temas relacionados con la atención a la diversidad poblacional. | P7: A82. Desempeño de los estudiantes del programa en las Pruebas de Estado de educación superior, en los últimos cinco años. Calificaciones promedio con respecto al promedio nacional. | Q7: A92. Movilidad estudiantil con otras instituciones nacionales e internacionales. | S7: A105. Estrategias pedagógicas, didácticas y comunicativas acordes con la metodología y con las posibilidades tecnológicas y las necesidades de los estudiantes en atención a su diversidad. | T7: A119. Criterios y procedimientos para la revisión de los sistemas de evaluación académica de los estudiantes. | W7: A134. Número y tipo de reconocimientos hechos en los últimos cinco años por entidades gubernamentales y no gubernamentales al impacto que el programa ha ejercido en los medios locales, regionales, nacionales o internacionales. | Z7: A153. Apreciación de profesores y estudiantes del programa sobre la capacidad, disponibilidad, dotación y utilización de laboratorios, talleres, ayudas audiovisuales y campos de práctica, entre otros recursos de apoyo docente. | AA7: A159. Inversión efectivamente realizada por la institución para los fines de internacionalización en los últimos cinco años. | AB7: A168. Resultados efectivos de la participación de profesores y estudiantes adscritos al Programa en actividades de cooperación académica. | AC7: A176. Actividad académica – pasantías, talleres, actividades conjuntas – relacionadas con la realidad empresarial, organizadas desde los primeros semestres con una lógica enfocada en el entendimiento creciente de aquella según sus mayores grados de complejidad. | AD7: A187. Publicaciones en revistas indexadas y especializadas nacionales e internacionales, innovaciones, patentes, productos o procesos técnicos y tecnológicos patentables o no patentables o protegidas por secreto industrial, libros, capítulos de libros, dirección de trabajos de grado de maestría y doctorado, paquetes tecnológicos, normas resultado de investigación, producción artística y cultural, productos de apropiación social del conocimiento, productos asociados a servicios técnicos o consultoría cualificada , elaborados por profesores adscritos al programa, de acuerdo con su tipo y naturaleza. | AE7: A195. Programas y estrategias de seguimiento integral a la comunidad institucional y acciones derivadas que conduzcan al desarrollo humano y el respeto a la diferencia. | AG7: A207. Apreciación del personal administrativo del programa sobre la claridad de las funciones encomendadas, sobre la articulación de sus tareas con las necesidades. | AH7: A214. Apreciación de directivos, profesores, estudiantes y personal administrativo sobre la eficacia de los sistemas de información académica y de los mecanismos de comunicación del Programa. | AJ7: A227. Evidencia de los procesos de análisis de la situación de los egresados. | AM7: A244. Apreciación de directivos y profesores adscritos al programa sobre la suficiencia de los recursos presupuestales de que se dispone en el mismo y sobre la ejecución presupuestal. | AY7: C13. Producción, pertinencia, utilización e impacto de material docente | BA7: C23. Resultados de aprendizaje | BG7: C46. Aseguramiento de la alta calidad y mejora continua
C8: A17. Cambios en el plan de estudios, resultantes de experiencias relativas al análisis y propuestas de solución a los problemas del contexto. | E8: A30. En los programas de salud, donde sea pertinente, evidenciar adecuadas rotaciones y entrenamiento médico. Los profesores-médicos que tienen a cargo los programas de docencia de servicio cuentan con el nivel de formación adecuado y la experiencia requerida. | J8: A54. Apreciación de directivos, profesores y estudiantes del programa adscritos directamente o a través de la Facultad o Departamento respectivo, sobre la calidad y la suficiencia del número y de la dedicación de los profesores al servicio de éste. | P8: A83. Valor agregado obtenido en los resultados de las Pruebas de Estado (Saber Pro), con relación a las Pruebas Saber Once utilizadas como mecanismo de ingreso a la educación superior y al desempeño de los estudiantes adscritos al programa. | Q8: A93. Existencia de sistemas de homologación de créditos y de tránsito del pregrado al postgrado. | S8: A106. Articulación entre las estrategias pedagógicas propias de la metodología de enseñanza y los recursos tecnológicos utilizados. | W8: A135. Mecanismos para el análisis de las acciones que el programa ejerce sobre el medio y para la revisión periódica de las estrategias implementadas en esa materia. | AA8: A160. Prospectos o iniciativas en curso de doble titulación con otras entidades, de acuerdo con el tipo y naturaleza del Programa. | AB8: A169. Participación de profesores adscritos al programa en redes académicas, científicas, técnicas y tecnológicas, económicas, a nivel nacional e internacional, de acuerdo con el tipo y modalidad del Programa. | AC8: A177. Existencia dentro del plan de estudios de espacios académicos y de vinculación con el sector productivo donde se analiza la naturaleza de la investigación científica, técnica y tecnológica, la innovación, sus objetos de indagación, sus problemas, oportunidades y sus resultados y soluciones. | AD8: A188. En el caso de las artes, el reconocimiento en libros de arte y revistas especializadas, la presentación, exposición o ejecución en instituciones de reconocido prestigio, la participación en eventos organizados por comunidades artísticas y académicas. En el caso de la literatura, la publicación por editoriales reconocidas en el ámbito literario e incluidas en antologías, entre otras. | AE8: A196. Investigación permanente de la problemática social del entorno que incide en la comunidad institucional. | AG8: A208. Apreciación de profesores y estudiantes adscritos al programa sobre la eficiencia, eficacia y orientación de los procesos administrativos hacia el desarrollo de las funciones misionales. | AH8: A215. Profesores, administrativos y estudiantes que confirman el acceso con calidad a los sistemas de comunicación e información mediados por las TIC. | AJ8: A228. Mecanismos y estrategias para efectuar ajustes al programa en atención a las necesidades del entorno, evidenciados a través del seguimiento de los egresados. | AM8: A245. Existencia de estudio de viabilidad financiera del programa, que incluya un plan básico de inversión orientado a la consolidación del Proyecto Educativo. | AY8: C14. Remuneración por méritos | BA8: C24. Competencias
C9: A18. Proyectos que adelanta el programa, mediante sus funciones de docencia, investigación, innovación, creación artística y cultural, y extensión tendientes a ejercer un impacto sobre el medio, de acuerdo con el Proyecto Educativo del Programa. | J9: A55. Existencia y utilización de sistemas y criterios para evaluar el número, la dedicación, el nivel de formación y la experiencia de los profesores del programa, adscritos directamente o a través de la Facultad o Departamento respectivo; periodicidad de esta evaluación; acciones adelantadas por la institución y el programa, a partir de los resultados de las evaluaciones realizadas en esta materia en los últimos cinco años. | P9: A84. Identificación en el perfil profesional y ocupacional de los distintos tipos de competencias, especialmente actitudes, conocimientos, capacidades y habilidades requeridas en el nivel de formación y las actividades académicas necesarias para su desarrollo. | Q9: A94. Convenios y relaciones de cooperación con Instituciones de Educación media y superior y con el sector laboral, para asegurar el tránsito y continuidad de los estudiantes en el sistema educativo y su inserción en el sistema productivo, de acuerdo con el tipo y modalidad del programa. | S9: A107. Estrategias y mecanismos pedagógicos aplicados y orientados hacia la integración de las tres funciones sustantivas de investigación, docencia y proyección social. | W9: A136. Información sobre las comunidades, empresas, gobiernos, instituciones, organizaciones de usuarios, y asociaciones a los que se presta asistencia técnica o tecnológica, servicios, asesorías y otros apoyos que apuntan a la resolución de problemas o a la ejecución de programas de mejoramiento, de acuerdo con la naturaleza y modalidad del programa. | AA9: A161. Incidencia verificable en el enriquecimiento de la calidad del Programa de la interacción con comunidades académicas nacionales e internacionales. | AB9: A170. Inversión efectiva desarrollada para proyectos de movilidad en doble vía en los últimos cinco años. | AC9: A178. Participación de los estudiantes en los programas institucionales de jóvenes investigadores. | AD9: A189. Apoyo administrativo y financiero para el desarrollo y gestión de la investigación, gestión del conocimiento (vigilancia tecnológica), la creación de empresas y de planes de negocio (como los centros de incubación y financiación empresarial, oficinas de transferencia de resultados de investigación, centros de investigación y desarrollo tecnológico, entre otros) proyectos de innovación en conjunto con empresas y la creación artística y cultural, de acuerdo con la naturaleza del programa. | AE9: A197. Estrategias que permitan a los estudiantes vincularse a redes de apoyo orientadas a contrarrestar las situaciones de vulnerabilidad. | AH9: A216. Existencia de estrategias que garanticen la conectividad a los miembros de la comunidad académica del Programa, de acuerdo con la modalidad en que éste es ofrecido. | AJ9: A229. Estrategias que faciliten el paso del estudiante al mundo laboral. | AM9: A246. Los planes de mejoramiento del programa se soportan en un presupuesto de apropiación programada. | AY9: C15. Evaluación de profesores | BA9: C25. Evaluación y autorregulación del programa académico
C10: A19. Estudios orientados a evaluar el impacto del programa con respecto al cumplimiento de sus propósitos y objetivos, así como la incidencia en el entorno social y su grupo de referencia disciplinar o profesional. | P10: A85. Articulación del plan de estudios con los diversos niveles de formación (periodos académicos, especialización, maestría y doctorado, componentes propedéuticos y/o ciclos, entre otros). | Q10: A95. Oferta académica que facilite la aplicación de criterios de flexibilidad con miras a garantizar la participación de los estudiantes, en el diseño de su propio plan académico, de acuerdo con sus intereses y la adquisición de, competencias, tales como actitudes, conocimientos, capacidades y habilidades, con el apoyo de un tutor o asesor. | S10: A108. Estudios realizados por la Institución y el programa para identificar y evaluar la permanencia y retención, de acuerdo con la metodología de enseñanza en que se ofrece el programa. | AA10: A162. Evidencias del impacto social que ha generado la inserción del Programa en los contextos académicos nacionales e internacionales, de acuerdo a su naturaleza. | AC10: A179. Participación de los estudiantes en prácticas empresariales en temas de investigación y desarrollo, ingeniería y experimentación en Colombia y en el extranjero. | AE10: A198. En los programas de salud, donde sea pertinente, evidenciar estrategias de bienestar adecuadas para los estudiantes en prácticas (lockers, camarotes, dormitorios) entre otros. | AH10: A217. Mecanismos de comunicación para facilitar que la población estudiantil en toda su diversidad tenga acceso a la información. | BA10: C26. Vinculación e interacción social
P11: A86. Aplicación de estrategias efectivas orientadas al desarrollo de competencias, especialmente conocimientos, capacidades y habilidades comunicativas en un segundo idioma extranjero. | Q11: A96. Acciones llevadas a cabo entre la Institución y otras instituciones del sector público o privado (educativo, productivo, financiero, entre otros) para articular y afirmar el carácter secuencial y complementario de los ciclos, desde el punto de vista académico y laboral, de acuerdo con el tipo y modalidad del programa. | S11: A109. Correlación entre la duración prevista para el programa, de acuerdo con su metodología y plan de estudios, y la que realmente tiene lugar. | AC11: A180. Participación de los estudiantes en proyectos Universidad Empresa Estado que adelante la Institución. | AZ11: C25. Recursos informáticos y de comunicación
S12: A110. Estrategias para garantizar el éxito académico de los estudiantes en el tiempo previsto para el desarrollo del plan de estudios, atendiendo los estándares de calidad. | AC12: A181. Participación de los estudiantes en programas de innovación tales como: transferencia de conocimiento, emprendimiento y creatividad. | AZ12: C26. Recursos de apoyo docente
S13: A111. Informes estadísticos sobre la población de estudiantes del programa desde el primero hasta el último semestre, en las últimas cinco cohortes.
S14: A112. Apreciación de profesores y estudiantes sobre la correspondencia entre las condiciones y exigencias académicas de permanencia y graduación en el programa, y la naturaleza del mismo.
S15: A113. Existencia de mecanismo de seguimiento, acompañamiento especial a estudiantes y adecuaciones locativas para facilitar el óptimo desempeño de admitidos en condición de vulnerabilidad y discapacidad, entre otros.

Sheet PERSONAL
B2: UNIVERSIDAD CESMAG
B3: VICERRECTORIA FINANCIERA Y DESARROLLO INSITUCIONAL
B4: FORMATO DE PROYECTOS ACTIVIADES PLAN DE MEJORAMIENTO
B6: PROGRAMA O DEPENDENCIA: | E6: Imputar a:
B7: =+PM!E7 -> 0 | E7: AÑO | F7: =+PM!D5 -> AÑO:
B8: NOMBRE: | C8: =+PM!D4 -> PLAN DE MEJORAMIENTO
B10: Personal Docente necesario para el desarrollo de las Actividades | J10: HORAS | K10: 6
B11: Son aquellos costos ocasionados por concepto de la relación laboral existente de conformidad con las disposiciones legales vigentes. Se presupuesta al personal docente contratado por medio tiempo y tiempo completo, que labora en la Universidad. y que se dedicaran en horas al desarrollo de las diferentes actividades del objetivo del plan de mejoramiento | J11: SEMANAS | K11: 4 | L11: =+K10*K11 -> 24 | M11: 192
J12: MES | L12: =+L11*K12 -> 0 | M12: =+M11/L11 -> 8
B14: Servicios Personales con cargo a la Nómina de la Institución
B15: ANEXO # Docentes Tiempo Completo | I15: TIEMPO | J15: 30 | L15: PRUEBA
B16: No. | C16: CONCEPTO | D16: Descripción del Rubro | E16: HORAS | F16: VR. UN. | G16: VR TOTAL | H16: CÓDIGO OBJETIVO | I16: SEMANAS | J16: MESES | K16: DÍAS | L16: No. DOCENTES | M16: H/semanales ASIGNADAS | N16: NÙMERO DE HORAS
B17: 1 | C17: Profesional Auxiliar | D17: Horas para desarrollar el documento | E17: 150 | F17: =IFERROR(VLOOKUP(C17,'2025'!$A$148:$B$161,2,0),0) -> 17790 | G17: =(E17*F17)*1.51852 -> 4052170.6 | H17: OPM_02 | I17: 4 | J17: =+I17/4 -> 1 | K17: =+J17*J15 -> 30 | L17: 5 | M17: 1 | N17: =+I17*L17*M17 -> 20 | O17: Este número de horas sería el que va en la casilla HORAS, del formato
B18: =+B17+1 -> 2 | D18: Horas de apoyo en los documentos | E18: 10 | F18: =IFERROR(VLOOKUP(C18,'2025'!$A$148:$B$161,2,0),0) -> 0 | G18: =(E18*F18)*1.51852 -> 0 | H18: OPM_01 | I18: 32 | J18: =+I18/4 -> 8 | K18: =+J18*J15 -> 240 | L18: 4 | M18: 2 | N18: =+I18*L18*M18 -> 256
B19: =+B18+1 -> 3 | E19: 200 | F19: =IFERROR(VLOOKUP(C19,'2025'!$A$148:$B$161,2,0),0) -> 0 | G19: =(E19*F19)*1.51852 -> 0 | H19: OPM_03 | I19: 16 | J19: =+I19/4 -> 4 | K19: =+J19*$J$15 -> 120 | L19: 2 | M19: 2 | N19: =+I19*L19*M19 -> 64
B20: =+B19+1 -> 4 | F20: =IFERROR(VLOOKUP(C20,'2025'!$A$148:$B$161,2,0),0) -> 0 | G20: =(E20*F20)*1.51852 -> 0 | H20: OPM_04
B21: =+B20+1 -> 5 | F21: =IFERROR(VLOOKUP(C21,'2025'!$A$148:$B$161,2,0),0) -> 0 | G21: =(E21*F21)*1.51852 -> 0 | H21: OPM_05
B22: =+B21+1 -> 6 | F22: =IFERROR(VLOOKUP(C22,'2025'!$A$148:$B$161,2,0),0) -> 0 | G22: =(E22*F22)*1.51852 -> 0 | H22: OPM_07
B23: =+B22+1 -> 7 | F23: =IFERROR(VLOOKUP(C23,'2025'!$A$148:$B$161,2,0),0) -> 0 | G23: =(E23*F23)*1.51852 -> 0
B24: =+B23+1 -> 8 | F24: =IFERROR(VLOOKUP(C24,'2025'!$A$148:$B$161,2,0),0) -> 0 | G24: =(E24*F24)*1.51852 -> 0
B25: =+B24+1 -> 9 | F25: =IFERROR(VLOOKUP(C25,'2025'!$A$148:$B$161,2,0),0) -> 0 | G25: =(E25*F25)*1.51852 -> 0
B26: =+B25+1 -> 10 | F26: =IFERROR(VLOOKUP(C26,'2025'!$A$148:$B$161,2,0),0) -> 0 | G26: =(E26*F26)*1.51852 -> 0
B27: =+B26+1 -> 11 | F27: =IFERROR(VLOOKUP(C27,'2025'!$A$148:$B$161,2,0),0) -> 0 | G27: =(E27*F27)*1.51852 -> 0
B28: =+B27+1 -> 12 | F28: =IFERROR(VLOOKUP(C28,'2025'!$A$148:$B$161,2,0),0) -> 0 | G28: =(E28*F28)*1.51852 -> 0
B29: =+B28+1 -> 13 | F29: =IFERROR(VLOOKUP(C29,'2025'!$A$148:$B$161,2,0),0) -> 0 | G29: =(E29*F29)*1.51852 -> 0
B30: =+B29+1 -> 14 | F30: =IFERROR(VLOOKUP(C30,'2025'!$A$148:$B$161,2,0),0) -> 0 | G30: =(E30*F30)*1.51852 -> 0
B31: =+B30+1 -> 15 | F31: =IFERROR(VLOOKUP(C31,'2025'!$A$148:$B$161,2,0),0) -> 0 | G31: =(E31*F31)*1.51852 -> 0
B32: =+B31+1 -> 16 | F32: =IFERROR(VLOOKUP(C32,'2025'!$A$148:$B$161,2,0),0) -> 0 | G32: =(E32*F32)*1.51852 -> 0
B33: =+B32+1 -> 17 | F33: =IFERROR(VLOOKUP(C33,'2025'!$A$148:$B$161,2,0),0) -> 0 | G33: =(E33*F33)*1.51852 -> 0
B34: =+B33+1 -> 18 | F34: =IFERROR(VLOOKUP(C34,'2025'!$A$148:$B$161,2,0),0) -> 0 | G34: =(E34*F34)*1.51852 -> 0
... B41: =+B40+1 -> 25 | F41: =IFERROR(VLOOKUP(C41,'2025'!$A$148:$B$161,2,0),0) -> 0 | G41: =(E41*F41)*1.51852 -> 0
C42: SUBTOTAL | G42: =SUM(G17:G41) -> 4052170.6
B44: ANEXO # Docentes Medio Tiempo
B45: No. | C45: CONCEPTO | D45: Descripción del Rubro | E45: HORAS | F45: VR. UN. | G45: VR TOTAL | H45: CÓDIGO OBJETIVO
B46: 1 | C46: Medio Tiempo Profesional | E46: 70 | F46: =IFERROR(VLOOKUP(C46,'2025'!$A$167:$B$170,2,0),0) -> 17510 | G46: =(E46*F46)*1.51852 -> 1861250 | H46: OPM_01
B47: =+B46+1 -> 2 | F47: =IFERROR(VLOOKUP(C47,'2025'!$A$167:$B$170,2,0),0) -> 0 | G47: =(E47*F47)*1.51852 -> 0 | H47: OPM_02
B48: =+B47+1 -> 3 | F48: =IFERROR(VLOOKUP(C48,'2025'!$A$167:$B$170,2,0),0) -> 0 | G48: =(E48*F48)*1.51852 -> 0 | H48: OPM_03
B49: =+B48+1 -> 4 | F49: =IFERROR(VLOOKUP(C49,'2025'!$A$167:$B$170,2,0),0) -> 0 | G49: =(E49*F49)*1.51852 -> 0 | H49: OPM_04
B50: =+B49+1 -> 5 | F50: =IFERROR(VLOOKUP(C50,'2025'!$A$167:$B$170,2,0),0) -> 0 | G50: =(E50*F50)*1.51852 -> 0
B51: =+B50+1 -> 6 | F51: =IFERROR(VLOOKUP(C51,'2025'!$A$167:$B$170,2,0),0) -> 0 | G51: =(E51*F51)*1.51852 -> 0
B52: =+B51+1 -> 7 | F52: =IFERROR(VLOOKUP(C52,'2025'!$A$167:$B$170,2,0),0) -> 0 | G52: =(E52*F52)*1.51852 -> 0
B53: =+B52+1 -> 8 | F53: =IFERROR(VLOOKUP(C53,'2025'!$A$167:$B$170,2,0),0) -> 0 | G53: =(E53*F53)*1.51852 -> 0
B54: =+B53+1 -> 9 | F54: =IFERROR(VLOOKUP(C54,'2025'!$A$167:$B$170,2,0),0) -> 0 | G54: =(E54*F54)*1.51852 -> 0
B55: =+B54+1 -> 10 | F55: =IFERROR(VLOOKUP(C55,'2025'!$A$167:$B$170,2,0),0) -> 0 | G55: =(E55*F55)*1.51852 -> 0
B56: =+B55+1 -> 11 | F56: =IFERROR(VLOOKUP(C56,'2025'!$A$167:$B$170,2,0),0) -> 0 | G56: =(E56*F56)*1.51852 -> 0
B57: =+B56+1 -> 12 | F57: =IFERROR(VLOOKUP(C57,'2025'!$A$167:$B$170,2,0),0) -> 0 | G57: =(E57*F57)*1.51852 -> 0 | N57: =SUM(N17:N56) -> 340
B58: =+B57+1 -> 13 | F58: =IFERROR(VLOOKUP(C58,'2025'!$A$167:$B$170,2,0),0) -> 0 | G58: =(E58*F58)*1.51852 -> 0
C59: SUBTOTAL | G59: =SUM(G46:G58) -> 1861250
B62: ANEXO # Otros Costos por Personal
B63: No. | C63: CONCEPTO | D63: UNIDAD | E63: HORAS | F63: VR. UN. | G63: VR TOTAL | H63: CÓDIGO OBJETIVO
B64: 1 | G64: =E64*F64 -> 0 | H64: OPM_01
B65: =+B64+1 -> 2 | G65: =E65*F65 -> 0 | H65: OPM_02
B66: =+B65+1 -> 3 | G66: =E66*F66 -> 0 | H66: OPM_03
B67: =+B66+1 -> 4 | G67: =E67*F67 -> 0 | H67: OPM_04
B68: =+B67+1 -> 5 | G68: =E68*F68 -> 0
B69: =+B68+1 -> 6 | G69: =E69*F69 -> 0
B70: =+B69+1 -> 7 | G70: =E70*F70 -> 0
B71: =+B70+1 -> 8 | G71: =E71*F71 -> 0
B72: =+B71+1 -> 9 | G72: =E72*F72 -> 0
B73: =+B72+1 -> 10 | G73: =E73*F73 -> 0
B74: =+B73+1 -> 11 | G74: =E74*F74 -> 0
B75: =+B74+1 -> 12 | G75: =E75*F75 -> 0
B76: =+B75+1 -> 13 | G76: =E76*F76 -> 0
B77: =+B76+1 -> 14 | G77: =E77*F77 -> 0
B78: =+B77+1 -> 15 | G78: =E78*F78 -> 0
B79: =+B78+1 -> 16 | G79: =E79*F79 -> 0
B80: =+B79+1 -> 17 | G80: =E80*F80 -> 0
C81: SUBTOTAL | G81: =SUM(G64:G80) -> 0
B83: ANEXO # Honorarios (Personal Externo)
B84: Hace referencia a los servicios profesionales que se requieren contratar para el desarrollo de una actividad que se considere calificada como: conferencistas, asesores, expertos, evaluadores, capacitadores, servicios de profesionales, etc.
B89: No. | C89: CONCEPTO | D89: UNIDAD | E89: HORAS | F89: VR. UN. | G89: VR TOTAL | H89: CÓDIGO OBJETIVO
B90: 1 | C90: Capacitación al personal Docente, Experto en el tema Psicoanálisis | D90: horas del capacitador | E90: 24 | F90: 80000 | G90: =E90*F90 -> 1920000 | H90: OPM_01
B91: =+B90+1 -> 2 | G91: =E91*F91 -> 0 | H91: OPM_02
B92: =+B91+1 -> 3 | G92: =E92*F92 -> 0 | H92: OPM_03
B93: =+B92+1 -> 4 | G93: =E93*F93 -> 0 | H93: OPM_04
B94: =+B93+1 -> 5 | G94: =E94*F94 -> 0
B95: =+B94+1 -> 6 | G95: =E95*F95 -> 0
B96: =+B95+1 -> 7 | G96: =E96*F96 -> 0
B97: =+B96+1 -> 8 | G97: =E97*F97 -> 0
B98: =+B97+1 -> 9 | G98: =E98*F98 -> 0
B99: =+B98+1 -> 10 | G99: =E99*F99 -> 0
B100: =+B99+1 -> 11 | G100: =E100*F100 -> 0
B101: =+B100+1 -> 12 | G101: =E101*F101 -> 0
B102: =+B101+1 -> 13 | G102: =E102*F102 -> 0
B103: =+B102+1 -> 14 | G103: =E103*F103 -> 0
B104: =+B103+1 -> 15 | G104: =E104*F104 -> 0
C105: SUBTOTAL | G105: =SUM(G90:G104) -> 1920000
D108: TOTAL | E108: =+G42+G59+G81+G105 -> 7833420.6

Sheet TIPO
A1: UNIVERSIDAD CESMAG
A2: TIPIFICACION DE PROYECTOS
A4: TIPO | B4: DESCRIPCIÓN | C4: GOBERNANZA | D4: EVANGELIZACIÓN DE LAS CULTURAS | E4: DESARROLLO INSTITUCIONAL | F4: DOCENCIA | G4: INVESTIGACIÓN | H4: PROYECCIÓN SOCIAL | I4: BIENESTAR UNIVERSITARIO | J4: PROCESOS ADMINISTRATIVOS DE APOYO
A5: ACTIVIDAD | B5: Son acciones que se desarrollan por una persona o un grupo de personas de manera cotidiana, como parte de una función asignada en cumplimiento del quehacer académico. | C5: Cursos Elección de representantes a los cuerpos colegiados Seguimiento al normograma institucional Auditorías internas de calidad Control de salidas no conformes | D5: Retiros espirituales Convivencias Encuentros religiosos Encuentros espirituales y convivencias Misiones Diálogos Laboratorios de Paz | F5: Muestras Académicas Seminarios Encuentros Actividades didácticas (celebración día del idioma) Talleres Inducción a estudiantes Planeación académica Inducción y planeación curricular Salidas no conformes Desarrollo de convenios Pasantías | G5: Convocatorias de investigación Desarrollo de convenios | H5: Brigadas Encuentros Actividades lúdicas Campañas Desarrollo de convenios | I5: Conformación y participación en encuentros, campeonatos … deportivo Conformación y participación de encuentros culturales y artísticos Bienvenida a estudiantes Conmemoraciones Mentorías Asesorías Tutorías Orientación vocacional Caracterización de estudiantes | J5: Actividades de SST Encuentros Actividades lúdicas para funcionarios Convocatorias para personal Promoción y prevención médica, odontológica y salud mental
A6: EVENTO | B6: Es un suceso programado, con la utilización de recursos humanos, materiales, técnicos, y financieros con un costo determinado, que queda a cargo de una unidad académica o administrativa. Los eventos pueden ser: académicos, culturales, deportivos, recreativos e institucionales, loso cuales requieren preparación y deben comunicarse oportunamente a la sociedad o al sector al que se dirigen. | C6: Cursos Diplomados | D6: Cursos Diplomados Círculos literarios y culturales Espacios de diálogo intercultural | F6: Seminarios Talleres Diplomados Foros Congresos Cursos especiales Cursos cortos Acompañamiento académico disciplinar Acompañamiento para la graduación exitosa Desarrollo de convenios | G6: Publicación de productos Ponencias Convocatorias externas de investigación Publicación de productos de investigación Desarrollo de convenios | H6: Seminarios Talleres Diplomados Cursos especiales Cursos cortos Prácticas formativas Desarrollo de convenios | I6: Festival de Danzas Encuentros deportivos | J6: Seminarios Talleres Diplomados Foros Congresos Cursos especiales Cursos cortos Eventos deportivos
A7: ESTRATEGIA | B7: Estrategias: conjunto de acciones encaminadas a lograr el cumplimiento de indicadores institucionales | C7: Actualización PEI Formulación de planes de gestión Formulación de planes de acción | D7: Integración de la escuela de humanidades en los espacios académicos de los programas | E7: Asesorías recibidas | F7: Actualización PEP, PED Estudio del arte de los programas académicos Implementación de TIC en los espacios académicos Integración de las ciencias básicas en los microcurrículos de los programas Gestión de la internacionalización Formación, capacitación y actualización docente Movilidad Estudiantil Movilidad Docente | G7: Gestión de planes de mejoramiento en investigación Evaluación del impacto de la innovación | H7: Encuentros con egresados Bolsa de empleo | I7: Acciones de acompañamiento para la permanencia de estudiantes | J7: Autoevaluación de programas Autoevalaución institucional Plan de compras Plan de comunicaciones
A8: PROYECTO | B8: Es el conjunto de actividades interrelacionadas que se desarrollan de manera coordinada por una persona o grupo de personas para alcanzar un objetivo Un proyecto tiene unas características específicas, como son: - Manejo de una metodología clara y definida, que permite dividir el proyecto en fases, que contienen un objetivo, tiempo de ejecución, recursos limitados y cada fase debe tener un resultado que se pueda evaluar o comprobar. - Tener un cronograma de actividades. - Contener resultados esenciales | D8: Diplomados | E8: Proyectos institucionales Proyectos sociales institucionales | F8: Apertura de programas nuevos | H8: Proyectos sociales de programa
A9: PROYECTO ESPECIAL | B9: Son los proyectros en los que siempre convergen las tres funciones sustantivas: docencia, investigación y proyección social. | F9: Desarrollo de la investigación formativa Integración de la docencia, la investigación y la proyección social
A10: PROYECTO DE INVERSIÓN | B10: Proyecto de inversión, es una propuesta de acción que a partir de gastos de activos líquidos se tiene el propósito de generar u obtener beneficios económicos. | H10: Educación continua
A11: PROYECTO ESTRATÉGICO | B11: Conjunto de actividades que tiene como propósito, ampliar la capacidad de la prestación del servicio de educación superior, y que contribuye de una manera particularmente significativa para el logro de los objetivos institucionales, dentro del marco de su propia estrategia. | C11: Implementación de sistemas Modernización de la estructura orgánica Certificaciones por organismos nacionales e internacionales Acreditación de alta calidad de programas Acreditación de alta calidad institucional Estudios del contexto Estudios de la satisfacción del cliente | E11: Programas para ETDH (Educación para el trabajo y desarrollo humano) Programas de Educación continuada Desarrollo, dotación y mejoramiento de la planta física Desarrollo, dotación y mejoramiento de la infraestructura tecnológica Desarrollo, dotación y mejoramiento de bienes muebles Programas virtuales Unidad de Correspondencia - Ventanilla Única Extensión de programas académicos | F11: Renovación de Registro Calificado Proyecto Pedagógico Interdisciplinario Flexibilidad curricular Formación Programas para ETDH (Educación para el trabajo y desarrollo humano) Integración de la docencia, la investigación y la proyección social Gestión de la internacionalización Acreditación de alta calidad de programas Construcción y actualización del Proyecto Educativo de Posgrados Proyectos de Educación no Formal Estudios de impacto de los egresados Desarrollo de la educación virtual Estudio de relevancia académica y pertinencia social de los programas Diversificación de la oferta académica | G11: Desarrollo grupos de investigación Productos de investigación Formación docente en investigación Investigación científica Integración de la docencia, la investigación y la proyección social | H11: Integración de la docencia, la investigación y la proyección social Estudios de egresados | I11: Proyectos para fortalecer la permanencia de estudiantes

Sheet PROGRAMAS Y DEPENDENCIAS
A1: UNIVERSIDAD CESMAG
A2: RELACION DE PROGRAMAS Y DEPENDENCIAS DE LA UNIVERSIDAD
A4: C.C. | B4: SUB.C.C. | C4: DESCRIPCION | D4: C.C.
A5: 30100 | B5: 1 | C5: ACOMPAÑAMIENTO INTEGRAL | D5: 30100
A6: 30303 | B6: 1 | C6: AGRUPACIONES ARTISTICAS | D6: 30303
A7: 5015 | B7: 3 | C7: ARCHIVO Y CORRESPONDENCIA | D7: 5015
A8: 5012 | B8: 1 | C8: AUDITORIA INTERNA | D8: 5012
A9: 30700 | B9: 1 | C9: CAPELLANÍA Y ACOMPAÑAMIENTO ESPIRITUAL | D9: 30700
A10: 11730 | B10: 1 | C10: CENTRO DE CONCILIACION Y CONSULTORIOS JURIDICOS | D10: 11730
A11: 30104 | B11: 1 | C11: CENTRO DE ESTIMULACIÓN INFANTIL | D11: 30104
A12: 1012 | B12: 1 | C12: CENTRO DE IDIOMAS | D12: 1012
A13: 11720 | B13: 1 | C13: CENTRO DE INVESTIGACION SOCIOJURIDICO | D13: 11720
A14: 1015 | B14: 1 | C14: CENTRO DE RECURSOS EDUCATIVOS | D14: 1015
A15: 30302 | B15: 1 | C15: DEPORTE COMPETITIVO | D15: 30302
A16: 30301 | B16: 1 | C16: DEPORTE FORMATIVO | D16: 30301
... A95: 3010 | B95: 1 | C95: VICERRECTORIA PARA EVANGELIZACIÓN DE LAS CULTURAS | D95: 3010

Sheet PROYECTOS PDI
A1: Código Proyecto | B1: Centro de Costo Contabilidad | C1: No. | D1: EJES | E1: Reto | F1: Código Objetivo | G1: Objetivo Estratégico | H1: Código Proyecto | I1: Proyecto | J1: Proceso Responsable | K1: Meta | L1: Indicador | M1: Numerador | N1: Denominador | O1: Resultado | P1: Meta 2018 | Q1: Porcentaje de Avance | R1: Observaciones
A2: RI-2-3 | B2: 7001 | C2: 1 | D2: AUTOEVALUACIÓN Y ACREDITACIÓN | E2: RI-2 | F2: OE-1 | G2: Articular un modelo de autoevaluación que permitan el desarrollo institución desde el concepto de la mejora continua en lo referente a calidad académica. | H2: RI-2-3 | I2: Articular un modelo de autoevaluación que permitan el desarrollo institución desde el concepto de la mejora continua en lo referente a calidad académica. | J2: Gestión de la Calidad | K2: A 2021 tener acreditado un programa de pregrado y/o posgrado por cada Facultad. | L2: Número de programas de pregrado y posgrado acreditados en alta calidad. | N2: N/A | O2: No aplica para el periodo | P2: 0 | Q2: =IFERROR(O2/P2,"")
A3: RI-4-1 | B3: 7002 | C3: 2 | D3: AUTOEVALUACIÓN Y ACREDITACIÓN | E3: RI-4 | F3: OE-2 | G3: Ofrecer programas académicos pertinentes y con altos niveles de calidad. | H3: RI-4-1 | I3: Actualización de los PEP en coherencia con el PEI, Misión y Visión Institucionales y carácter institucional. | J3: Gestión de la Docencia | K3: 100% de los PEP actualizados y socializados con la comunidad académica. (Base Año 2016-II). | L3: Números de PEP actualizados y socializados / Número de programas activos | M3: 12 | N3: 13 | O3: =IFERROR(IF(N3="N/A",M3,(M3/N3)),"") -> 0.92307692 | P3: 0.8 | Q3: =IFERROR(O3/P3,"") -> 1.1538462
A4: RI-4-7 | B4: 7003 | C4: 3 | D4: DOCENCIA | E4: RI-4 | F4: OE-4 | G4: Actualizar la oferta de programas académicos en pregrado y posgrado para responder con pertinencia a las necesidades de la región y las tendencias del sector educativo. | H4: RI-4-7 | I4: Identificar el estado de arte de las profesiones y programas académicos a nivel nacional, local e internacional. | J4: Gestión de la Docencia | K4: 100% programas académicos con estudio del estado del arte de su profesión a nivel local, nacional e internacional. | L4: Número de programas académicos con estudio de estado del arte de su profesión a nivel local y nacional/ Número total de programas activos | M4: 12 | N4: 13 | O4: =IFERROR(IF(N4="N/A",M4,(M4/N4)),"") -> 0.92307692 | P4: 0.5 | Q4: =IFERROR(O4/P4,"") -> 1.8461538
A5: RI-6-27 | B5: 7004 | C5: 3 | D5: DOCENCIA | E5: RI-6 | F5: OE-4 | G5: Actualizar la oferta de programas académicos en pregrado y posgrado para responder con pertinencia a las necesidades de la región y las tendencias del sector educativo. | H5: RI-6-27 | I5: Obtener el registro calificado de nuevos programas académicos en la sede principal y extensiones, y renovar los registros calificados de los programas existentes. | J5: Gestión de la Docencia | K5: Incrementar progresivamente la oferta académica a nivel de pregrado acorde con las capacidades institucionales | L5: Número de programas activos | M5: 13 | N5: N/A | O5: =IFERROR(IF(N5="N/A",M5,(M5/N5)),"") -> 13 | P5: 13 | Q5: =IFERROR(O5/P5,"") -> 1
A6: RI-6-28 | B6: 7005 | C6: 3 | D6: DOCENCIA | E6: RI-6 | F6: OE-4 | G6: Actualizar la oferta de programas académicos en pregrado y posgrado para responder con pertinencia a las necesidades de la región y las tendencias del sector educativo. | H6: RI-6-28 | I6: Crear y ofrecer programas de postgrado a nivel de especializaciones propias y maestrías en convenio. | J6: Gestión de la Docencia | K6: Incrementar progresivamente la oferta académica a nivel de posgrado acorde con las capacidades institucionales. | L6: Número total de Posgrados propios | M6: 1 | N6: N/A | O6: =IFERROR(IF(N6="N/A",M6,(M6/N6)),"") -> 1 | P6: 3 | Q6: =IFERROR(O6/P6,"") -> 0.33333333
A7: RI-6-29 | B7: 7006 | C7: 3 | D7: DOCENCIA | E7: RI-6 | F7: OE-4 | G7: Actualizar la oferta de programas académicos en pregrado y posgrado para responder con pertinencia a las necesidades de la región y las tendencias del sector educativo. | H7: RI-6-29 | I7: Implementar las tecnologías de información y comunicación en los programas académicos y de extensión que ofrece la IU CESMAG, como apoyo a la presencialidad en el proceso enseñanza – aprendizaje. | J7: Gestión de la Docencia | K7: Incrementar anualmente en un 10% el número de profesores que integran apoyo virtual en sus espacios académicos. (Base Año 2017) | L7: Número de profesores (acumulado) que han integrado apoyo virtual en el desarrollo de sus espacios académico/ Número total de profesores | M7: 148 | N7: 499 | O7: =IFERROR(IF(N7="N/A",M7,(M7/N7)),"") -> 0.29659319 | P7: 0.1 | Q7: =IFERROR(O7/P7,"") -> 2.9659319
A8: RI-4-2 | B8: 7007 | C8: 4 | D8: DOCENCIA | E8: RI-4 | F8: OE-5 | G8: Consolidar del modelo pedagógico y la articulación exitosa de estrategias interdisplinares, prácticas didacticas innovadoras y la evaluación periódica del equipo docente. | H8: RI-4-2 | I8: Consolidar la articulación del Proyecto Pedagógico Interdisciplinario que posibilite su aplicación desde el PEP hasta el impacto en los microcurrículos de los programas. | J8: Gestión de la Docencia | K8: 80% de PEP actualizados con estrategias para la implementación del Proyecto Pedagógico Interdisciplinario de acuerdo a las particularidades del programa. | L8: Número de PEP con implementación del proyecto pedagógico interdisciplinario / Número de programas activos | M8: 8 | N8: 13 | O8: =IFERROR(IF(N8="N/A",M8,(M8/N8)),"") -> 0.61538462 | P8: 0.6 | Q8: =IFERROR(O8/P8,"") -> 1.025641
A9: RI-4-4 | B9: 7008 | C9: 4 | D9: DOCENCIA | E9: RI-4 | F9: OE-5 | G9: Consolidar del modelo pedagógico y la articulación exitosa de estrategias interdisplinares, prácticas didacticas innovadoras y la evaluación periódica del equipo docente. | H9: RI-4-4 | I9: Articular adecuadamente la departamentamentalización de las Ciencias Básicas y su impacto en los PEP y microcurrículos de los programas para beneficiar la flexibilidad curricular. | J9: Gestión de la Docencia | K9: 100% de los PEP actualizados en los componentes de Ciencias Básicas con el enfoque de departamentalización. | L9: Número de PEP que están actualizados en el componente de Ciencias Básicas / Número de programas activos | M9: 6 | N9: 13 | O9: =IFERROR(IF(N9="N/A",M9,(M9/N9)),"") -> 0.46153846 | P9: 0.7 | Q9: =IFERROR(O9/P9,"") -> 0.65934066
A10: RI-4-6 | B10: 7009 | C10: 4 | D10: DOCENCIA | E10: RI-4 | F10: OE-5 | G10: Consolidar del modelo pedagógico y la articulación exitosa de estrategias interdisplinares, prácticas didacticas innovadoras y la evaluación periódica del equipo docente. | H10: RI-4-6 | I10: Articulación del sistema de evaluación de desempeño docente con alcance a los conceptos de autoevaluación, coevaluación y heteroevaluación. | J10: Gestión de la Docencia | K10: Incrementar anualmente en un 1% el número de profesores TC con calificaciones promedio superiores a 4,0 | L10: Número de docentes tiempo completo con calificación igual o superior a 4.0. / Número de docentes TC | M10: Pendiente informacion por parte Desatrollo Software | N10: 420 | O10: =IFERROR(IF(N10="N/A",M10,(M10/N10)),"") | P10: 0.93 | Q10: =IFERROR(O10/P10,"")
A11: RI-4-5 | B11: 7010 | C11: 5 | D11: DOCENCIA | E11: RI-4 | F11: OE-6 | G11: Promover a los integrantes de la planta profesoral en las diferentes categorías del escalafón, mediante estrategias de permanencia, cualificación y actualización profesional y el manejo de segunda lengua. | H11: RI-4-5 | I11: Fortalecimiento de las competencias académicas, profesionales, investigativas y de segunda lengua, de los profesores. | J11: Gestión de la Docencia | K11: Logran una movilidad anual del 10% de los profesores TC y MT hacia niveles superiores del escalafón. | L11: Número de docentes TC y MT promovidos en el año 2018 en los diferentes niveles de escalafón / Número Total de Docentes TC y MT | M11: 18 | N11: 476 | O11: =IFERROR(IF(N11="N/A",M11,(M11/N11)),"") -> 0.037815126 | P11: 0.1 | Q11: =IFERROR(O11/P11,"") -> 0.37815126
A12: RI-4-10 | B12: 7011 | C12: 5 | D12: DOCENCIA | E12: RI-4 | F12: OE-6 | G12: Promover a los integrantes de la planta profesoral en las diferentes categorías del escalafón, mediante estrategias de permanencia, cualificación y actualización profesional y el manejo de segunda lengua. | H12: RI-4-10 | I12: Mejoramiento de la formación de profesores a nivel de maestrías y doctorados de los profesores. | J12: Gestión de la Docencia | K12: Lograr un 70% de la comunidad de profesores (TC y MT) con nivel de formación en grados de maestría y doctorado. | L12: Número de profesores (TC y MT) con nivel de formación en grados de maestría y doctorado./ Total de Profesores TC y MT | M12: 143 | N12: 265 | O12: =IFERROR(IF(N12="N/A",M12,(M12/N12)),"") -> 0.53962264 | P12: 0.55 | Q12: =IFERROR(O12/P12,"") -> 0.98113208
A13: RI-5-9 | B13: 7012 | C13: 6 | D13: INVESTIGACIÓN | E13: RI-5 | F13: OE-14 | G13: Fomentar el mejoramiento continuo en la gestión de investigación. | H13: RI-5-9 | I13: Gestionar la mejora continua de la investigación institucional en todos los programas académicos. | J13: Gestión de la Investigación | K13: 100% de Planes de mejoramiento de los programas gestionados en lo aspectos correspondientes a la investigación. | L13: Número de planes de mejoramiento gestionados en los correspondiente a investigacion/ Número total de planes de mejoramiento con alcance a investigación | O13: =IFERROR(IF(N13="N/A",M13,(M13/N13)),"") | P13: 1 | Q13: =IFERROR(O13/P13,"")
A14: RI-5-13 | B14: 7013 | C14: 7 | D14: INVESTIGACIÓN | E14: RI-5 | F14: OE-15 | G14: Promover la investigación formativa en todos los programas con la participación activa de la comunidad académica. | H14: RI-5-13 | I14: Fortalecer investigación formativa realizada en los semilleros de estudiantes investigadores. | J14: Gestión de la Investigación | K14: Incrementar anualmente en un 2% la participación de estudiantes en los semilleros de investigación. | L14: Número de participantes semilleros de investigación periodo P / Número de participantes semilleros de investigación periodo P-1 | M14: Ya envian informacion | O14: =IFERROR(IF(N14="N/A",M14,(M14/N14)),"") | P14: 0.02 | Q14: =IFERROR(O14/P14,"")
A15: RI-5-14 | B15: 7014 | C15: 7 | D15: INVESTIGACIÓN | E15: RI-5 | F15: OE-15 | G15: Promover la investigación formativa en todos los programas con la participación activa de la comunidad académica. | H15: RI-5-14 | I15: Impulsar el desarrollo de la investigación formativa con la participación de docentes y estudiantes, egresados, administrativos y sector externo. | J15: Gestión de la Investigación | K15: Incrementar anualmente en un 2% la participación de estudiantes y profesores en eventos e iniciativas que promuevan la investigación a nivel formativo. | L15: Número de participantes en eventos e iniciativas que promuevan la investigación a nivel formativo periodo P / Número de participantes en eventos e iniciativas que promuevan la investigación a nivel formativo periodo P-1 | M15: 108 | N15: 0 | O15: =IFERROR(IF(N15="N/A",M15,(M15/N15)),"") | P15: 0.02 | Q15: =IFERROR(O15/P15,"")
A16: RI-5-8 | B16: 7015 | C16: 8 | D16: INVESTIGACIÓN | E16: RI-5 | F16: OE-16 | G16: Promover la producción investigativa de calidad en los diferentes campos del saber complados por el Sistema de Investigaciones | H16: RI-5-8 | I16: Crear y consolidar grupos de investigación de la Institución. | J16: Gestión de la Investigación | K16: Tener a 2021 el 80% de los grupos de investigación clasificados en SNCTI. | L16: Número de grupos de investigación clasificados / Número de grupos de investigación de la Institución | M16: 14 | N16: 20 | O16: =IFERROR(IF(N16="N/A",M16,(M16/N16)),"") -> 0.7 | P16: 0.8 | Q16: =IFERROR(O16/P16,"") -> 0.875 | R16: Proyecto OE-7 y RI-8-31
A17: RI-5-11 | B17: 7016 | C17: 8 | D17: INVESTIGACIÓN | E17: RI-5 | F17: OE-16 | G17: Promover la producción investigativa de calidad en los diferentes campos del saber complados por el Sistema de Investigaciones | H17: RI-5-11 | I17: Fortalecer los procesos de publicación de la producción investigativa de acuerdo a los criterios de evaluación del SNCTI. | J17: Gestión de la Investigación | K17: Alcanzar al 2021 una producción acumulada de 981 productos de investigación y desarrollo tecnológico: • 209 Productos por año de formación de recurso humano para CTeI | L17: Número acumulado de productos por año de formación de recurso humano para CTeI | M17: 445 | N17: N/A | O17: =IFERROR(IF(N17="N/A",M17,(M17/N17)),"") -> 445 | P17: 209 | Q17: =IFERROR(O17/P17,"") -> 2.1291866
A18: RI-5-12 | B18: 7017 | C18: 8 | D18: INVESTIGACIÓN | E18: RI-5 | F18: OE-16 | G18: Promover la producción investigativa de calidad en los diferentes campos del saber complados por el Sistema de Investigaciones | H18: RI-5-12 | I18: Fortalecer la cultura investigativa en la comunidad académica. | J18: Gestión de la Investigación | K18: Incrementar anualmente en un 2% la participación de docentes, estudiantes, directivos, administrativos y egresados en iniciativas que promuevan la investigación científica. | L18: Número de participantes en iniciativas que promuevan la investigación científica periodo P / Número de participantes en iniciativas que promuevan la investigación científica periodo P-1 | M18: No se tiene información | O18: =IFERROR(IF(N18="N/A",M18,(M18/N18)),"") | P18: 0.02 | Q18: =IFERROR(O18/P18,"")
A19: RI-7-16 | B19: 7018 | C19: 9 | D19: PROYECCIÓN SOCIAL Y EXTENSIÓN | E19: RI-7 | F19: OE-17 | G19: Desarrollar un portafolio de servicios de asesoría, consultoría, capacitación y desarrollo de proyectos de extensión al servicio de la comunidad académica y sector externo. | H19: RI-7-16 | I19: Prestar servicios de asesoría, consultoría, capacitación formulación y desarrollo de propuestas, programas y proyectos, acordes a las diferentes disciplinas que ofrece la Institución tendientes a mejorar condiciones económicas, sociales culturales y ambientales con programas especiales y aplicación de TIC, y la interacción de los docentes y estudiantes de los diferentes programas académicos. | J19: Gestión de la Proyección Institucional | K19: Incrementar progresivamente la contribución al ingreso institucional desde los servicios de educación continua, convenios y extensión. | L19: Porcentaje de ingresos de servicios de educación continua, convenios y extensión P./ Porcentaje de ingresos de servicios de educación continua, convenios y extensión. P-1 | M19: 943308194 | N19: 2324936452 | O19: =IFERROR(IF(N19="N/A",M19,(M19/N19)),"") -> 0.40573504 | P19: 0.05 | Q19: =IFERROR(O19/P19,"") -> 8.1147009
A20: RI-7-30 | B20: 7019 | C20: 9 | D20: PROYECCIÓN SOCIAL Y EXTENSIÓN | E20: RI-7 | F20: OE-17 | G20: Desarrollar un portafolio de servicios de asesoría, consultoría, capacitación y desarrollo de proyectos de extensión al servicio de la comunidad académica y sector externo. | H20: RI-7-30 | I20: Ofrecer y desarrollar programas de formación laboral o académica a la comunidad mediante el Instituto para el Trabajo y Desarrollo Humano de la Institución. | J20: Gestión de la Docencia | K20: Programas ofrecidos en modalidad ETDH (Eduación para al Trabajo y el Desarrollo Humano) | L20: Número de Programas ofrecidos en modalidad ETDH (Eduación para al Trabajo y el Desarrollo Humano) | O20: =IFERROR(IF(N20="N/A",M20,(M20/N20)),"") | P20: 0 | Q20: =IFERROR(O20/P20,"")
A21: RI-11-18 | B21: 7020 | C21: 10 | D21: PROYECCIÓN SOCIAL Y EXTENSIÓN | E21: RI-11 | F21: OE-18 | G21: Fortalecer lazos de vinculación institucional con comunidades externas en el desarrollo de las funciones sustantivas y el desarrollo de tejido social en la región. | H21: RI-11-18 | I21: Fortalecimiento del compromiso social, contribución activa y voluntaria al mejoramiento de la calidad de vida de las comunidades, generando espacios propicios para su desarrollo económico, social y ambiental. | J21: Gestión de la Proyección Institucional | K21: 100% de programas con espacios académicos que articulen iniciativas de proyección e impacto social. | L21: Números de programas que articulen espacios academicos de proyección e impacto social/ Número total de Programas activos | N21: 13 | O21: =IFERROR(IF(N21="N/A",M21,(M21/N21)),"") -> 0 | P21: 0.7 | Q21: =IFERROR(O21/P21,"") -> 0
A22: RI-11-17 | B22: 7021 | C22: 11 | D22: PROYECCIÓN SOCIAL Y EXTENSIÓN | E22: RI-11 | F22: OE-19 | G22: Fortalecer lazos de vinculación institucional con los egresados en el desarrollo de las funciones sustantivas y fortalecimiento del bienestar institucional. | H22: RI-11-17 | I22: Fortalecer la Asociación General de Egresados I.U. CESMAG para mantener vínculos académicos y sociales con los egresados posibilitando su sostenibilidad. | J22: Gestión de la Proyección Institucional | K22: Incrementar anualmente en un 10% la participación de egresados en la vida institucional con articulación de la ASEIUC. (Base 2016) | L22: Número de egresados participantes en actividades institucionales P./ Numero total de egresados P-1. | M22: 1315 | N22: 13262 | O22: =IFERROR(IF(N22="N/A",M22,(M22/N22)),"") -> 0.099155482 | P22: 0.1 | Q22: =IFERROR(O22/P22,"") -> 0.99155482
A23: RI-11-19 | B23: 7022 | C23: 11 | D23: PROYECCIÓN SOCIAL Y EXTENSIÓN | E23: RI-11 | F23: OE-19 | G23: Fortalecer lazos de vinculación institucional con los egresados en el desarrollo de las funciones sustantivas y fortalecimiento del bienestar institucional. | H23: RI-11-19 | I23: Caracterización e impacto del egresado en el medio. | J23: Gestión de la Proyección Institucional | K23: Actualización periódica del estudio de caracterización e impacto de los egresados en el medio. | L23: Números programas con estudio actualizado de caracterización e impacto de los egresados en el medio P. / Números programas activos | M23: 12 | N23: 13 | O23: =IFERROR(IF(N23="N/A",M23,(M23/N23)),"") -> 0.92307692 | P23: 1 | Q23: =IFERROR(O23/P23,"") -> 0.92307692
A24: RI-11-20 | B24: 7023 | C24: 11 | D24: PROYECCIÓN SOCIAL Y EXTENSIÓN | E24: RI-11 | F24: OE-19 | G24: Fortalecer lazos de vinculación institucional con los egresados en el desarrollo de las funciones sustantivas y fortalecimiento del bienestar institucional. | H24: RI-11-20 | I24: Alistamiento y preparación para la empleabilidad y emprendimiento. | J24: Gestión de la Proyección Institucional | K24: Incrementar anualmente en un 5% la participación de estudiantes de últimos semestres y egresados en procesos de selección por Bolsa de Empleo y en actividades de orientación profesional y emprendimiento. | L24: Número de estudiantes de último semestre y egresados participaron en proceso de selección por Bolsa de Empleo P./ Número de estudiantes de último semestre y egresados participaron en proceso de selección por Bolsa de Empleo P-1. | M24: No se tiene información | O24: =IFERROR(IF(N24="N/A",M24,(M24/N24)),"") | P24: 0.05 | Q24: =IFERROR(O24/P24,"")
A25: RI-11-36 | B25: 7024 | C25: 12 | D25: IDENTIDAD INSTITUCIONAL | E25: RI-11 | F25: OE-9 | G25: Articular la acción evangelizadora con las funciones sustantivas de la educación promoviendo la identidad franciscana y capuchina a través de espacios de reflexión y participación para contribuir al desarrollo humano de las personas que integran la comunidad académica. | H25: RI-11-36 | I25: Implementar el sistema de evangelización para las culturas con cobertura a todos los estamentos de la comunidad académica bajo los preceptos de la espiritualidad fransicana y capuchina. | J25: Gestión para la Evangelización de las Culturas | K25: Incrementar un 10% la participación de la comunidad académica en los procesos y actividades de evangelización. | L25: Número de participantes en los procesos y actividades de evangelizaciòn periodo P / Número de participantes en los procesos y actividades de evangelizaciòn periodo P-1 | M25: 259 | N25: 1362 | O25: =IFERROR(IF(N25="N/A",M25,(M25/N25)-1),"") -> -0.80983847 | P25: 0.1 | Q25: =IFERROR(O25/P25,"") -> -8.0983847
A26: RI-1-21 | B26: 7025 | C26: 13 | D26: IDENTIDAD INSTITUCIONAL | E26: RI-1 | F26: OE-10 | G26: Fortalecer la gestión de las comunicaciones en todos los niveles de la Institución para un adecuado manejo reputacional y preparar la transición de marca en el reconocimiento como universidad. | H26: RI-1-21 | I26: Unificar el departamento de Comunicaciones, publicidad y mercadeo como responsable de la gestión integral de las comunicaciones en cumplimiento de las políticas institucionales. | J26: Gestión de la Comunicación | K26: Ejecución del 100% de estrategias comunicacionales orientadas a gestionar la reputación de la Institutición con todos los grupos de interés. | L26: Número de estrategias ejecutadas a gestionar la reputación de la Institución / Número de estrategias planteadas | M26: 6 | N26: 6 | O26: =IFERROR(IF(N26="N/A",M26,(M26/N26)),"") -> 1 | P26: 1 | Q26: =IFERROR(O26/P26,"") -> 1
A27: RI-12-15 | B27: 7026 | C27: 14 | D27: INTERNACIONALIZACIÓN | E27: RI-12 | F27: OE-13 | G27: Fortalecer la internacionalización en las funciones sustantivas para promover la inserción y visibilidad de la institución en contextos internacionales. | H27: RI-12-15 | I27: Fortalecimiento de la internacionalización para promover la visibilidad nacional e internacional desde la participación dinámicae en procesos nacionales e internacionales de intercambio de conocimiento, experiencias prácticas y la formación cultural. | J27: Gestión de la Proyección Institucional | K27: 100% de programas con resultados visibles de internacionalización. | L27: Número de programas con resultados visibles de internacionalización/ Número total de Programas activos. | M27: 9 | N27: 13 | O27: =IFERROR(IF(N27="N/A",M27,(M27/N27)),"") -> 0.69230769 | P27: 1 | Q27: =IFERROR(O27/P27,"") -> 0.69230769 | R27: Proyecto OE-16 y RI-5-11
A28: RI-9-32 | B28: 7027 | C28: 15 | D28: INFRAESTRUCTURA FÍSICA Y TECNOLÓGICA | E28: RI-9 | F28: OE-11 | G28: Gestionar la infraestructura física para proporcionar a la comunidad académica,ambientes educativos adecuados y suficientes. | H28: RI-9-32 | I28: Desarrollar y dotar la planta física para ampliar la capacidad de espacios físicos al servicio de la comunidad académica | J28: Gestión de Bienes y Servicios | K28: Ampliar la capacidad fìsica de la Institución en un 50% para el año 2021. | L28: Capacidad física en m2 periodo P / Capacidad física en m2 periodo P-1 | O28: No aplica para el periodo | P28: 0 | Q28: =IFERROR(O28/P28,"") | R28: Proyecto OE-16 y RI-5-11
A29: RI-9-33 | B29: 7028 | C29: 16 | D29: INFRAESTRUCTURA FÍSICA Y TECNOLÓGICA | E29: RI-9 | F29: OE-12 | G29: Gestionar la infraestructura tecnológica para garantizar una conectividad eficiente y segura que soporte los procesos académicos, administrativos y de apoyo. | H29: RI-9-33 | I29: Mejorar la cobertura de conectividad para el fortalecimiento de los procesos académicos y administrativos. | J29: Gestión de la Tecnología | K29: Ampliar progresivamente la cobertura de cubrimiento de la Sede Principal con conexión inalámbrica. | L29: Cubrimiento de red con conexión inalambrica. Sede Principal de la Institución. | M29: 94 | N29: N/A | O29: =IFERROR(IF(N29="N/A",(M29/100),(M29/N29)),"") -> 0.94 | P29: 0.85 | Q29: =IFERROR(O29/P29,"") -> 1.1058824 | R29: Proyecto OE-16 y RI-5-11
A30: RI-9-34 | B30: 7029 | C30: 16 | D30: INFRAESTRUCTURA FÍSICA Y TECNOLÓGICA | E30: RI-9 | F30: OE-12 | G30: Gestionar la infraestructura tecnológica para garantizar una conectividad eficiente y segura que soporte los procesos académicos, administrativos y de apoyo. | H30: RI-9-34 | I30: Mejorar las prestaciones técnicas y de cobertura a nivel de software, hardware y conectividad necesarios para el fortalecimiento de los procesos académicos y administrativos. | J30: Gestión de la Tecnología | K30: Incrementar el porcentaje de procesos de primer nivel gestionados con soporte tecnológico específico, hasta llegar a un 80% en 2021. (Base 14 procesos 2017) | L30: Número de procesos de primer nivel con soporte tecnológico específico/ Total de procesos de la institución | M30: 4 | N30: 14 | O30: =IFERROR(IF(N30="N/A",M30,(M30/N30)),"") -> 0.28571429 | P30: 0.55 | Q30: =IFERROR(O30/P30,"") -> 0.51948052
A31: RI-9-35 | B31: 7030 | C31: 16 | D31: INFRAESTRUCTURA FÍSICA Y TECNOLÓGICA | E31: RI-9 | F31: OE-12 | G31: Gestionar la infraestructura tecnológica para garantizar una conectividad eficiente y segura que soporte los procesos académicos, administrativos y de apoyo. | H31: RI-9-35 | I31: Proveer la infraestructura tecnológica en cuanto a software y hardware necesaria para que la Institución, a través de los programas académicos y educación continuada, pueda ofrecer educación bajo la metodología virtual. | J31: Gestión de la Tecnología | K31: Incrementar en un 5% el número de espacios académicos virtualizados o con apoyo virtual en los programas académicos y de educación continua. (Base 2017) | L31: Número de espacios académicos con apoyo virtual en los programas/ Número total de espacios académicos | M31: 265 | N31: 678 | O31: =IFERROR(IF(N31="N/A",M31,(M31/N31)),"") -> 0.39085546 | P31: 0.05 | Q31: =IFERROR(O31/P31,"") -> 7.8171091
A32: RI-4-22 | B32: 7031 | C32: 17 | D32: BIENESTAR INSTITUCIONAL | E32: RI-4 | F32: OE-3 | G32: Promover el desarrollo integral de las personas que conforman la comunidad académica, la permanencia estudiantil y la práctica de actividades deportivas, culturales y recreativas que estimulen la convivencia pacífica y la justicia social. | H32: RI-4-22 | I32: Articular y consolidar el Programa de Permanencia de Estudiantes con sus componentes de acompañamiento, desarrollo humano e inclusión, acorde con los lineamientos de ley y con el PEI. | J32: Gestión del Bienestar Institucional | K32: Reducir en un (1) punto porcencual la tasa de deserción por semestre a 2021 (Año Base, 2016) | L32: Tasa de deserción 2016-II - Tasa de deserción actual | O32: No aplica para el periodo | P32: 0 | Q32: =IFERROR(O32/P32,"")
A33: RI-4-23 | B33: 7032 | C33: 17 | D33: BIENESTAR INSTITUCIONAL | E33: RI-4 | F33: OE-3 | G33: Promover el desarrollo integral de las personas que conforman la comunidad académica, la permanencia estudiantil y la práctica de actividades deportivas, culturales y recreativas que estimulen la convivencia pacífica y la justicia social. | H33: RI-4-23 | I33: Consolidar el Centro de Estimulación Infantil como estrategia para la permanencia de estudiantes están en riesgo de deserción por su condición de padres o madres. | J33: Gestión del Bienestar Institucional | K33: Continuación de estudios del 100% de estudiantes beneficiarios del Centro de Estimulación Infantil. | L33: Número de beneficiarios del centro de estimulación infantil que continuaron sus estudios en el periodo/ Número de beneficiarios del centro de estimulación infantil | M33: 48 | N33: 66 | O33: =IFERROR(IF(N33="N/A",M33,(M33/N33)),"") -> 0.72727273 | P33: 1 | Q33: =IFERROR(O33/P33,"") -> 0.72727273
A34: RI-4-24 | B34: 7033 | C34: 17 | D34: BIENESTAR INSTITUCIONAL | E34: RI-4 | F34: OE-3 | G34: Promover el desarrollo integral de las personas que conforman la comunidad académica, la permanencia estudiantil y la práctica de actividades deportivas, culturales y recreativas que estimulen la convivencia pacífica y la justicia social. | H34: RI-4-24 | I34: Articular en el Sistema de Bienestar Institucional estrategias para promover el desarrollo humano con la práctica de actividades deportivas, culturales y recreativas, y la convivencia pacífica de la comunidad académica. | J34: Gestión del Bienestar Institucional | K34: Incrementar anualmente en un 5% la participación de la comunidad académica en actividades de bienestar, hasta lograr en 2021 una cobertura del 70% (Año Base 2017) | L34: Número de participantes en actividades de bienestar P / Número de participantes en actividades de bienestar P-1 | M34: 20437 | N34: 10796 | O34: =IFERROR(IF(N34="N/A",M34,((M34/N34)-1)),"") -> 0.89301593 | P34: 0.05 | Q34: =IFERROR(O34/P34,"") -> 17.860319
A35: RI-8-31 | B35: 7034 | C35: 18 | D35: GESTIÓN ORGANIZACIONAL Y ADMINISTRATIVA | E35: RI-8 | F35: OE-7 | G35: Fortalecer el clima organizacional para favorecer el desarrollo del talento humano, su permanencia y fidelidad hacia la institución eliminando factores de riesgo laboral y psicosocial. | H35: RI-8-31 | I35: Articular y gestionar un programa integral y sistemático de identificación, control e intervención de los factores de riesgo psicosocial con el fin de generar comportamientos de vida, trabajo y convivencia laboral saludable. | J35: Gestión Humana | K35: 100% de empleados reportados por riesgo social con acompañamiento institucional. | L35: Número de Empleados Reportados con Riesgo social con acompañamiento/ Número de Empleados Reportados con Riesgo social | M35: 9 | N35: 0 | O35: =IFERROR(IF(N35="N/A",M35,(M35/N35)),"") | P35: 1 | Q35: =IFERROR(O35/P35,"")
A36: RI-10-25 | B36: 7035 | C36: 19 | D36: GESTIÓN ORGANIZACIONAL Y ADMINISTRATIVA | E36: RI-10 | F36: OE-8 | G36: Implementar un sistema de gestión organizacional con enfoque de procesos que permita la integración de las estructuras académico-administrativas hacia el mejoramiento continuo, soportado en un equipo humano competente y que permita la transición exitosa hacia el reconocimiento como universidad. | H36: RI-10-25 | I36: Implementar un sistema de gestión de la calidad con alcance al rediseño de la estructura orgánica y de procesos, que conduzca a la certificación de procesos bajo normas técnicas colombianas. | J36: Gestión del Direccionamiento Estratégico | K36: Procesos misionales con Certificación ISO 9001:2015. | L36: Número de Procesos misionales con Certificación ISO 9001:2015. | N36: N/A | O36: No aplica para el periodo | P36: 0 | Q36: =IFERROR(O36/P36,"")
A37: RI-10-26 | B37: 7036 | C37: 19 | D37: GESTIÓN ORGANIZACIONAL Y ADMINISTRATIVA | E37: RI-10 | F37: OE-8 | G37: Implementar un sistema de gestión organizacional con enfoque de procesos que permita la integración de las estructuras académico-administrativas hacia el mejoramiento continuo, soportado en un equipo humano competente y que permita la transición exitosa hacia el reconocimiento como universidad. | H37: RI-10-26 | I37: Implementar la Unidad de Correspondencia como extensión operativa del Archivo Central, bajo la dirección de la Secretaría General, soportado tecnológicamente y orientado al cumplimiento de requisitos técnicos (NTC ISO 9001:2015). | J37: Gestión Documental | K37: Incremento sostenido a razón de un 10% anual en la gestión controlada de trámites por ventanilla única. | L37: Porcentaje de trámites atendidos en ventanilla única periodo P - Porcentaje de tr{amites atendidos en ventanilla única periodo P-1 | M37: Està en proceso | O37: =IFERROR(IF(N37="N/A",M37,(M37-N37)),"") | P37: 0.1 | Q37: =IFERROR(O37/P37,"")
A38: N/A

Sheet ADQUISICIÓN DE ACTIVOS
B2: UNIVERSIDAD CESMAG
B3: VICERRECTORIA FINANCIERA Y DESARROLLO INSITUCIONAL
B4: FORMATO DE PROYECTOS ACTIVIADES PLAN DE MEJORAMIENTO
B6: PROGRAMA O DEPENDENCIA: | E6: Imputar a:
B7: =+PERSONAL!B7 -> 0 | E7: AÑO | F7: =+PERSONAL!F7 -> AÑO:
B8: NOMBRE: | C8: =+PERSONAL!C8 -> PLAN DE MEJORAMIENTO
B12: ACTIVOS
B13: Hace referencia a los elementos de Propiedad, planta y equipo que se requiere adquirir para el desarrollo de la actividad u objetivo propuesto en el Plan de Mejoramiento; entre ellos están: Material Bibliográfico, equipos de cómputo, equipos de laboratorio, bases de datos, entre otros
B18: ADQUISICIÓN DE ACTIVOS
B20: No. | C20: CLASE DE ELEMENTO | D20: Descripción del Rubro | E20: Cantidad | F20: VR. UN. | G20: VR TOTAL | H20: CÓDIGO OBJETIVO
B21: 1 | C21: EQUIPO PARA LABORATORIO | D21: Adquisición Material Bibliográfico | E21: 100 | F21: 150000 | G21: =(E21*F21)*1.51852 -> 22777800
B22: =+B21+1 -> 2 | G22: =(E22*F22)*1.51852 -> 0
B23: =+B22+1 -> 3 | G23: =(E23*F23)*1.51852 -> 0
B24: =+B23+1 -> 4 | G24: =(E24*F24)*1.51852 -> 0
B25: =+B24+1 -> 5 | G25: =(E25*F25)*1.51852 -> 0
B26: =+B25+1 -> 6 | G26: =(E26*F26)*1.51852 -> 0
B27: =+B26+1 -> 7 | G27: =(E27*F27)*1.51852 -> 0
B28: =+B27+1 -> 8 | G28: =(E28*F28)*1.51852 -> 0
B29: =+B28+1 -> 9 | G29: =(E29*F29)*1.51852 -> 0
B30: =+B29+1 -> 10 | G30: =(E30*F30)*1.51852 -> 0
B31: =+B30+1 -> 11 | G31: =(E31*F31)*1.51852 -> 0
B32: =+B31+1 -> 12 | G32: =(E32*F32)*1.51852 -> 0
B33: =+B32+1 -> 13 | G33: =(E33*F33)*1.51852 -> 0
... B44: =+B43+1 -> 24 | G44: =(E44*F44)*1.51852 -> 0
C45: SUBTOTAL | G45: =SUM(G21:G44) -> 22777800

Sheet PUBLICIDAD
B2: UNIVERSIDAD CESMAG
B3: VICERRECTORIA FINANCIERA Y DESARROLLO INSITUCIONAL
B4: FORMATO DE PROYECTOS ACTIVIADES PLAN DE MEJORAMIENTO
B6: PROGRAMA O DEPENDENCIA: | E6: Imputar a:
B7: =+'ADQUISICIÓN DE ACTIVOS'!B7:D7 -> 0 | E7: AÑO | F7: =+'ADQUISICIÓN DE ACTIVOS'!F7 -> AÑO:
B8: NOMBRE: | C8: =+'ADQUISICIÓN DE ACTIVOS'!C8:D8 -> PLAN DE MEJORAMIENTO
B10: Publicidad necesaria para el desarrollo delas actividades
B11: Corresponde a los costos en que incurre la Institución por la promoción y divulgación de eventos académicos, deportivos y culturales de carácter Institucional, por medios masivos de comunicación como prensa, revistas, radio y televisión. Se incluye el costo por pautas publicitarias, impresión de plegables, afiches, pasacalles, flayers, pendones, y folletos, entre otros.
B15: Publicidad
B16: No. | C16: CONCEPTO | D16: Descripción del Rubro | E16: Cantidad | F16: VR. UN. | G16: VR TOTAL | H16: CÓDIGO OBJETIVO
B17: 1 | F17: =IFERROR(VLOOKUP(C17,'2025'!$A$233:$B$235,2,0),0) -> 0 | G17: =(E17*F17) -> 0
B18: =+B17+1 -> 2 | F18: =IFERROR(VLOOKUP(C18,'2025'!$A$233:$B$235,2,0),0) -> 0 | G18: =(E18*F18) -> 0
B19: =+B18+1 -> 3 | F19: =IFERROR(VLOOKUP(C19,'2025'!$A$233:$B$235,2,0),0) -> 0 | G19: =(E19*F19) -> 0
B20: =+B19+1 -> 4 | F20: =IFERROR(VLOOKUP(C20,'2025'!$A$233:$B$235,2,0),0) -> 0 | G20: =(E20*F20) -> 0
B21: =+B20+1 -> 5 | F21: =IFERROR(VLOOKUP(C21,'2025'!$A$233:$B$235,2,0),0) -> 0 | G21: =(E21*F21) -> 0
B22: =+B21+1 -> 6 | F22: =IFERROR(VLOOKUP(C22,'2025'!$A$233:$B$235,2,0),0) -> 0 | G22: =(E22*F22) -> 0
B23: =+B22+1 -> 7 | F23: =IFERROR(VLOOKUP(C23,'2025'!$A$233:$B$235,2,0),0) -> 0 | G23: =(E23*F23) -> 0
B24: =+B23+1 -> 8 | F24: =IFERROR(VLOOKUP(C24,'2025'!$A$233:$B$235,2,0),0) -> 0 | G24: =(E24*F24) -> 0
B25: =+B24+1 -> 9 | F25: =IFERROR(VLOOKUP(C25,'2025'!$A$233:$B$235,2,0),0) -> 0 | G25: =(E25*F25) -> 0
B26: =+B25+1 -> 10 | F26: =IFERROR(VLOOKUP(C26,'2025'!$A$233:$B$235,2,0),0) -> 0 | G26: =(E26*F26) -> 0
B27: =+B26+1 -> 11 | F27: =IFERROR(VLOOKUP(C27,'2025'!$A$233:$B$235,2,0),0) -> 0 | G27: =(E27*F27) -> 0
B28: =+B27+1 -> 12 | F28: =IFERROR(VLOOKUP(C28,'2025'!$A$233:$B$235,2,0),0) -> 0 | G28: =(E28*F28) -> 0
B29: =+B28+1 -> 13 | F29: =IFERROR(VLOOKUP(C29,'2025'!$A$233:$B$235,2,0),0) -> 0 | G29: =(E29*F29) -> 0
... B52: =+B51+1 -> 36 | F52: =IFERROR(VLOOKUP(C52,'2025'!$A$233:$B$235,2,0),0) -> 0 | G52: =(E52*F52) -> 0
C53: SUBTOTAL | G53: =SUM(G17:G52) -> 0

Sheet ÚTILES Y PAPELERÍA
B2: UNIVERSIDAD CESMAG
B3: VICERRECTORIA FINANCIERA Y DESARROLLO INSITUCIONAL
B4: FORMATO DE PROYECTOS ACTIVIADES PLAN DE MEJORAMIENTO
B6: PROGRAMA O DEPENDENCIA: | E6: Imputar a:
B7: =+PUBLICIDAD!B7 -> 0 | E7: AÑO | F7: =+PUBLICIDAD!F7 -> AÑO:
B8: NOMBRE: | C8: =+PUBLICIDAD!C8 -> PLAN DE MEJORAMIENTO
B12: Útiles y Papelería
B13: Son los gastos ocasionados por concepto de útiles y papelería, se registran conceptos como: lapiceros, lápices, cosedoras, perforadoras, sacaganchos, cds, cinta, pegastic, tijeras, clips, tinta para sellos, cintas para impresora, recargue de tóneres, papel contac, fólderes, sobres, resmas de papel carta y oficio, etc. Esta cuenta tiene que ver también con el registro de fotocopias
B17: Útiles y Papelería
B18: No. | C18: CONCEPTO | D18: Descripción del Rubro | E18: Cantidad | F18: VR. UN. | G18: VR TOTAL | H18: CÓDIGO OBJETIVO
B19: 1 | C19: Papelería | D19: Para la elaboración del Documento | E19: 1 | F19: 250000 | G19: =(E19*F19) -> 250000
B20: =+B19+1 -> 2 | G20: =(E20*F20) -> 0
B21: =+B20+1 -> 3 | G21: =(E21*F21) -> 0
B22: =+B21+1 -> 4 | G22: =(E22*F22) -> 0
B23: =+B22+1 -> 5 | G23: =(E23*F23) -> 0
B24: =+B23+1 -> 6 | G24: =(E24*F24) -> 0
B25: =+B24+1 -> 7 | G25: =(E25*F25) -> 0
B26: =+B25+1 -> 8 | G26: =(E26*F26) -> 0
B27: =+B26+1 -> 9 | G27: =(E27*F27) -> 0
B28: =+B27+1 -> 10 | G28: =(E28*F28) -> 0
B29: =+B28+1 -> 11 | G29: =(E29*F29) -> 0
B30: =+B29+1 -> 12 | G30: =(E30*F30) -> 0
B31: =+B30+1 -> 13 | G31: =(E31*F31) -> 0
... B47: =+B46+1 -> 29 | G47: =(E47*F47) -> 0
C48: SUBTOTAL | G48: =SUM(G19:G21) -> 250000

Sheet ESPACIOS FÍSICOS y EQUIP
B2: UNIVERSIDAD CESMAG
B3: VICERRECTORIA FINANCIERA Y DESARROLLO INSITUCIONAL
B4: FORMATO DE PROYECTOS ACTIVIADES PLAN DE MEJORAMIENTO
B6: PROGRAMA O DEPENDENCIA: | E6: Imputar a:
B7: =+'ÚTILES Y PAPELERÍA'!B7:D7 -> 0 | E7: AÑO | G7: =+'ÚTILES Y PAPELERÍA'!F7 -> AÑO:
B8: NOMBRE: | C8: =+'ÚTILES Y PAPELERÍA'!C8:D8 -> PLAN DE MEJORAMIENTO
B11: ALQUILER DE INSTALACIONES Y EQUIPOS
B12: Hace referecia al alquiler de espacios especiales que la Universidad disponde para desarrollar las diferentes actividades. Si bien el uso de estos espacios para proyectos internos de la Universidad no requieren salida de efectivo, el uso en de ellos es un recurso físico que se debe cuantificar. (Actividades de: capacitación, sensibilización, encuestas en salas especiales, conferencias, entre otros eventos)
B16: Auditorio y espacios diferentes a Aulas Edificio San Francisco
B17: No. | C17: CONCEPTO | D17: UNI | E17: Cantidad en Horas | F17: Descuento por horas | G17: VR. UN. | H17: VR TOTAL | I17: CÓDIGO OBJETIVO
B18: 1 | C18: Auditorio Santa Clara (76 personas) jornada de 4 horas | E18: 20 | F18: =IF(AND(E18>=1,E18<=10),0%,IF(AND(E18>=11,E18<=40),10%,IF(AND(E18>=41,E18<=80),20%,IF(AND(E18>=81,E18<=130),40%,IF(AND(E18>=131,E18<=180),50%,IF(AND(E18>=181,E18<=250),60%)))))) -> 0.1 | G18: =IFERROR(VLOOKUP(C18,'2025'!$A$61:$B$86,2,0),0) -> 747500 | H18: =+E18*G18 -> 14950000 | I18: OPM_01
B19: =1+B18 -> 2 | F19: =IF(AND(E19>=1,E19<=10),0%,IF(AND(E19>=11,E19<=40),10%,IF(AND(E19>=41,E19<=80),20%,IF(AND(E19>=81,E19<=130),40%,IF(AND(E19>=131,E19<=180),50%,IF(AND(E19>=181,E19<=250),60%)))))) -> FALSE | G19: =IFERROR(VLOOKUP(C19,'2025'!$A$61:$B$86,2,0),0) -> 0 | H19: =+E19*G19 -> 0
B20: =1+B19 -> 3 | F20: =IF(AND(E20>=1,E20<=10),0%,IF(AND(E20>=11,E20<=40),10%,IF(AND(E20>=41,E20<=80),20%,IF(AND(E20>=81,E20<=130),40%,IF(AND(E20>=131,E20<=180),50%,IF(AND(E20>=181,E20<=250),60%)))))) -> FALSE | G20: =IFERROR(VLOOKUP(C20,'2025'!$A$61:$B$86,2,0),0) -> 0 | H20: =+E20*G20 -> 0
B21: =1+B20 -> 4 | F21: =IF(AND(E21>=1,E21<=10),0%,IF(AND(E21>=11,E21<=40),10%,IF(AND(E21>=41,E21<=80),20%,IF(AND(E21>=81,E21<=130),40%,IF(AND(E21>=131,E21<=180),50%,IF(AND(E21>=181,E21<=250),60%)))))) -> FALSE | G21: =IFERROR(VLOOKUP(C21,'2025'!$A$61:$B$86,2,0),0) -> 0 | H21: =+E21*G21 -> 0
C22: SUBTOTAL | H22: =SUM(H18:H21) -> 14950000
B23: Aulas
B24: No. | C24: CONCEPTO | D24: UNI | E24: Cantidad en Horas | F24: Descuento por horas | G24: VR. UN. | H24: VR TOTAL | I24: CÓDIGO OBJETIVO
B25: 1 | C25: Valor Hora Aulas sin Equipos Sede Central | F25: =IF(AND(E25>=1,E25<=10),0%,IF(AND(E25>=11,E25<=40),10%,IF(AND(E25>=41,E25<=80),20%,IF(AND(E25>=81,E25<=130),40%,IF(AND(E25>=131,E25<=180),50%,IF(AND(E25>=181,E25<=250),60%)))))) -> FALSE | G25: =IF(F25="falso",IFERROR(VLOOKUP(C25,'2025'!$A$90:$B$91,2,0),0),IFERROR(VLOOKUP(C25,'2025'!$A$90:$B$91,2,0),0)*(1-F25)) -> 40000 | H25: =+E25*G25 -> 0
B26: =1+B25 -> 2 | C26: Valor Hora Aulas sin Equipos Sede MUSD | F26: =IF(AND(E26>=1,E26<=10),0%,IF(AND(E26>=11,E26<=40),10%,IF(AND(E26>=41,E26<=80),20%,IF(AND(E26>=81,E26<=130),40%,IF(AND(E26>=131,E26<=180),50%,IF(AND(E26>=181,E26<=250),60%)))))) -> FALSE | G26: =IF(F26="falso",IFERROR(VLOOKUP(C26,'2025'!$A$90:$B$91,2,0),0),IFERROR(VLOOKUP(C26,'2025'!$A$90:$B$91,2,0),0)*(1-F26)) -> 50000 | H26: =+E26*G26 -> 0
B27: =1+B26 -> 3 | C27: Valor Hora Aulas sin Equipos Sede Central | F27: =IF(AND(E27>=1,E27<=10),0%,IF(AND(E27>=11,E27<=40),10%,IF(AND(E27>=41,E27<=80),20%,IF(AND(E27>=81,E27<=130),40%,IF(AND(E27>=131,E27<=180),50%,IF(AND(E27>=181,E27<=250),60%)))))) -> FALSE | G27: =IF(F27="falso",IFERROR(VLOOKUP(C27,'2025'!$A$90:$B$91,2,0),0),IFERROR(VLOOKUP(C27,'2025'!$A$90:$B$91,2,0),0)*(1-F27)) -> 40000 | H27: =+E27*G27 -> 0
C28: SUBTOTAL | H28: =SUM(H25:H27) -> 0
B29: Otros Espacios Institucionales
B30: No. | C30: CONCEPTO | D30: UNI | E30: Cantidad en Horas | F30: Descuento por horas | G30: VR. UN. | H30: VR TOTAL | I30: CÓDIGO OBJETIVO
B31: 1 | C31: Cámara de Gesell Valor hora | F31: =IF(AND(E31>=1,E31<=10),0%,IF(AND(E31>=11,E31<=40),10%,IF(AND(E31>=41,E31<=80),20%,IF(AND(E31>=81,E31<=130),40%,IF(AND(E31>=131,E31<=180),50%,IF(AND(E31>=181,E31<=250),60%)))))) -> FALSE | G31: =IF(F31="falso",IFERROR(VLOOKUP(C31,'2025'!$A$92:$B$97,2,0),0),IFERROR(VLOOKUP(C31,'2025'!$A$92:$B$97,2,0),0)*(1-F31)) -> 96000 | H31: =+E31*G31 -> 0
B32: =+B31+1 -> 2 | C32: Coliseo Con amplificación, video proyector y sillas ( valor hora) | F32: =IF(AND(E32>=1,E32<=10),0%,IF(AND(E32>=11,E32<=40),10%,IF(AND(E32>=41,E32<=80),20%,IF(AND(E32>=81,E32<=130),40%,IF(AND(E32>=131,E32<=180),50%,IF(AND(E32>=181,E32<=250),60%)))))) -> FALSE | G32: =IF(F32="falso",IFERROR(VLOOKUP(C32,'2025'!$A$92:$B$97,2,0),0),IFERROR(VLOOKUP(C32,'2025'!$A$92:$B$97,2,0),0)*(1-F32)) -> 150000 | H32: =+E32*G32 -> 0
B33: =+B32+1 -> 3 | C33: Cámara de Gesell Valor hora | F33: =IF(AND(E33>=1,E33<=10),0%,IF(AND(E33>=11,E33<=40),10%,IF(AND(E33>=41,E33<=80),20%,IF(AND(E33>=81,E33<=130),40%,IF(AND(E33>=131,E33<=180),50%,IF(AND(E33>=181,E33<=250),60%)))))) -> FALSE | G33: =IF(F33="falso",IFERROR(VLOOKUP(C33,'2025'!$A$92:$B$97,2,0),0),IFERROR(VLOOKUP(C33,'2025'!$A$92:$B$97,2,0),0)*(1-F33)) -> 96000 | H33: =+E33*G33 -> 0
B34: =+B33+1 -> 4 | C34: Cámara de Gesell Valor hora | F34: =IF(AND(E34>=1,E34<=10),0%,IF(AND(E34>=11,E34<=40),10%,IF(AND(E34>=41,E34<=80),20%,IF(AND(E34>=81,E34<=130),40%,IF(AND(E34>=131,E34<=180),50%,IF(AND(E34>=181,E34<=250),60%)))))) -> FALSE | G34: =IF(F34="falso",IFERROR(VLOOKUP(C34,'2025'!$A$92:$B$97,2,0),0),IFERROR(VLOOKUP(C34,'2025'!$A$92:$B$97,2,0),0)*(1-F34)) -> 96000 | H34: =E34*G34 -> 0
C35: SUBTOTAL | H35: =SUM(H31:H34) -> 0
B36: Espacios Deportivos MUSD
B37: No. | C37: CONCEPTO | D37: Descripción | E37: CAN | G37: VR. UN. | H37: VR TOTAL
B38: 1 | C38: Cancha de futbol 5 (por partido) | F38: =IF(AND(E38>=1,E38<=10),0%,IF(AND(E38>=11,E38<=40),10%,IF(AND(E38>=41,E38<=80),20%,IF(AND(E38>=81,E38<=130),40%,IF(AND(E38>=131,E38<=180),50%,IF(AND(E38>=18),60%)))))) -> FALSE | G38: =IF(F38="falso",IFERROR(VLOOKUP(C38,'2025'!$A$103:$B$116,2,0),0),IFERROR(VLOOKUP(C38,'2025'!$A$103:$B$116,2,0),0)*(1-F38)) -> 90000 | H38: =+E38*G38 -> 0
B39: =+B38+1 -> 2 | C39: Cancha de futbol 11 (por partido) | F39: =IF(AND(E39>=1,E39<=10),0%,IF(AND(E39>=11,E39<=40),10%,IF(AND(E39>=41,E39<=80),20%,IF(AND(E39>=81,E39<=130),40%,IF(AND(E39>=131,E39<=180),50%,IF(AND(E39>=18),60%)))))) -> FALSE | G39: =IF(F39="falso",IFERROR(VLOOKUP(C39,'2025'!$A$103:$B$116,2,0),0),IFERROR(VLOOKUP(C39,'2025'!$A$103:$B$116,2,0),0)*(1-F39)) -> 380000 | H39: =+E39*G39 -> 0
B40: =+B39+1 -> 3 | F40: =IF(AND(E40>=1,E40<=10),0%,IF(AND(E40>=11,E40<=40),10%,IF(AND(E40>=41,E40<=80),20%,IF(AND(E40>=81,E40<=130),40%,IF(AND(E40>=131,E40<=180),50%,IF(AND(E40>=18),60%)))))) -> FALSE | G40: =IF(F40="falso",IFERROR(VLOOKUP(C40,'2025'!$A$103:$B$116,2,0),0),IFERROR(VLOOKUP(C40,'2025'!$A$103:$B$116,2,0),0)*(1-F40)) -> 0 | H40: =+E40*G40 -> 0
B41: =+B40+1 -> 4 | F41: =IF(AND(E41>=1,E41<=10),0%,IF(AND(E41>=11,E41<=40),10%,IF(AND(E41>=41,E41<=80),20%,IF(AND(E41>=81,E41<=130),40%,IF(AND(E41>=131,E41<=180),50%,IF(AND(E41>=18),60%)))))) -> FALSE | G41: =IF(F41="falso",IFERROR(VLOOKUP(C41,'2025'!$A$103:$B$116,2,0),0),IFERROR(VLOOKUP(C41,'2025'!$A$103:$B$116,2,0),0)*(1-F41)) -> 0 | H41: =E41*G41 -> 0
C42: SUBTOTAL | H42: =SUM(H38:H41) -> 0
B43: Otros conceptos y Equipos
B44: No. | C44: CONCEPTO | D44: Descripción | E44: CAN | G44: VR. UN. | H44: VR TOTAL
B45: 1 | C45: SALA ZOOM (Se coloca cantidad por usuarios) | G45: 18000 | H45: =+E45*G45 -> 0
B46: =+B45+1 -> 2 | C46: PLATAFORMA TAU (Se coloca cantidad por usuarios) | G46: 22000 | H46: =+E46*G46 -> 0
B47: =+B46+1 -> 3 | C47: Jornada de 4 horas mañana, tarde o noche por equipo | G47: 12000 | H47: =+E47*G47 -> 0
B48: =+B47+1 -> 4 | C48: Jornada de 4 horas mañana, tarde o noche Video Beam | G48: 55000 | H48: =+E48*G48 -> 0
B49: =+B48+1 -> 5 | H49: =+E49*G49 -> 0
C50: SUBTOTAL | H50: =SUM(H45:H49) -> 0
C51: SUBTOTAL ALQUILER DE INSTALACIONES Y EQUIPOS | H51: =+H22+H35+H28+H42+H50 -> 14950000
B53: Otros
B54: No. | C54: CONCEPTO | D54: UNI | E54: CAN | G54: VR. UN. | H54: VR TOTAL | I54: CÓDIGO OBJETIVO
B55: 1 | H55: =+E55*G55 -> 0
B56: =+B55+1 -> 2 | H56: =+E56*G56 -> 0
B57: =+B56+1 -> 3 | H57: =+E57*G57 -> 0
B58: =+B57+1 -> 4 | H58: =+E58*G58 -> 0
B59: =+B58+1 -> 5 | H59: =+E59*G59 -> 0
C60: SUBTOTAL | H60: =SUM(H55:H59) -> 0

Sheet DIVERSOS
B2: UNIVERSIDAD CESMAG
B3: VICERRECTORIA FINANCIERA Y DESARROLLO INSITUCIONAL
B4: FORMATO DE PROYECTOS ACTIVIADES PLAN DE MEJORAMIENTO
B6: PROGRAMA O DEPENDENCIA: | E6: Imputar a:
B7: =+'ESPACIOS FÍSICOS y EQUIP'!B7:D7 -> 0 | F7: =+'ESPACIOS FÍSICOS y EQUIP'!G7 -> AÑO:
B8: NOMBRE: | C8: =+'ESPACIOS FÍSICOS y EQUIP'!C8:D8 -> PLAN DE MEJORAMIENTO
B10: DIVERSOS
B11: Son todos aquellos gastos ocasionados por conceptos diferentes a los especificados anteriormente como: suscripciones, elementos de aseo y cafetería, combustibles, taxis, estampillas, casino y restaurante-refrigerios, ropería y lencería, entre otros
B13: COSTOS DIVERSOS
B14: No. | C14: CONCEPTO | D14: Descripción del Rubro | E14: Cantidad | F14: VR. UN. | G14: VR TOTAL | H14: CÓDIGO OBJETIVO
B15: 1 | F15: 0 | G15: =(E15*F15) -> 0
B16: =+B15+1 -> 2 | F16: =IFERROR(VLOOKUP(C16,'2025'!$A$148:$B$161,2,0),0) -> 0 | G16: =(E16*F16) -> 0
B17: =+B16+1 -> 3 | F17: =IFERROR(VLOOKUP(C17,'2025'!$A$148:$B$161,2,0),0) -> 0 | G17: =(E17*F17) -> 0
B18: =+B17+1 -> 4 | F18: =IFERROR(VLOOKUP(C18,'2025'!$A$148:$B$161,2,0),0) -> 0 | G18: =(E18*F18) -> 0
B19: =+B18+1 -> 5 | F19: =IFERROR(VLOOKUP(C19,'2025'!$A$148:$B$161,2,0),0) -> 0 | G19: =(E19*F19) -> 0
B20: =+B19+1 -> 6 | F20: =IFERROR(VLOOKUP(C20,'2025'!$A$148:$B$161,2,0),0) -> 0 | G20: =(E20*F20) -> 0
B21: =+B20+1 -> 7 | F21: =IFERROR(VLOOKUP(C21,'2025'!$A$148:$B$161,2,0),0) -> 0 | G21: =(E21*F21) -> 0
B22: =+B21+1 -> 8 | F22: =IFERROR(VLOOKUP(C22,'2025'!$A$148:$B$161,2,0),0) -> 0 | G22: =(E22*F22) -> 0
B23: =+B22+1 -> 9 | F23: =IFERROR(VLOOKUP(C23,'2025'!$A$148:$B$161,2,0),0) -> 0 | G23: =(E23*F23) -> 0
B24: =+B23+1 -> 10 | F24: =IFERROR(VLOOKUP(C24,'2025'!$A$148:$B$161,2,0),0) -> 0 | G24: =(E24*F24) -> 0
B25: =+B24+1 -> 11 | F25: =IFERROR(VLOOKUP(C25,'2025'!$A$148:$B$161,2,0),0) -> 0 | G25: =(E25*F25) -> 0
B26: =+B25+1 -> 12 | F26: =IFERROR(VLOOKUP(C26,'2025'!$A$148:$B$161,2,0),0) -> 0 | G26: =(E26*F26) -> 0
B27: =+B26+1 -> 13 | F27: =IFERROR(VLOOKUP(C27,'2025'!$A$148:$B$161,2,0),0) -> 0 | G27: =(E27*F27) -> 0
... B32: =+B31+1 -> 18 | F32: =IFERROR(VLOOKUP(C32,'2025'!$A$148:$B$161,2,0),0) -> 0 | G32: =(E32*F32) -> 0
C33: SUBTOTAL | G33: =SUM(G15:G32) -> 0

Sheet Presupuesto x Objetivo
B1: UNIVERSIDAD CESMAG
B2: PRESUPUESTO POR OBJETIVO ACTIVIDADES PLAN DE MEJORAMIENTO
B3: VICERRECTORIA FINANCIERA Y DESARROLLO INSTITUCIONAL
B5: PROGRAMA O DEPENDENCIA: | E5: Imputar a:
B6: =+DIVERSOS!B7 -> 0 | E6: CÓDIGO PDI
E7: =+DIVERSOS!F7 -> AÑO:
B8: OBJETIVO: | D8: =VLOOKUP(H8,PM!$B$11:$H$29,8,0) -> #N/A | E8: CÓDIGO OBJETIVO | H8: OPMPSICOLOGÍA_50
B10: No. | D10: CONCEPTO | E10: Anexo No | G10: VR TOTAL
B11: 1 | C11: 22 | D11: PERSONAL
B12: =+B11+1 -> 2 | C12: 221 | D12: Docentes Tiempo Completo | G12: =SUMIF(PERSONAL!H17:H41,'Presupuesto x Objetivo'!$H$8,PERSONAL!G17:G41) -> 0
B13: =+B12+1 -> 3 | C13: 222 | D13: Docentes Medio Tiempo | G13: =SUMIF(PERSONAL!H46:H58,'Presupuesto x Objetivo'!$H$8,PERSONAL!G46:G58) -> 0
B14: =+B13+1 -> 4 | C14: 223 | D14: Otros costos de Personal | G14: =SUMIF(PERSONAL!H64:H80,'Presupuesto x Objetivo'!$H$8,PERSONAL!G64:G80) -> 0
B15: =+B14+1 -> 5 | C15: 224 | D15: Honorarios | G15: =SUMIF(PERSONAL!H90:H104,'Presupuesto x Objetivo'!$H$8,PERSONAL!G90:G104) -> 0
B16: =+B15+1 -> 6 | D16: SUBTOTAL ITEM 2.2.(sume renglones 21 a 24) | G16: =SUM(G12:H15) -> 0
B17: =+B16+1 -> 7 | D17: TOTAL SERVICIOS PERSONALES 15 + 22 | G17: =+G16 -> 0
B18: =+B17+1 -> 8 | C18: 23 | D18: Adquisición de Activos | G18: =SUMIF('ADQUISICIÓN DE ACTIVOS'!H:H,'Presupuesto x Objetivo'!$H$8,'ADQUISICIÓN DE ACTIVOS'!G:G) -> 0
B19: =+B18+1 -> 9 | C19: 231 | D19: Publicidad | G19: =SUMIF(PUBLICIDAD!H:H,'Presupuesto x Objetivo'!$H$8,PUBLICIDAD!G:G) -> 0
B20: =+B19+1 -> 10 | C20: 232 | D20: Útiles y Papelería | G20: =SUMIF('ÚTILES Y PAPELERÍA'!H:H,'Presupuesto x Objetivo'!$H$8,'ÚTILES Y PAPELERÍA'!G:G) -> 0
B21: =+B20+1 -> 11 | C21: 238 | D21: Diversos | G21: =SUMIF(DIVERSOS!H:H,'Presupuesto x Objetivo'!$H$8,DIVERSOS!G:G) -> 0
B22: =+B21+1 -> 12 | D22: SUBTOTAL Item 2.3 (Sume Renglones 25 a 32) | G22: =SUM(G18:H21) -> 0
B23: =+B22+1 -> 13 | C23: 24 | D23: GASTOS GENERALES QUE NO IMPLICAN DESEMBOLSO DE EFECTIVO | G23: 0
B24: =+B23+1 -> 14 | C24: 241 | D24: Alquiler de instalaciones y equipos | G24: =SUMIF('ESPACIOS FÍSICOS y EQUIP'!I:I,'Presupuesto x Objetivo'!$H$8,'ESPACIOS FÍSICOS y EQUIP'!H:H) -> 0
B25: =+B24+1 -> 15 | D25: SUBTOTAL ITEM 2.4. (SUME RENGLONES 35 + 36) | G25: =+G24 -> 0
B26: =+B25+1 -> 16 | D26: TOTAL SERVICIOS PERSONALES Y GENERALES (23+ 33 + 37 ) | G26: =+G17+G22 -> 0
B27: =+B26+1 -> 17 | D27: IMPREVISTOS Renglones [(38)(5/100)] | G27: =+G26*0.05 -> 0
B28: =+B27+1 -> 18 | D28: TOTAL GASTOS (SUME RENGLONES 38 + 39) | G28: =+G27+G26 -> 0
B29: =+B28+1 -> 19 | D29: INVERSION INSTITUCIONAL | G29: =+G28 -> 0
B30: Firma Responsable del proyecto
E33: Vicerrectoría del Area
B34: Presupuesto financieramente viable? SI ____ NO____
E37: Director de Planeación
E40: Vicerrectoría Financiera y Dllo Instinal
E41: Fecha:

Sheet Presupuesto Pycto
B1: UNIVERSIDAD CESMAG
B2: PRESUPUESTO GENERAL DEL PLAN DE MEJORAMIENTO
B3: VICERRECTORIA FINANCIERA Y DESARROLLO INSTITUCIONAL
B5: PROGRAMA O DEPENDENCIA: | E5: Imputar a:
B6: =+DIVERSOS!B7 -> 0 | E6: CÓDIGO PDI
E7: =+DIVERSOS!F7 -> AÑO:
B9: No. | D9: CONCEPTO | E9: Anexo No | G9: VR TOTAL
B10: 1 | C10: 22 | D10: PERSONAL
B11: =+B10+1 -> 2 | C11: 221 | D11: Docentes Tiempo Completo | G11: =+PERSONAL!G42 -> 4052170.6
B12: =+B11+1 -> 3 | C12: 222 | D12: Docentes Medio Tiempo | G12: =+PERSONAL!G59 -> 1861250
B13: =+B12+1 -> 4 | C13: 223 | D13: Otros costos de Personal | G13: =+PERSONAL!G81 -> 0
B14: =+B13+1 -> 5 | C14: 224 | D14: Honorarios | G14: =+PERSONAL!G105 -> 1920000
B15: =+B14+1 -> 6 | D15: SUBTOTAL ITEM 22 | G15: =SUM(G11:H14) -> 7833420.6
B16: =+B15+1 -> 7 | D16: TOTAL SERVICIOS PERSONALES | G16: =+G15 -> 7833420.6
B17: =+B16+1 -> 8 | C17: 23 | D17: Adquisición de Activos | G17: =+'ADQUISICIÓN DE ACTIVOS'!G45 -> 22777800
B18: =+B17+1 -> 9 | C18: 231 | D18: Publicidad | G18: =+PUBLICIDAD!G53 -> 0
B19: =+B18+1 -> 10 | C19: 232 | D19: Útiles y Papelería | G19: =+'ÚTILES Y PAPELERÍA'!G48 -> 250000
B20: =+B19+1 -> 11 | C20: 238 | D20: Diversos | G20: =+DIVERSOS!G33 -> 0
B21: =+B20+1 -> 12 | D21: SUBTOTAL Item 23 | G21: =SUM(G17:H20) -> 23027800
B22: =+B21+1 -> 13 | C22: 24 | D22: GASTOS GENERALES QUE NO IMPLICAN DESEMBOLSO DE EFECTIVO | G22: 0
B23: =+B22+1 -> 14 | C23: 241 | D23: Alquiler de instalaciones y equipos | G23: =+'ESPACIOS FÍSICOS y EQUIP'!H51+'ESPACIOS FÍSICOS y EQUIP'!H60 -> 14950000
B24: =+B23+1 -> 15 | D24: SUBTOTAL ITEM 24 | G24: =+G23 -> 14950000
B25: =+B24+1 -> 16 | D25: TOTAL SERVICIOS PERSONALES Y GENERALES (22+ 23 ) | G25: =+G16+G21 -> 30861221
B26: =+B25+1 -> 17 | D26: IMPREVISTOS Renglones [(16)(5/100)] | G26: =+G25*0.05 -> 1543061
B27: =+B26+1 -> 18 | D27: TOTAL GASTOS (SUME RENGLONES 15 + 16 + 17) | G27: =+G26+G25+G24 -> 47354282
B28: =+B27+1 -> 19 | D28: INVERSION INSTITUCIONAL | G28: =+G27 -> 47354282
B29: Firma Responsable del proyecto
E32: Vicerrectoría del Area
B33: Presupuesto financieramente viable? SI ____ NO____
E36: Director de Planeación
E39: Vicerrectoría Financiera y Dllo Instinal
E40: Fecha:

Sheet 2025
A1: UNIVERSIDAD CESMAG
A2: DECRETO RECTORAL 001
A3: Para: Todo el Personal | B3: IPC | D3: 0.1602
A4: De: Rectoría | B4: VALOR SMMLV | D4: 1300000
A5: Asunto: Tarifas 2024
A6: Reemplaza: Circular 08 de 2024
A7: Fecha de expedición: Enero 16 de 2024
A11: Tarifas a cobrar por la Universidad Cesmag para el año 2022
A12: Constancias, Duplicados y Otros
A13: Detalle | B13: Personal y/o Estudiantes Entidades Gorettianas | C13: Externos | D13: Observaciones
A14: Constancia de trabajo | B14: 2900 | C14: NA | G14: =IFERROR(VLOOKUP(C14,'2025'!B660,0),0) -> 0
A15: Certificado para contrato por OPS | B15: 8900
A16: Record de trabajo | B16: 15200 | C16: NA
A17: Certificado Record de contratos por OPS | B17: 22500
A18: Duplicado desprendible de pago | B18: 2900 | C18: NA
A19: Duplicado certificado de ingresos y retenciones | B19: 2900 | C19: NA
A20: Duplicado carné | B20: 22200 | C20: NA
A21: Duplicado Certificado Educación informal | B21: 8200 | C21: NA
A22: Duplicado Diplomas | B22: 180800 | C22: NA
A23: Duplicado de Acta de grado | B23: 30200
A24: Constancia de crédito y cartera | B24: 2900 | C24: NA
A25: Duplicado de Recibo de Matricula Pagado (Tesorería -Pagaduría) | B25: 2900 | C25: NA
A26: Programas analíticos | B26: 17300 | C26: NA | D26: Por semestre
A27: Escudos | C27: NA
A28: Carné elaboración para externos | B28: NA | C28: 31000 | D28: Previa aprobación de Vicerrectoría Administrativa-Financiera
A29: Cursos de Inglés A, A2, B1, B2, C1, C2 | B29: 480000 | C29: 480000
A30: Servicios por fotocopiado e impresión de documentos
A31: Detalle | B31: Personal y/o Estudiantes Entidades Gorettianas | C31: Externos | D31: Observaciones
A32: Fotocopia en blanco y negro CRE | B32: 100 | C32: NA
A33: Fotocopia a color una página CRE | B33: 100 | C33: NA
A34: Fotocopia a color por dos lados CRE | B34: 200 | C34: NA
A35: Impresión diplomas a color | B35: 4800 | C35: NA | D35: Impresora laser
A38: Mensualidad grupos Deportivos y Otros
A39: Detalle | B39: Personal y/o Estudiantes Entidades Gorettianas | C39: Externos | D39: Observaciones
A40: Taekwondo | B40: NA | C40: 19100 | D40: Mensuales por persona
A41: Gimnasia | B41: NA | C41: 19100 | D41: Mensuales por persona
A42: Preparación para ascenso a cinturón Taekwondo | B42: NA | C42: 96400 | D42: Semestre
A43: Sesión Laboratorio de Paz por persona | B43: NA | C43: 19700 | D43: sesiòn
A45: Presentaciones grupos Artísticos, no incluye transportes, alojamiento ni manutención.
A46: Detalle | B46: Personal y/o Estudiantes Entidades Gorettianas | C46: Externos | D46: Observaciones
A47: Grupo de Danzas | B47: 409000 | C47: 409000 | D47: Libre de Transporte y Lavado de Vestidos
A48: Grupo de Danzas con grupo Folklórico | B48: 613500 | C48: 613500 | D48: Libre de Transporte y Lavado de Vestidos
A49: Grupo Folklórico | B49: 204500 | C49: 204500
A50: Grupo musical | B50: 204500 | C50: 204500
A51: Presentaciones grupos Artísticos, no incluye transportes, alojamiento ni manutención.
A52: Detalle | B52: Personal y/o Estudiantes Entidades Gorettianas | C52: Externos | D52: Observaciones
A53: Danza por Pareja | B53: 204500 | C53: 204500 | D53: Libre de Transporte y Lavado de Vestidos
A54: Gimnasia | B54: 178700 | C54: 178700
A55: Taekwondo | B55: 178700 | C55: 178700
A56: Teatro | B56: 178700 | C56: 178700
A58: Alquiler Planta Fisica
A59: Auditorio Edificio San Francisco, el auditorio tiene uso exclusivo para actividades de carácter académico. | G59: tener en cuenta para 2020 tarifa de salones de Meditacion
A60: Detalle | B60: Personal y/o Estudiantes Entidades Gorettianas | C60: Externos | D60: Observaciones
A61: Auditorio San Francisco (457 personas) jornada de 4 horas | B61: 1299500 | C61: 1619200
A62: Auditorio San Francisco (457 personas) jornada de 8 horas | B62: 2185000 | C62: 2753100
A63: Auditorio San Francisco (457 personas) 1 hora adicional | B63: 276000 | C63: 340400
A64: Auditorio San Francisco (284 personas) jornada de 4 horas | B64: 943000 | C64: 1619200
A65: Auditorio San Francisco (284 personas) jornada de 8 horas | B65: 1725000 | C65: 2753100
A66: Auditorio San Francisco (284 personas) 1 hora adicional | B66: 207000 | C66: 340400
A67: Auditorio San Francisco (173 personas) jornada de 4 horas | B67: 862500 | C67: 1071800
A68: Auditorio San Francisco (173 personas) jornada de 8 horas | B68: 1495000 | C68: 1821600
A69: Auditorio San Francisco (173 personas) 1 hora adicional | B69: 179400 | C69: 225400
A70: Hall San Francisco (300 personas) jornada de 4 horas | B70: 660000 | C70: 822800
A71: Hall San Francisco (300 personas) jornada de 8 horas | B71: 1122000 | C71: 1399200
A72: Hall San Francisco (300 personas) 1 hora adicional | B72: 143000 | C72: 172700
... A84: Sala de Juntas Campus San Damián (15 personas) 1 hora adicional | B84: 57500 | C84: 57500
A85: Valor Hora para entidades Gorettianas | B85: Aplicar un descuento el 50% del valor de la hora externos por cada uno de los conceptos referenciados
A86: Valor hora para Convenios | B86: Aplicar un descuento el 20% del valor de la hora externos por cada uno de los conceptos referenciados
A88: Aulas y Otros Espacios Físicos
A89: Detalle | B89: Personal y/o Estudiantes Entidades Gorettianas | C89: Externos | D89: Observaciones
A90: Valor Hora Aulas sin Equipos Sede Central | B90: 40000 | C90: 60000
A91: Valor Hora Aulas sin Equipos Sede MUSD | B91: 50000 | C91: 70000
A92: Cámara de Gesell Valor hora | B92: 96000 | C92: 132000
A93: Coliseo Con amplificación, video proyector y sillas ( valor hora) | B93: 150000 | C93: 300000 | D93: Solo para costeo de proyectos
A94: Baloncesto, Microfotball y voleibol, diurno, partido | B94: 17300 | C94: 27300 | D94: Solo para costeo de proyectos
A95: Baloncesto, Microfotball y voleibol, nocturno, partido | B95: 24400 | C95: 32800 | D95: Solo para costeo de proyectos
A96: Tenis de campo (partido), diurno | B96: 13800 | C96: 27300 | D96: Solo para costeo de proyectos
A97: Tenis de campo (partido) nocturno | B97: 19200 | C97: 27300 | D97: Solo para costeo de proyectos
A98: Bienes Muebles
A99: Equipos de cómputo y video beam
A100: Jornada de 4 horas mañana, tarde o noche por equipo | B100: 8400 | C100: 10500
A101: Jornada de 4 horas mañana, tarde o noche Video Beam | B101: 40000 | C101: 50000
A102: Espacios Deportivas Sede MUSD
A103: Cancha de futbol 5 (por partido) | B103: 90000 | C103: 110000
A104: Cancha de futbol 11 (por partido) | B104: 380000 | C104: 430000
A105: Camerinos | B105: 50000 | C105: 50000
A106: Cancha de baloncesto, voleibol, microfutbol con gradería, coliseo cubierto (por partido) | B106: 210000 | C106: 250000
A107: Cancha de baloncesto, voleibol, microfutbol con gradería, canchas externas (por partido) | B107: 80000 | C107: 90000
A108: Voleibol playa | B108: 100000 | C108: 110000
A109: Tenis de mesa por partido | B109: 60000 | C109: 70000
A110: Pista de atletismo (hora para evento) | B110: 90000 | C110: 150000
A111: Zonas de integración (espacio libre para adecuación de diversas actividades lúdicas) | B111: 80000 | C111: 100000
A112: Piscina sesión 1 hora/persona. Docentes UNICESMAG | B112: 25000
A113: Piscina sesión 1 hora/persona. Estudiantes UNICESMAG | B113: 20000
A114: Piscina sesión 1 hora/persona. Egresados UNICESMAG | B114: 25000
A115: Piscina sesión 1 hora/persona. Personal de Entidades Gorettianas | B115: 25000
A116: Piscina sesión 1 hora/persona. Personal Externo | B116: 30000
A117: Stand | B117: 62000 | C117: 85000 | D117: Incluye armado
A119: ALQUILER DE AULAS Y OTROS ESPACIOS FISICOS
A120: PARA ALQUILER DE AULAS Y OTROS ESPACIÓS FISICOS TENER EN CUENTA:
...

Sheet Ejempl fase planificación
B2: FASE DE FASE DE PLANEACIÓN y EJECUCIÓN DESARROLLO DE LA FORMACIÓN CONTINUA
B3: No. | C3: ACTIVIDAD | D3: RESPONSABLE | E3: Agosto | I3: Septiembre | M3: Octubre | Q3: Noviembre | U3: Diciembre
E4: S1 | F4: S2 | G4: S3 | H4: S4 | I4: S1 | J4: S2 | K4: S3 | L4: S4 | M4: S1 | N4: S2 | O4: S3 | P4: S4 | Q4: S1 | R4: S2 | S4: S3 | T4: S4 | U4: S1 | V4: S2 | W4: S3 | X4: S4
B5: 1 | C5: Planificación y elaboración de propuesta | D5: Ivan Jojoa, Oscar Martos | F5: X | G5: X
B6: 2 | C6: Revisión de la propuesta por parte de Dirección de Posgrados | D6: Directora de Posgrados | H6: X | I6: X
B7: 3 | C7: Entrega de la propuesta a Vic. Adtiva para revisión y aprobación | D7: Directora de Posgrados, Consejo Académico y Consejo Directivo. | I7: X
B8: 4 | C8: Aprobación Consejos Académico y Directivo | D8: Consejos Académico y Directivo | J8: X | K8: X
B9: 5 | C9: Promoción e inscripción al Diplomado | D9: Dirección de Posgrados, Programa de Contaduría y Coordinador del Diplomado | K9: X | L9: X | M9: X
B10: 6 | C10: Realización diplomado | D10: Dirección de Posgrados, Programa de psicologia y Coordinador del Diplomado | N10: X | O10: X | P10: X | Q10: X | R10: X | S10: X | T10: X | U10: X
B11: 7 | C11: Logistica y clausura Diplomado | D11: Coordinador del Diplomado | U11: X
B12: FASE DE EVALUACIÓN
B13: 1 | C13: Envío de evaluación del Diplomado a los asistentes que se les haya elaborado el certificado | D13: Coordinador del Diplomado | U13: X
B14: 2 | C14: Entrega de resultado de evaluación al programa | D14: Coordinador del Diplomado | V14: X

Sheet 2019
A1: INSTITUCIÓN UNIVERSITARIA CESMAG
A2: CIRCULAR No. 200.06.01 - 005
A3: Para: Todo el Personal | D3: IPC | E3: 0.0318
A4: De: Rectoría | D4: Otro Incremento | E4: 0.04
A5: Asunto: Tarifas 2019
A6: Reemplaza: Circular 200.06.01-005 de enero 2018
A7: Fecha de expedición: Enero 24 de 2019
A14: Tarifas a cobrar por la Institución Universitaria CESMAG para el año 2019
A15: Clase de Servicio | B15: Personal y/o Estudiantes Entidades Gorettianas 2019 | D15: Externos 2019 | E15: Observaciones
A16: Constancia de trabajo | B16: 2000.42 | D16: NA
A17: Record de trabajo | B17: 10000 | D17: NA
A18: Duplicado desprendible de pago | B18: 1950 | D18: NA
A19: Duplicado certificado de ingresos y retenciones | B19: 1949.604 | D19: NA
A20: Duplicado carné | B20: 15000 | D20: NA
A21: Duplicado Certificado Educación informal | B21: 5400.36 | D21: NA
A22: Constancia de crédito y cartera | B22: 2000.42 | D22: NA
A23: Duplicado de Recibo de Matricula Pagado (Tesorería -Pagaduría) | B23: 2500 | D23: NA
A24: Programas analíticos | B24: 11399.8 | D24: NA | E24: Por semestre
A25: Escudos | B25: 9000 | D25: NA
A26: Edición de video por hora | B26: 29300.12 | D26: 30000 | E26: Con perillero
A27: Formulario para proveedores | B27: NA | D27: 51500
A28: Carné elaboración para externos | B28: NA | D28: 20000 | E28: Previa aprobación de Vicerrectoría Administrativa-Financiera
A29: Servicios por Empaste, fotocopiado, multicopiado e impresión de documentos
A30: Empastado hasta 100 hojas | B30: 5599.72 | D30: NA
A31: Empastado mas de 100 hojas | B31: 11449.98 | D31: NA
A32: Fotocopia en blanco y negro CRE | B32: 100 | D32: NA
A33: Fotocopia a color una página CRE | B33: 100 | D33: NA
A34: Fotocopia a color por dos lados CRE | B34: 200 | D34: NA
A35: Multicopiado 50 a 99 hojas carta y oficio (bond), kimberly y 90 gr. | B35: $62 $72 $155
A36: Multicopiado 100 a 199 hojas carta y oficio (bond), kimberly y 90 gr. | B36: $57 $62 $144
A37: Multicopiado 200 a 499 hojas carta y oficio (bond), kimberly y 90 gr. | B37: $52 $57 $134
A38: Multicopiado 500 o más hojas carta y oficio (bond), kimberly y 90 gr. | B38: $40, $45, $125. Otras especificaciones calcualrse en el momento.
A39: Impresión diplomas a color | B39: 3400 | D39: 3400 | E39: Impresora laser
A42: Videos y Revistas
A43: Revista Tiempos Nuevos No. 22 2015 | B43: 20000 | D43: 20000
A44: Revista Tiempos Nuevos No. 23 2016 | B44: 20000 | D44: 20000
A45: Revista Tiempos Nuevos No. 24 2017 | B45: 20000 | D45: 20000
A46: Revista Tiempos Nuevos No. 25 2018 | B46: 20000 | D46: 20000
A47: Grupos Cuotas de Sostenimiento
A48: Taekwondo | B48: NA | D48: 14000 | E48: Mensuales por persona
A49: Gimnasia | B49: NA | D49: 14000 | E49: Mensuales por persona
A50: Preparación para ascenso a cinturón Taekwondo | B50: NA | D50: 70700 | E50: Semestre
A51: Presentaciones, no incluye transportes, alojamiento ni manutención.
A52: Grupo de Danzas | B52: 300000 | D52: 300000 | E52: Libre de Transporte y Lavado de Vestidos
A53: Grupo de Danzas con grupo Folklórico | B53: 450000 | D53: 450000 | E53: Libre de Transporte y Lavado de Vestidos
A54: Grupo Folklórico | B54: 150000 | D54: 150000
A55: Grupo musical | B55: 150000 | D55: 150000
A56: Danza por Pareja | B56: 150000 | D56: 150000 | E56: Libre de Transporte y Lavado de Vestidos
A57: Gimnasia | B57: 131000 | D57: 131000
A58: Taekwondo | B58: 131000 | D58: 131000
A59: Teatro | B59: 131000 | D59: 131000
A60: Alquiler Vestuario
A61: Vestido completo | B61: 50000 | D61: 50000 | E61: Para presentaciones no institucionales
A62: Accesorios adicionales, por cada uno
A63: Alquiler Planta Fisica
A64: Auditorio Edificio San Francisco, el auditorio tiene uso exclusivo para actividades de carácter académico. | C64: valor por hora
A65: Auditorio completo valor hora | B65: =731400 -> 731400 | C65: =+B65/4 -> 182850 | D65: 921500
A66: Auditorio completo valor hora | B66: =1253800 -> 1253800 | C66: =+B66/8 -> 156725 | D66: 1580000
A67: Auditorio completo valor hora adicional | B67: 156700 | C67: =+B67 -> 156700 | D67: 197500
A68: Auditorio (Espacio 1) valor hora | B68: =438900 -> 438900 | C68: =+B68/4 -> 109725 | D68: 552900
A69: Auditorio (Espacio 1) valor hora | B69: =752300 -> 752300 | C69: =+B69/8 -> 94037.5 | D69: 948000
A70: Auditorio valor hora adicional (Espacio 1) | B70: 94000 | C70: =+B70 -> 94000 | D70: 118500
A71: Auditorio (Espacio 2) valor hora | B71: =292600 -> 292600 | C71: =+B71/4 -> 73150 | D71: 368600
A72: Auditorio (Espacio 2) valor hora | B72: =501500 -> 501500 | C72: =+B72/8 -> 62687.5 | D72: 632000
A73: Auditorio valor hora adicional (Espacio 2) | B73: 62700 | C73: =+B73 -> 62700 | D73: 79000
A74: Hall cafeteria san Francisco valor hora | B74: =636100 -> 636100 | C74: =+B74/4 -> 159025 | D74: 641200
A75: Servicio adicional de parqueadero para 33 carros | B75: 45400 | C75: =+B75 -> 45400 | D75: 45800 | E75: Hora
A76: Servicio adicional de parqueadero para 33 carros Media Jornada | B76: 113400 | C76: =+B76 -> 113400 | D76: 114300 | E76: Media jornada (4 horas)
A77: Servicio adicional de parqueadero para 33 carros Jornada Completa | B77: 151300 | C77: =+B77 -> 151300 | D77: 152500 | E77: jornada completa (8 horas)
A78: Aulas sin equipos audiovisuales Edificio San Francisco | B78: =34000/4 -> 8500 | C78: =+B78 -> 8500 | D78: 37400
A79: Aulas con equipos audiovisuales Edificio San Francisco | B79: =76200/4 -> 19050 | C79: =+B79 -> 19050 | D79: 95000
A80: Otros espacios
A81: Aula de audiovisuales con equipos valor hora mañana, tarde o noche | B81: =58800/4 -> 14700 | C81: =+B81/4 -> 3675 | D81: 73100
A82: Aula sin equipos valor hora mañana, tarde o noche | B82: 6525 | C82: =+B82/4 -> 1631.25 | D82: 28800
A83: Cámara de Gesell valor hora mañana, tarde o noche | B83: =92200/4 -> 23050 | C83: =+B83/4 -> 5762.5 | D83: 111400
A84: Estudio de radio y televisión Una hora sin auxiliar | B84: 23400 | C84: =+B84 -> 23400 | D84: 23400
A85: Estudio Fotográfico valor hora mañana, tarde o noche | B85: =96300/4 -> 24075 | C85: =+B85/4 -> 6018.75 | D85: 115400
A86: Laboratorio de pruebas valor hora mañana, tarde o noche | B86: =62300/4 -> 15575 | C86: =+B86/4 -> 3893.75 | D86: 75900 | E86: No incluye pruebas
A87: Salón de danzas con amplificación valor hora mañana, tarde o noche | B87: 7825 | C87: =+B87/4 -> 1956.25 | D87: 36500
A88: Auditorio Santa Clara con amplificación y sillas valor hora mañana, tarde o noche | B88: =271300/4 -> 67825 | C88: =+B88/4 -> 16956.25 | D88: 315300
A89: Aula de Sistemas con servicio de internet valor hora mañana, tarde o noche por equipo | B89: 4200 | C89: =+B89/4 -> 1050 | D89: 5200
A90: Coliseo Con amplificación, video proyector y sillas ( valor hora) | B90: 71200 | C90: =+B90 -> 71200 | D90: NA | E90: Solo para costeo de proyectos
A91: Sala de Gimnasia Maquinas, spining y colchonetas, valor hora | B91: 4900 | C91: =+B91 -> 4900 | D91: 5300
A92: Sala de Gimnasia Colchonetas valor diario individual | B92: 8600 | C92: =+B92/8 -> 1075 | D92: NA | E92: Solo para costeo de proyectos
A93: Baloncesto, Microfotball y voleibol, diurno, partido | B93: 12700 | C93: =+B93 -> 12700 | D93: 25400
A94: Baloncesto, Microfotball y voleibol, nocturno, partido | B94: 17800 | C94: =+B94 -> 17800 | D94: 31700
A95: Tenis de campo (partido), diurno | B95: 10000 | C95: =+B95 -> 10000 | D95: 14100
A96: Tenis de campo (partido) nocturno | B96: 14100 | C96: =+B96 -> 14100 | D96: 17100
A97: Metro cuadrado de medio Universitario San Damian | B97: 24400 | C97: =+B97 -> 24400 | D97: NA | E97: para costeo de proyectos de investigaciones
A98: Parqueaderos
A99: Parqueadero de carros edificio San Fco (para empleados) | B99: 55000 | C99: =+B99 -> 55000 | D99: NA | E99: Valor por semestre
A100: Parqueadero motocicletas edificio San Fco (para empleados) | B100: 32000 | C100: =+B100 -> 32000 | D100: NA | E100: Valor por semestre
A101: Bienes Muebles
A102: Mesones | B102: 15800 | C102: =+B102 -> 15800 | D102: 15800 | E102: valor diario individual
A103: Mesa de tenis | B103: 12300 | C103: =+B103 -> 12300 | D103: 12300 | E103: hora
A104: Sillas | B104: 3600 | C104: =+B104 -> 3600 | D104: 3600 | E104: Unidad
A105: Stand | B105: 36700 | C105: =+B105 -> 36700 | D105: 55000 | E105: Incluye armado
A106: Equipo de Amplificación
A107: Jornada de 4 horas Diurnas 6:00 a.m. 6:00 p.m. | B107: NA | D107: 93700
A108: Nocturnas 6.00 p.m - 10.00 p.m. | B108: NA | D108: 96400
...
